Workbook
Name VF: #REF!
Name REQUERIMIENTO: 'MOB-PEDG'!$K$4:$K$17
Name HERRAMIENTAS_V2: HERRAMIENTAS!$A$4:$AE$555
Name REQUERIMIENTO: HERRAMIENTAS!$AD$4:$AD$555
Name HERRAMIENTAS_V2: 'MOB-PEDG'!$A$4:$W$17
Name VF: 'MOB-PEDG'!$T$4:$T$17

Sheet EQUIPOS
B2: DESGLOSE DE EQUIPOS | N2: 👽 | S2: 🐈‍⬛
I3: =SUBTOTAL(9,I5:I478) -> 5147 | N3: PRIMERA VALIDACIÓN | S3: SEGUNDA VALIDACIÓN | W3: EXTRAÍDO DE PLAN DE COMPRAS
A4: N° | B4: REVISADO | C4: EN REQ | D4: RUBRO | E4: TIPO DE PRODUCTO | F4: CÓDIGO ENTIDAD | G4: CÓDIGO INTERNO (EETT) | H4: PRODUCTO | I4: CANT TOTAL | J4: CANT PLAN | K4: ¿IGUAL? | L4: TALLER | M4: EETT | N4: DETALLE | O4: MARCA | P4: MODELO | Q4: LINK DE REFERENCIA | R4: CET | S4: VALIDACIÓN FINAL | T4: MARCA | U4: MODELO | V4: FICHA TÉCNICA ACTUALIZADA | W4: TIPO DE VALIDACIÓN | X4: PROCEDENCIA | Y4: COMPRADOR | Z4: DESCRIPCIÓN SIDIGE | AB4: N° REQ | AC4: SKU | AD4: DESCRIPCIÓN | AE4: UNIDAD MEDIDA | AF4: CORTE FILTRO PEDAGOGÍA
A5: 1 | B5: TRUE | C5: TRUE | D5: BIEN | E5: EQUIPOS | F5: COM-106 | G5: COM-106 | H5: BALANZA 3KG | I5: =SUMIFS('Hoja 10'!$O:$O,'Hoja 10'!$F:$F,$G5) -> 4 | J5: =IFERROR(__xludf.DUMMYFUNCTION("VLOOKUP(G5,IMPORTRANGE(""https://docs.google.com/spreadsheets/d/12RxCea4e5ggM7QGn1XE3FbLQa_-QbCNdBi90OdPjRqg/edit?gid=1692403370#gid=1692403370"", ""'Plan de Compras'!D4:2432""), 8,0)"),4.0) -> 4 | K5: =IF( C5=TRUE, IF(I5=J5,"SI","NO"), "-") -> SI | L5: INDUSTRIA ALIMENTARIA | M5: 12 Taller_Industria_Alimentaria_Firmado.pdf | O5: =VLOOKUP($G5,'Hoja 10'!$F$4:$AA478, 19,0) -> OHAUS | P5: =VLOOKUP($G5,'Hoja 10'!$F$4:$AA478, 20,0) -> Valor™ 4000 | Q5: =VLOOKUP($G5,'Hoja 10'!$F$4:$AA478, 21,0) -> https://eu-es.ohaus.com/es-eu/products/balances-scales/bench-scales/valor-4000/v41xwe3t | R5: COM-106 BALANZA 3KG - CET | S5: TRUE | T5: =IFERROR(__xludf.DUMMYFUNCTION(" IF ( VLOOKUP($G5,IMPORTRANGE(""https://docs.google.com/spreadsheets/d/1Gpl6jkTg7sL4VDNimUm3S9Vi1i95esohXCF3wuKOE8c"", ""'CONSOLIDADO'!G5:AB""), 10, 0) <> 0, IFERROR(VLOOKUP($G5,IMPORTRANGE(""https://docs.google.com/spreadsheets/d/1Gpl6jkTg7sL4VDNimUm3S9"&"Vi1i95esohXCF3wuKOE8c"", ""'CONSOLIDADO'!G5:AB""), 17, 0), ""-""), """" )"),"OHAUS") -> OHAUS | U5: =IFERROR(__xludf.DUMMYFUNCTION(" IF ( VLOOKUP($G5,IMPORTRANGE(""https://docs.google.com/spreadsheets/d/1Gpl6jkTg7sL4VDNimUm3S9Vi1i95esohXCF3wuKOE8c"", ""'CONSOLIDADO'!G5:AB""), 10, 0) <> 0, IFERROR(VLOOKUP($G5,IMPORTRANGE(""https://docs.google.com/spreadsheets/d/1Gpl6jkTg7sL4VDNimUm3S9"&"Vi1i95esohXCF3wuKOE8c"", ""'CONSOLIDADO'!G5:AB""), 18, 0), ""-""), """" )"),"Valor™ 4000") -> Valor™ 4000 | V5: =IFERROR(__xludf.DUMMYFUNCTION(" IF ( VLOOKUP($G5,IMPORTRANGE(""https://docs.google.com/spreadsheets/d/1Gpl6jkTg7sL4VDNimUm3S9Vi1i95esohXCF3wuKOE8c"", ""'CONSOLIDADO'!G5:AB""), 10, 0) <> 0, IFERROR(VLOOKUP($G5,IMPORTRANGE(""https://docs.google.com/spreadsheets/d/1Gpl6jkTg7sL4VDNimUm3S9"&"Vi1i95esohXCF3wuKOE8c"", ""'CONSOLIDADO'!G5:AB""), 19, 0), ""-""), """" )"),"https://eu-es.ohaus.com/es-eu/products/balances-scales/bench-scales/valor-4000/v41xwe3t") -> https://eu-es.ohaus.com/es-eu/products/balances-scales/bench-scales/valor-4000/v41xwe3t | W5: =IFERROR(__xludf.DUMMYFUNCTION("IFERROR(VLOOKUP(G5,IMPORTRANGE(""https://docs.google.com/spreadsheets/d/12RxCea4e5ggM7QGn1XE3FbLQa_-QbCNdBi90OdPjRqg"", ""'Plan de Compras'!D4:Q""), 12, 0), ""NO ESTÁ EN REQ"")"),"Técnica") -> Técnica | X5: =IFERROR(__xludf.DUMMYFUNCTION("IFERROR(VLOOKUP(G5,IMPORTRANGE(""https://docs.google.com/spreadsheets/d/12RxCea4e5ggM7QGn1XE3FbLQa_-QbCNdBi90OdPjRqg"", ""'Plan de Compras'!D4:Q""), 13, 0), """")"),"INTERNACIONAL") -> INTERNACIONAL | Y5: =IFERROR(__xludf.DUMMYFUNCTION("IFERROR(VLOOKUP(G5,IMPORTRANGE(""https://docs.google.com/spreadsheets/d/12RxCea4e5ggM7QGn1XE3FbLQa_-QbCNdBi90OdPjRqg"", ""'Plan de Compras'!D4:Q""), 14, 0), """")"),"DIEGO ") -> DIEGO | Z5: =IFERROR(__xludf.DUMMYFUNCTION("IFERROR(VLOOKUP(G5,IMPORTRANGE(""https://docs.google.com/spreadsheets/d/12RxCea4e5ggM7QGn1XE3FbLQa_-QbCNdBi90OdPjRqg"", ""'Plan de Compras'!D4:Q""), 4, 0), """")"),"BALANZA 3KG") -> BALANZA 3KG | AA5: =IF(H5=Z5,"TRUE", "FALSE") -> TRUE | AB5: =IFERROR(__xludf.DUMMYFUNCTION("IFERROR(IF(OR(C5=TRUE,C5=""""),VLOOKUP(G5,IMPORTRANGE(""https://docs.google.com/spreadsheets/d/1z9A1Wq-kKrhRNG5RS2a2fKpY1wIhSVz2ZNmP2mOl588/edit?usp=sharing"",""REQ VF!E4:H""),4,0),""NO APLICA""),""GENERAR REQ"")"),"GENERAR REQ") -> GENERAR REQ | AC5: =IFERROR(__xludf.DUMMYFUNCTION("IFERROR(QUERY(IMPORTRANGE(""https://docs.google.com/spreadsheets/d/1z9A1Wq-kKrhRNG5RS2a2fKpY1wIhSVz2ZNmP2mOl588/edit?usp=sharing"",""REQ VF!E4:Q""),""SELECT Col10, Col11, Col12 WHERE Col1 = '""&G5&""'"",0),""NO APLICA"")"),"NO APLICA") -> NO APLICA
C6: TRUE | D6: ACCESORIO | E6: EQUIPOS | G6: COM-106.1 | H6: FUNDA IMPERMEABLE (1 UND) | I6: =$I$5 -> 4 | J6: =IFERROR(__xludf.DUMMYFUNCTION("VLOOKUP(G6,IMPORTRANGE(""https://docs.google.com/spreadsheets/d/12RxCea4e5ggM7QGn1XE3FbLQa_-QbCNdBi90OdPjRqg/edit?gid=1692403370#gid=1692403370"", ""'Plan de Compras'!D4:2432""), 8,0)"),4.0) -> 4 | K6: =IF( C6=TRUE, IF(I6=J6,"SI","NO"), "-") -> SI | N6: CON PROVEEDOR EXTERNO | P6: 256 x 124 x 288 mm | S6: TRUE | T6: GENÉRICO | U6: FUNDAS IMPERMEABLES 23 CM X 36 CM X 39 CM PARA BALANZA 3KG | W6: =IFERROR(__xludf.DUMMYFUNCTION("IFERROR(VLOOKUP(G6,IMPORTRANGE(""https://docs.google.com/spreadsheets/d/12RxCea4e5ggM7QGn1XE3FbLQa_-QbCNdBi90OdPjRqg"", ""'Plan de Compras'!D4:Q""), 12, 0), ""NO ESTÁ EN REQ"")"),"Técnica") -> Técnica | X6: =IFERROR(__xludf.DUMMYFUNCTION("IFERROR(VLOOKUP(G6,IMPORTRANGE(""https://docs.google.com/spreadsheets/d/12RxCea4e5ggM7QGn1XE3FbLQa_-QbCNdBi90OdPjRqg"", ""'Plan de Compras'!D4:Q""), 13, 0), """")"),"NACIONAL") -> NACIONAL | Y6: =IFERROR(__xludf.DUMMYFUNCTION("IFERROR(VLOOKUP(G6,IMPORTRANGE(""https://docs.google.com/spreadsheets/d/12RxCea4e5ggM7QGn1XE3FbLQa_-QbCNdBi90OdPjRqg"", ""'Plan de Compras'!D4:Q""), 14, 0), """")"),"ANGIE") -> ANGIE | Z6: =IFERROR(__xludf.DUMMYFUNCTION("IFERROR(VLOOKUP(G6,IMPORTRANGE(""https://docs.google.com/spreadsheets/d/12RxCea4e5ggM7QGn1XE3FbLQa_-QbCNdBi90OdPjRqg"", ""'Plan de Compras'!D4:Q""), 4, 0), """")"),"FUNDA IMPERMEABLE (1 UND)") -> FUNDA IMPERMEABLE (1 UND) | AA6: =IF(H6=Z6,"TRUE", "FALSE") -> TRUE | AB6: =IFERROR(__xludf.DUMMYFUNCTION("IFERROR(IF(OR(C6=TRUE,C6=""""),VLOOKUP(G6,IMPORTRANGE(""https://docs.google.com/spreadsheets/d/1z9A1Wq-kKrhRNG5RS2a2fKpY1wIhSVz2ZNmP2mOl588/edit?usp=sharing"",""REQ VF!E4:H""),4,0),""NO APLICA""),""GENERAR REQ"")"),"GENERAR REQ") -> GENERAR REQ | AC6: =IFERROR(__xludf.DUMMYFUNCTION("IFERROR(QUERY(IMPORTRANGE(""https://docs.google.com/spreadsheets/d/1z9A1Wq-kKrhRNG5RS2a2fKpY1wIhSVz2ZNmP2mOl588/edit?usp=sharing"",""REQ VF!E4:Q""),""SELECT Col10, Col11, Col12 WHERE Col1 = '""&G6&""'"",0),""NO APLICA"")"),"NO APLICA") -> NO APLICA
A7: 2 | B7: TRUE | C7: TRUE | D7: BIEN | E7: EQUIPOS | F7: COM-107 | G7: COM-107 | H7: BALANZA 40KG | I7: =SUMIFS('Hoja 10'!$O:$O,'Hoja 10'!$F:$F,$G7) -> 8 | J7: =IFERROR(__xludf.DUMMYFUNCTION("VLOOKUP(G7,IMPORTRANGE(""https://docs.google.com/spreadsheets/d/12RxCea4e5ggM7QGn1XE3FbLQa_-QbCNdBi90OdPjRqg/edit?gid=1692403370#gid=1692403370"", ""'Plan de Compras'!D4:2432""), 8,0)"),8.0) -> 8 | K7: =IF( C7=TRUE, IF(I7=J7,"SI","NO"), "-") -> SI | L7: INDUSTRIA ALIMENTARIA | M7: 12 Taller_Industria_Alimentaria_Firmado.pdf | O7: =VLOOKUP($G7,'Hoja 10'!$F$4:$AA478, 19,0) -> OPALUX | P7: =VLOOKUP($G7,'Hoja 10'!$F$4:$AA478, 20,0) -> OPALUX | Q7: =VLOOKUP($G7,'Hoja 10'!$F$4:$AA478, 21,0) -> https://opalux.lifestore.pe/producto/balanza-electronica-digital-de-mesa-40kgs-opalux-lcd-recargable-con-brazo-y-bateria-4v4ah-220v/ | R7: COM-107 BALANZA 40KG - CET | S7: TRUE | T7: =IFERROR(__xludf.DUMMYFUNCTION(" IF ( VLOOKUP($G7,IMPORTRANGE(""https://docs.google.com/spreadsheets/d/1Gpl6jkTg7sL4VDNimUm3S9Vi1i95esohXCF3wuKOE8c"", ""'CONSOLIDADO'!G5:AB""), 10, 0) <> 0, IFERROR(VLOOKUP($G7,IMPORTRANGE(""https://docs.google.com/spreadsheets/d/1Gpl6jkTg7sL4VDNimUm3S9"&"Vi1i95esohXCF3wuKOE8c"", ""'CONSOLIDADO'!G5:AB""), 17, 0), ""-""), """" )"),"Torrey") -> Torrey | U7: =IFERROR(__xludf.DUMMYFUNCTION(" IF ( VLOOKUP($G7,IMPORTRANGE(""https://docs.google.com/spreadsheets/d/1Gpl6jkTg7sL4VDNimUm3S9Vi1i95esohXCF3wuKOE8c"", ""'CONSOLIDADO'!G5:AB""), 10, 0) <> 0, IFERROR(VLOOKUP($G7,IMPORTRANGE(""https://docs.google.com/spreadsheets/d/1Gpl6jkTg7sL4VDNimUm3S9"&"Vi1i95esohXCF3wuKOE8c"", ""'CONSOLIDADO'!G5:AB""), 18, 0), ""-""), """" )"),"PCR – 40T") -> PCR – 40T | V7: =IFERROR(__xludf.DUMMYFUNCTION(" IF ( VLOOKUP($G7,IMPORTRANGE(""https://docs.google.com/spreadsheets/d/1Gpl6jkTg7sL4VDNimUm3S9Vi1i95esohXCF3wuKOE8c"", ""'CONSOLIDADO'!G5:AB""), 10, 0) <> 0, IFERROR(VLOOKUP($G7,IMPORTRANGE(""https://docs.google.com/spreadsheets/d/1Gpl6jkTg7sL4VDNimUm3S9"&"Vi1i95esohXCF3wuKOE8c"", ""'CONSOLIDADO'!G5:AB""), 19, 0), ""-""), """" )"),"https://opalux.lifestore.pe/producto/balanza-electronica-digital-de-mesa-40kgs-opalux-lcd-recargable-con-brazo-y-bateria-4v4ah-220v/") -> https://opalux.lifestore.pe/producto/balanza-electronica-digital-de-mesa-40kgs-opalux-lcd-recargable-con-brazo-y-bateria-4v4ah-220v/ | W7: =IFERROR(__xludf.DUMMYFUNCTION("IFERROR(VLOOKUP(G7,IMPORTRANGE(""https://docs.google.com/spreadsheets/d/12RxCea4e5ggM7QGn1XE3FbLQa_-QbCNdBi90OdPjRqg"", ""'Plan de Compras'!D4:Q""), 12, 0), ""NO ESTÁ EN REQ"")"),"Técnica") -> Técnica | X7: =IFERROR(__xludf.DUMMYFUNCTION("IFERROR(VLOOKUP(G7,IMPORTRANGE(""https://docs.google.com/spreadsheets/d/12RxCea4e5ggM7QGn1XE3FbLQa_-QbCNdBi90OdPjRqg"", ""'Plan de Compras'!D4:Q""), 13, 0), """")"),"NACIONAL") -> NACIONAL | Y7: =IFERROR(__xludf.DUMMYFUNCTION("IFERROR(VLOOKUP(G7,IMPORTRANGE(""https://docs.google.com/spreadsheets/d/12RxCea4e5ggM7QGn1XE3FbLQa_-QbCNdBi90OdPjRqg"", ""'Plan de Compras'!D4:Q""), 14, 0), """")"),"ANGIE") -> ANGIE | Z7: =IFERROR(__xludf.DUMMYFUNCTION("IFERROR(VLOOKUP(G7,IMPORTRANGE(""https://docs.google.com/spreadsheets/d/12RxCea4e5ggM7QGn1XE3FbLQa_-QbCNdBi90OdPjRqg"", ""'Plan de Compras'!D4:Q""), 4, 0), """")"),"BALANZA 40KG") -> BALANZA 40KG | AA7: =IF(H7=Z7,"TRUE", "FALSE") -> TRUE | AB7: =IFERROR(__xludf.DUMMYFUNCTION("IFERROR(IF(OR(C7=TRUE,C7=""""),VLOOKUP(G7,IMPORTRANGE(""https://docs.google.com/spreadsheets/d/1z9A1Wq-kKrhRNG5RS2a2fKpY1wIhSVz2ZNmP2mOl588/edit?usp=sharing"",""REQ VF!E4:H""),4,0),""NO APLICA""),""GENERAR REQ"")"),"GENERAR REQ") -> GENERAR REQ | AC7: =IFERROR(__xludf.DUMMYFUNCTION("IFERROR(QUERY(IMPORTRANGE(""https://docs.google.com/spreadsheets/d/1z9A1Wq-kKrhRNG5RS2a2fKpY1wIhSVz2ZNmP2mOl588/edit?usp=sharing"",""REQ VF!E4:Q""),""SELECT Col10, Col11, Col12 WHERE Col1 = '""&G7&""'"",0),""NO APLICA"")"),"NO APLICA") -> NO APLICA | AF7: C
C8: TRUE | D8: ACCESORIO | E8: EQUIPOS | F8: COM-107 | G8: COM-107.1 | H8: FUNDA IMPERMEABLE (1 UND) | I8: =I7 -> 8 | J8: =IFERROR(__xludf.DUMMYFUNCTION("VLOOKUP(G8,IMPORTRANGE(""https://docs.google.com/spreadsheets/d/12RxCea4e5ggM7QGn1XE3FbLQa_-QbCNdBi90OdPjRqg/edit?gid=1692403370#gid=1692403370"", ""'Plan de Compras'!D4:2432""), 8,0)"),8.0) -> 8 | K8: =IF( C8=TRUE, IF(I8=J8,"SI","NO"), "-") -> SI | N8: CON PROVEEDOR EXTERNO | P8: 342 x 330 x 475 mm | S8: TRUE | T8: GENERICO | U8: FUNDAS IMPERMEABLES 48 CM X 42 CM X 40 CM PARA BALANZA 40KG | W8: =IFERROR(__xludf.DUMMYFUNCTION("IFERROR(VLOOKUP(G8,IMPORTRANGE(""https://docs.google.com/spreadsheets/d/12RxCea4e5ggM7QGn1XE3FbLQa_-QbCNdBi90OdPjRqg"", ""'Plan de Compras'!D4:Q""), 12, 0), ""NO ESTÁ EN REQ"")"),"Simple") -> Simple | X8: =IFERROR(__xludf.DUMMYFUNCTION("IFERROR(VLOOKUP(G8,IMPORTRANGE(""https://docs.google.com/spreadsheets/d/12RxCea4e5ggM7QGn1XE3FbLQa_-QbCNdBi90OdPjRqg"", ""'Plan de Compras'!D4:Q""), 13, 0), """")"),"NACIONAL") -> NACIONAL | Y8: =IFERROR(__xludf.DUMMYFUNCTION("IFERROR(VLOOKUP(G8,IMPORTRANGE(""https://docs.google.com/spreadsheets/d/12RxCea4e5ggM7QGn1XE3FbLQa_-QbCNdBi90OdPjRqg"", ""'Plan de Compras'!D4:Q""), 14, 0), """")"),"ANGIE") -> ANGIE | Z8: =IFERROR(__xludf.DUMMYFUNCTION("IFERROR(VLOOKUP(G8,IMPORTRANGE(""https://docs.google.com/spreadsheets/d/12RxCea4e5ggM7QGn1XE3FbLQa_-QbCNdBi90OdPjRqg"", ""'Plan de Compras'!D4:Q""), 4, 0), """")"),"FUNDA IMPERMEABLE (1 UND)") -> FUNDA IMPERMEABLE (1 UND) | AA8: =IF(H8=Z8,"TRUE", "FALSE") -> TRUE | AB8: =IFERROR(__xludf.DUMMYFUNCTION("IFERROR(IF(OR(C8=TRUE,C8=""""),VLOOKUP(G8,IMPORTRANGE(""https://docs.google.com/spreadsheets/d/1z9A1Wq-kKrhRNG5RS2a2fKpY1wIhSVz2ZNmP2mOl588/edit?usp=sharing"",""REQ VF!E4:H""),4,0),""NO APLICA""),""GENERAR REQ"")"),"GENERAR REQ") -> GENERAR REQ | AC8: =IFERROR(__xludf.DUMMYFUNCTION("IFERROR(QUERY(IMPORTRANGE(""https://docs.google.com/spreadsheets/d/1z9A1Wq-kKrhRNG5RS2a2fKpY1wIhSVz2ZNmP2mOl588/edit?usp=sharing"",""REQ VF!E4:Q""),""SELECT Col10, Col11, Col12 WHERE Col1 = '""&G8&""'"",0),""NO APLICA"")"),"NO APLICA") -> NO APLICA
A9: 3 | B9: TRUE | C9: TRUE | D9: BIEN | E9: EQUIPOS | F9: COM-108 | G9: COM-108 | H9: BALANZA 5KG | I9: =SUMIFS('Hoja 10'!$O:$O,'Hoja 10'!$F:$F,$G9) -> 4 | J9: =IFERROR(__xludf.DUMMYFUNCTION("VLOOKUP(G9,IMPORTRANGE(""https://docs.google.com/spreadsheets/d/12RxCea4e5ggM7QGn1XE3FbLQa_-QbCNdBi90OdPjRqg/edit?gid=1692403370#gid=1692403370"", ""'Plan de Compras'!D4:2432""), 8,0)"),4.0) -> 4 | K9: =IF( C9=TRUE, IF(I9=J9,"SI","NO"), "-") -> SI | L9: INDUSTRIA ALIMENTARIA | M9: 12 Taller_Industria_Alimentaria_Firmado.pdf | O9: =VLOOKUP($G9,'Hoja 10'!$F$4:$AA478, 19,0) -> Precisur | P9: =VLOOKUP($G9,'Hoja 10'!$F$4:$AA478, 20,0) -> BRD | Q9: =VLOOKUP($G9,'Hoja 10'!$F$4:$AA478, 21,0) -> https://lacasadelabalanzaperu.com/producto/balanza-gramera-brd-de-5-kilos/?srsltid=AfmBOoqESFO4ybWNXMKI8ni8CSFROATsEcEQxFdxgt7due_hwv2yVsh2 | R9: COM-108 BALANZA 5KG - CET | S9: TRUE | T9: =IFERROR(__xludf.DUMMYFUNCTION(" IF ( VLOOKUP($G9,IMPORTRANGE(""https://docs.google.com/spreadsheets/d/1Gpl6jkTg7sL4VDNimUm3S9Vi1i95esohXCF3wuKOE8c"", ""'CONSOLIDADO'!G5:AB""), 10, 0) <> 0, IFERROR(VLOOKUP($G9,IMPORTRANGE(""https://docs.google.com/spreadsheets/d/1Gpl6jkTg7sL4VDNimUm3S9"&"Vi1i95esohXCF3wuKOE8c"", ""'CONSOLIDADO'!G5:AB""), 17, 0), ""-""), """" )"),"Precisur") -> Precisur | U9: =IFERROR(__xludf.DUMMYFUNCTION(" IF ( VLOOKUP($G9,IMPORTRANGE(""https://docs.google.com/spreadsheets/d/1Gpl6jkTg7sL4VDNimUm3S9Vi1i95esohXCF3wuKOE8c"", ""'CONSOLIDADO'!G5:AB""), 10, 0) <> 0, IFERROR(VLOOKUP($G9,IMPORTRANGE(""https://docs.google.com/spreadsheets/d/1Gpl6jkTg7sL4VDNimUm3S9"&"Vi1i95esohXCF3wuKOE8c"", ""'CONSOLIDADO'!G5:AB""), 18, 0), ""-""), """" )"),"BRD") -> BRD | V9: =IFERROR(__xludf.DUMMYFUNCTION(" IF ( VLOOKUP($G9,IMPORTRANGE(""https://docs.google.com/spreadsheets/d/1Gpl6jkTg7sL4VDNimUm3S9Vi1i95esohXCF3wuKOE8c"", ""'CONSOLIDADO'!G5:AB""), 10, 0) <> 0, IFERROR(VLOOKUP($G9,IMPORTRANGE(""https://docs.google.com/spreadsheets/d/1Gpl6jkTg7sL4VDNimUm3S9"&"Vi1i95esohXCF3wuKOE8c"", ""'CONSOLIDADO'!G5:AB""), 19, 0), ""-""), """" )"),"https://balanzasprecisur.com/balanzas-grameras/balanza-gramera-precisur-brd-de-5-kilos/?srsltid=AfmBOoonqZsXOjmBofRnpTJMaafb52Afo-ssPdM32gdpQef_duHaKTSH") -> https://balanzasprecisur.com/balanzas-grameras/balanza-gramera-precisur-brd-de-5-kilos/?srsltid=AfmBOoonqZsXOjmBofRnpTJMaafb52Afo-ssPdM32gdpQef_duHaKTSH | W9: =IFERROR(__xludf.DUMMYFUNCTION("IFERROR(VLOOKUP(G9,IMPORTRANGE(""https://docs.google.com/spreadsheets/d/12RxCea4e5ggM7QGn1XE3FbLQa_-QbCNdBi90OdPjRqg"", ""'Plan de Compras'!D4:Q""), 12, 0), ""NO ESTÁ EN REQ"")"),"Técnica") -> Técnica | X9: =IFERROR(__xludf.DUMMYFUNCTION("IFERROR(VLOOKUP(G9,IMPORTRANGE(""https://docs.google.com/spreadsheets/d/12RxCea4e5ggM7QGn1XE3FbLQa_-QbCNdBi90OdPjRqg"", ""'Plan de Compras'!D4:Q""), 13, 0), """")"),"NACIONAL") -> NACIONAL | Y9: =IFERROR(__xludf.DUMMYFUNCTION("IFERROR(VLOOKUP(G9,IMPORTRANGE(""https://docs.google.com/spreadsheets/d/12RxCea4e5ggM7QGn1XE3FbLQa_-QbCNdBi90OdPjRqg"", ""'Plan de Compras'!D4:Q""), 14, 0), """")"),"ANGIE") -> ANGIE | Z9: =IFERROR(__xludf.DUMMYFUNCTION("IFERROR(VLOOKUP(G9,IMPORTRANGE(""https://docs.google.com/spreadsheets/d/12RxCea4e5ggM7QGn1XE3FbLQa_-QbCNdBi90OdPjRqg"", ""'Plan de Compras'!D4:Q""), 4, 0), """")"),"BALANZA 5KG") -> BALANZA 5KG | AA9: =IF(H9=Z9,"TRUE", "FALSE") -> TRUE | AB9: =IFERROR(__xludf.DUMMYFUNCTION("IFERROR(IF(OR(C9=TRUE,C9=""""),VLOOKUP(G9,IMPORTRANGE(""https://docs.google.com/spreadsheets/d/1z9A1Wq-kKrhRNG5RS2a2fKpY1wIhSVz2ZNmP2mOl588/edit?usp=sharing"",""REQ VF!E4:H""),4,0),""NO APLICA""),""GENERAR REQ"")"),"GENERAR REQ") -> GENERAR REQ | AC9: =IFERROR(__xludf.DUMMYFUNCTION("IFERROR(QUERY(IMPORTRANGE(""https://docs.google.com/spreadsheets/d/1z9A1Wq-kKrhRNG5RS2a2fKpY1wIhSVz2ZNmP2mOl588/edit?usp=sharing"",""REQ VF!E4:Q""),""SELECT Col10, Col11, Col12 WHERE Col1 = '""&G9&""'"",0),""NO APLICA"")"),"NO APLICA") -> NO APLICA | AF9: C
C10: TRUE | D10: ACCESORIO | E10: EQUIPOS | F10: COM-108 | G10: COM-108.1 | H10: CARGADOR DE PILAS RECARGABLES (1 UND) | I10: =$I$9 -> 4 | J10: =IFERROR(__xludf.DUMMYFUNCTION("VLOOKUP(G10,IMPORTRANGE(""https://docs.google.com/spreadsheets/d/12RxCea4e5ggM7QGn1XE3FbLQa_-QbCNdBi90OdPjRqg/edit?gid=1692403370#gid=1692403370"", ""'Plan de Compras'!D4:2432""), 8,0)"),4.0) -> 4 | K10: =IF( C10=TRUE, IF(I10=J10,"SI","NO"), "-") -> SI | N10: CARGADOR DE PILAS AA/AAA | Q10: https://www.coolbox.pe/cargador-de-pilas-radioshack-aaaaa-2-pilas-aa-2309221/p | S10: TRUE | T10: Beston | U10: HD-4883 | W10: =IFERROR(__xludf.DUMMYFUNCTION("IFERROR(VLOOKUP(G10,IMPORTRANGE(""https://docs.google.com/spreadsheets/d/12RxCea4e5ggM7QGn1XE3FbLQa_-QbCNdBi90OdPjRqg"", ""'Plan de Compras'!D4:Q""), 12, 0), ""NO ESTÁ EN REQ"")"),"Técnica") -> Técnica | X10: =IFERROR(__xludf.DUMMYFUNCTION("IFERROR(VLOOKUP(G10,IMPORTRANGE(""https://docs.google.com/spreadsheets/d/12RxCea4e5ggM7QGn1XE3FbLQa_-QbCNdBi90OdPjRqg"", ""'Plan de Compras'!D4:Q""), 13, 0), """")"),"NACIONAL") -> NACIONAL | Y10: =IFERROR(__xludf.DUMMYFUNCTION("IFERROR(VLOOKUP(G10,IMPORTRANGE(""https://docs.google.com/spreadsheets/d/12RxCea4e5ggM7QGn1XE3FbLQa_-QbCNdBi90OdPjRqg"", ""'Plan de Compras'!D4:Q""), 14, 0), """")"),"ALFIO") -> ALFIO | Z10: =IFERROR(__xludf.DUMMYFUNCTION("IFERROR(VLOOKUP(G10,IMPORTRANGE(""https://docs.google.com/spreadsheets/d/12RxCea4e5ggM7QGn1XE3FbLQa_-QbCNdBi90OdPjRqg"", ""'Plan de Compras'!D4:Q""), 4, 0), """")"),"CARGADOR DE PILAS RECARGABLES (1 UND)") -> CARGADOR DE PILAS RECARGABLES (1 UND) | AA10: =IF(H10=Z10,"TRUE", "FALSE") -> TRUE | AB10: =IFERROR(__xludf.DUMMYFUNCTION("IFERROR(IF(OR(C10=TRUE,C10=""""),VLOOKUP(G10,IMPORTRANGE(""https://docs.google.com/spreadsheets/d/1z9A1Wq-kKrhRNG5RS2a2fKpY1wIhSVz2ZNmP2mOl588/edit?usp=sharing"",""REQ VF!E4:H""),4,0),""NO APLICA""),""GENERAR REQ"")"),"GENERAR REQ") -> GENERAR REQ | AC10: =IFERROR(__xludf.DUMMYFUNCTION("IFERROR(QUERY(IMPORTRANGE(""https://docs.google.com/spreadsheets/d/1z9A1Wq-kKrhRNG5RS2a2fKpY1wIhSVz2ZNmP2mOl588/edit?usp=sharing"",""REQ VF!E4:Q""),""SELECT Col10, Col11, Col12 WHERE Col1 = '""&G10&""'"",0),""NO APLICA"")"),"NO APLICA") -> NO APLICA
C11: TRUE | D11: ACCESORIO | E11: EQUIPOS | F11: COM-108 | G11: COM-108.2 | H11: PACK DE 2 PILAS RECARGABLES (1 UND) | I11: =$I$9 -> 4 | J11: =IFERROR(__xludf.DUMMYFUNCTION("VLOOKUP(G11,IMPORTRANGE(""https://docs.google.com/spreadsheets/d/12RxCea4e5ggM7QGn1XE3FbLQa_-QbCNdBi90OdPjRqg/edit?gid=1692403370#gid=1692403370"", ""'Plan de Compras'!D4:2432""), 8,0)"),4.0) -> 4 | K11: =IF( C11=TRUE, IF(I11=J11,"SI","NO"), "-") -> SI | N11: PILAS RECARGABLES AAA 800 MAH | Q11: https://www.coolbox.pe/pila-recargable-energizer-aaa-x2-220390/p | S11: TRUE | T11: Camelion | U11: 1001503407 | W11: =IFERROR(__xludf.DUMMYFUNCTION("IFERROR(VLOOKUP(G11,IMPORTRANGE(""https://docs.google.com/spreadsheets/d/12RxCea4e5ggM7QGn1XE3FbLQa_-QbCNdBi90OdPjRqg"", ""'Plan de Compras'!D4:Q""), 12, 0), ""NO ESTÁ EN REQ"")"),"Técnica") -> Técnica | X11: =IFERROR(__xludf.DUMMYFUNCTION("IFERROR(VLOOKUP(G11,IMPORTRANGE(""https://docs.google.com/spreadsheets/d/12RxCea4e5ggM7QGn1XE3FbLQa_-QbCNdBi90OdPjRqg"", ""'Plan de Compras'!D4:Q""), 13, 0), """")"),"NACIONAL") -> NACIONAL | Y11: =IFERROR(__xludf.DUMMYFUNCTION("IFERROR(VLOOKUP(G11,IMPORTRANGE(""https://docs.google.com/spreadsheets/d/12RxCea4e5ggM7QGn1XE3FbLQa_-QbCNdBi90OdPjRqg"", ""'Plan de Compras'!D4:Q""), 14, 0), """")"),"ALFIO") -> ALFIO | Z11: =IFERROR(__xludf.DUMMYFUNCTION("IFERROR(VLOOKUP(G11,IMPORTRANGE(""https://docs.google.com/spreadsheets/d/12RxCea4e5ggM7QGn1XE3FbLQa_-QbCNdBi90OdPjRqg"", ""'Plan de Compras'!D4:Q""), 4, 0), """")"),"PACK DE 2 PILAS RECARGABLES (1 UND)") -> PACK DE 2 PILAS RECARGABLES (1 UND) | AA11: =IF(H11=Z11,"TRUE", "FALSE") -> TRUE | AB11: =IFERROR(__xludf.DUMMYFUNCTION("IFERROR(IF(OR(C11=TRUE,C11=""""),VLOOKUP(G11,IMPORTRANGE(""https://docs.google.com/spreadsheets/d/1z9A1Wq-kKrhRNG5RS2a2fKpY1wIhSVz2ZNmP2mOl588/edit?usp=sharing"",""REQ VF!E4:H""),4,0),""NO APLICA""),""GENERAR REQ"")"),"GENERAR REQ") -> GENERAR REQ | AC11: =IFERROR(__xludf.DUMMYFUNCTION("IFERROR(QUERY(IMPORTRANGE(""https://docs.google.com/spreadsheets/d/1z9A1Wq-kKrhRNG5RS2a2fKpY1wIhSVz2ZNmP2mOl588/edit?usp=sharing"",""REQ VF!E4:Q""),""SELECT Col10, Col11, Col12 WHERE Col1 = '""&G11&""'"",0),""NO APLICA"")"),"NO APLICA") -> NO APLICA
C12: TRUE | D12: ACCESORIO | E12: EQUIPOS | F12: COM-108 | G12: COM-108.3 | H12: FUNDA IMPERMEABLE (1 UND) | I12: =$I$9 -> 4 | J12: =IFERROR(__xludf.DUMMYFUNCTION("VLOOKUP(G12,IMPORTRANGE(""https://docs.google.com/spreadsheets/d/12RxCea4e5ggM7QGn1XE3FbLQa_-QbCNdBi90OdPjRqg/edit?gid=1692403370#gid=1692403370"", ""'Plan de Compras'!D4:2432""), 8,0)"),4.0) -> 4 | K12: =IF( C12=TRUE, IF(I12=J12,"SI","NO"), "-") -> SI | N12: CON PROVEEDOR EXTERNO | P12: 195 x 180 x 50 mm | S12: TRUE | T12: GENÉRICO | U12: FUNDAS IMPERMEABLES 22 CM X 23 CM X 9 CM PARA BALANZA 5KG | W12: =IFERROR(__xludf.DUMMYFUNCTION("IFERROR(VLOOKUP(G12,IMPORTRANGE(""https://docs.google.com/spreadsheets/d/12RxCea4e5ggM7QGn1XE3FbLQa_-QbCNdBi90OdPjRqg"", ""'Plan de Compras'!D4:Q""), 12, 0), ""NO ESTÁ EN REQ"")"),"Simple") -> Simple | X12: =IFERROR(__xludf.DUMMYFUNCTION("IFERROR(VLOOKUP(G12,IMPORTRANGE(""https://docs.google.com/spreadsheets/d/12RxCea4e5ggM7QGn1XE3FbLQa_-QbCNdBi90OdPjRqg"", ""'Plan de Compras'!D4:Q""), 13, 0), """")"),"NACIONAL") -> NACIONAL | Y12: =IFERROR(__xludf.DUMMYFUNCTION("IFERROR(VLOOKUP(G12,IMPORTRANGE(""https://docs.google.com/spreadsheets/d/12RxCea4e5ggM7QGn1XE3FbLQa_-QbCNdBi90OdPjRqg"", ""'Plan de Compras'!D4:Q""), 14, 0), """")"),"ANGIE") -> ANGIE | Z12: =IFERROR(__xludf.DUMMYFUNCTION("IFERROR(VLOOKUP(G12,IMPORTRANGE(""https://docs.google.com/spreadsheets/d/12RxCea4e5ggM7QGn1XE3FbLQa_-QbCNdBi90OdPjRqg"", ""'Plan de Compras'!D4:Q""), 4, 0), """")"),"FUNDA IMPERMEABLE (1 UND)") -> FUNDA IMPERMEABLE (1 UND) | AA12: =IF(H12=Z12,"TRUE", "FALSE") -> TRUE | AB12: =IFERROR(__xludf.DUMMYFUNCTION("IFERROR(IF(OR(C12=TRUE,C12=""""),VLOOKUP(G12,IMPORTRANGE(""https://docs.google.com/spreadsheets/d/1z9A1Wq-kKrhRNG5RS2a2fKpY1wIhSVz2ZNmP2mOl588/edit?usp=sharing"",""REQ VF!E4:H""),4,0),""NO APLICA""),""GENERAR REQ"")"),"GENERAR REQ") -> GENERAR REQ | AC12: =IFERROR(__xludf.DUMMYFUNCTION("IFERROR(QUERY(IMPORTRANGE(""https://docs.google.com/spreadsheets/d/1z9A1Wq-kKrhRNG5RS2a2fKpY1wIhSVz2ZNmP2mOl588/edit?usp=sharing"",""REQ VF!E4:Q""),""SELECT Col10, Col11, Col12 WHERE Col1 = '""&G12&""'"",0),""NO APLICA"")"),"NO APLICA") -> NO APLICA
A13: 4 | B13: TRUE | C13: TRUE | D13: BIEN | E13: EQUIPOS | F13: COM-110 | G13: COM-110-X | H13: BALANZA DIGITAL | I13: =SUMIFS('Hoja 10'!$O:$O,'Hoja 10'!$F:$F,$G13) -> 1 | J13: =IFERROR(__xludf.DUMMYFUNCTION("VLOOKUP(G13,IMPORTRANGE(""https://docs.google.com/spreadsheets/d/12RxCea4e5ggM7QGn1XE3FbLQa_-QbCNdBi90OdPjRqg/edit?gid=1692403370#gid=1692403370"", ""'Plan de Compras'!D4:2432""), 8,0)"),1.0) -> 1 | K13: =IF( C13=TRUE, IF(I13=J13,"SI","NO"), "-") -> SI | L13: COCINA Y REPOSTERÍA | M13: 5 Taller_Cocina y Respostería_Firmado.pdf | O13: =VLOOKUP($G13,'Hoja 10'!$F$4:$AA478, 19,0) -> Torrey | P13: =VLOOKUP($G13,'Hoja 10'!$F$4:$AA478, 20,0) -> PCR – 40T | Q13: =VLOOKUP($G13,'Hoja 10'!$F$4:$AA478, 21,0) -> https://balanzasprecisur.com/balanzas-comerciales/balanza-torrey-pcr-40t-de-40-kilos/ | R13: COM-110-X BALANZA DIGITAL - CET | S13: TRUE | T13: =IFERROR(__xludf.DUMMYFUNCTION(" IF ( VLOOKUP($G13,IMPORTRANGE(""https://docs.google.com/spreadsheets/d/1Gpl6jkTg7sL4VDNimUm3S9Vi1i95esohXCF3wuKOE8c"", ""'CONSOLIDADO'!G5:AB""), 10, 0) <> 0, IFERROR(VLOOKUP($G13,IMPORTRANGE(""https://docs.google.com/spreadsheets/d/1Gpl6jkTg7sL4VDNimUm3"&"S9Vi1i95esohXCF3wuKOE8c"", ""'CONSOLIDADO'!G5:AB""), 17, 0), ""-""), """" )"),"Torrey") -> Torrey | U13: =IFERROR(__xludf.DUMMYFUNCTION(" IF ( VLOOKUP($G13,IMPORTRANGE(""https://docs.google.com/spreadsheets/d/1Gpl6jkTg7sL4VDNimUm3S9Vi1i95esohXCF3wuKOE8c"", ""'CONSOLIDADO'!G5:AB""), 10, 0) <> 0, IFERROR(VLOOKUP($G13,IMPORTRANGE(""https://docs.google.com/spreadsheets/d/1Gpl6jkTg7sL4VDNimUm3"&"S9Vi1i95esohXCF3wuKOE8c"", ""'CONSOLIDADO'!G5:AB""), 18, 0), ""-""), """" )"),"PCR – 40T") -> PCR – 40T | V13: =IFERROR(__xludf.DUMMYFUNCTION(" IF ( VLOOKUP($G13,IMPORTRANGE(""https://docs.google.com/spreadsheets/d/1Gpl6jkTg7sL4VDNimUm3S9Vi1i95esohXCF3wuKOE8c"", ""'CONSOLIDADO'!G5:AB""), 10, 0) <> 0, IFERROR(VLOOKUP($G13,IMPORTRANGE(""https://docs.google.com/spreadsheets/d/1Gpl6jkTg7sL4VDNimUm3"&"S9Vi1i95esohXCF3wuKOE8c"", ""'CONSOLIDADO'!G5:AB""), 19, 0), ""-""), """" )"),"https://balanzasprecisur.com/balanzas-comerciales/balanza-torrey-pcr-40t-de-40-kilos/") -> https://balanzasprecisur.com/balanzas-comerciales/balanza-torrey-pcr-40t-de-40-kilos/ | W13: =IFERROR(__xludf.DUMMYFUNCTION("IFERROR(VLOOKUP(G13,IMPORTRANGE(""https://docs.google.com/spreadsheets/d/12RxCea4e5ggM7QGn1XE3FbLQa_-QbCNdBi90OdPjRqg"", ""'Plan de Compras'!D4:Q""), 12, 0), ""NO ESTÁ EN REQ"")"),"Técnica") -> Técnica | X13: =IFERROR(__xludf.DUMMYFUNCTION("IFERROR(VLOOKUP(G13,IMPORTRANGE(""https://docs.google.com/spreadsheets/d/12RxCea4e5ggM7QGn1XE3FbLQa_-QbCNdBi90OdPjRqg"", ""'Plan de Compras'!D4:Q""), 13, 0), """")"),"NACIONAL") -> NACIONAL | Y13: =IFERROR(__xludf.DUMMYFUNCTION("IFERROR(VLOOKUP(G13,IMPORTRANGE(""https://docs.google.com/spreadsheets/d/12RxCea4e5ggM7QGn1XE3FbLQa_-QbCNdBi90OdPjRqg"", ""'Plan de Compras'!D4:Q""), 14, 0), """")"),"ANGIE") -> ANGIE | Z13: =IFERROR(__xludf.DUMMYFUNCTION("IFERROR(VLOOKUP(G13,IMPORTRANGE(""https://docs.google.com/spreadsheets/d/12RxCea4e5ggM7QGn1XE3FbLQa_-QbCNdBi90OdPjRqg"", ""'Plan de Compras'!D4:Q""), 4, 0), """")"),"BALANZA DIGITAL") -> BALANZA DIGITAL | AA13: =IF(H13=Z13,"TRUE", "FALSE") -> TRUE | AB13: =IFERROR(__xludf.DUMMYFUNCTION("IFERROR(IF(OR(C13=TRUE,C13=""""),VLOOKUP(G13,IMPORTRANGE(""https://docs.google.com/spreadsheets/d/1z9A1Wq-kKrhRNG5RS2a2fKpY1wIhSVz2ZNmP2mOl588/edit?usp=sharing"",""REQ VF!E4:H""),4,0),""NO APLICA""),""GENERAR REQ"")"),"GENERAR REQ") -> GENERAR REQ | AC13: =IFERROR(__xludf.DUMMYFUNCTION("IFERROR(QUERY(IMPORTRANGE(""https://docs.google.com/spreadsheets/d/1z9A1Wq-kKrhRNG5RS2a2fKpY1wIhSVz2ZNmP2mOl588/edit?usp=sharing"",""REQ VF!E4:Q""),""SELECT Col10, Col11, Col12 WHERE Col1 = '""&G13&""'"",0),""NO APLICA"")"),"NO APLICA") -> NO APLICA | AF13: C
C14: TRUE | D14: ACCESORIO | E14: EQUIPOS | F14: COM-110 | G14: COM-110-X.1 | H14: FUNDA IMPERMEABLE (1 UND) | I14: =$I$13 -> 1 | J14: =IFERROR(__xludf.DUMMYFUNCTION("VLOOKUP(G14,IMPORTRANGE(""https://docs.google.com/spreadsheets/d/12RxCea4e5ggM7QGn1XE3FbLQa_-QbCNdBi90OdPjRqg/edit?gid=1692403370#gid=1692403370"", ""'Plan de Compras'!D4:2432""), 8,0)"),1.0) -> 1 | K14: =IF( C14=TRUE, IF(I14=J14,"SI","NO"), "-") -> SI | N14: CON PROVEEDOR EXTERNO | P14: 360 x 435 x 365 mm | S14: TRUE | T14: GENERICO | U14: FUNDAS IMPERMEABLES 48 CM X 42 CM X 40 CM PARA BALANZA DIGITAL | W14: =IFERROR(__xludf.DUMMYFUNCTION("IFERROR(VLOOKUP(G14,IMPORTRANGE(""https://docs.google.com/spreadsheets/d/12RxCea4e5ggM7QGn1XE3FbLQa_-QbCNdBi90OdPjRqg"", ""'Plan de Compras'!D4:Q""), 12, 0), ""NO ESTÁ EN REQ"")"),"Simple") -> Simple | X14: =IFERROR(__xludf.DUMMYFUNCTION("IFERROR(VLOOKUP(G14,IMPORTRANGE(""https://docs.google.com/spreadsheets/d/12RxCea4e5ggM7QGn1XE3FbLQa_-QbCNdBi90OdPjRqg"", ""'Plan de Compras'!D4:Q""), 13, 0), """")"),"NACIONAL") -> NACIONAL | Y14: =IFERROR(__xludf.DUMMYFUNCTION("IFERROR(VLOOKUP(G14,IMPORTRANGE(""https://docs.google.com/spreadsheets/d/12RxCea4e5ggM7QGn1XE3FbLQa_-QbCNdBi90OdPjRqg"", ""'Plan de Compras'!D4:Q""), 14, 0), """")"),"ANGIE") -> ANGIE | Z14: =IFERROR(__xludf.DUMMYFUNCTION("IFERROR(VLOOKUP(G14,IMPORTRANGE(""https://docs.google.com/spreadsheets/d/12RxCea4e5ggM7QGn1XE3FbLQa_-QbCNdBi90OdPjRqg"", ""'Plan de Compras'!D4:Q""), 4, 0), """")"),"FUNDA IMPERMEABLE (1 UND)") -> FUNDA IMPERMEABLE (1 UND) | AA14: =IF(H14=Z14,"TRUE", "FALSE") -> TRUE | AB14: =IFERROR(__xludf.DUMMYFUNCTION("IFERROR(IF(OR(C14=TRUE,C14=""""),VLOOKUP(G14,IMPORTRANGE(""https://docs.google.com/spreadsheets/d/1z9A1Wq-kKrhRNG5RS2a2fKpY1wIhSVz2ZNmP2mOl588/edit?usp=sharing"",""REQ VF!E4:H""),4,0),""NO APLICA""),""GENERAR REQ"")"),"GENERAR REQ") -> GENERAR REQ | AC14: =IFERROR(__xludf.DUMMYFUNCTION("IFERROR(QUERY(IMPORTRANGE(""https://docs.google.com/spreadsheets/d/1z9A1Wq-kKrhRNG5RS2a2fKpY1wIhSVz2ZNmP2mOl588/edit?usp=sharing"",""REQ VF!E4:Q""),""SELECT Col10, Col11, Col12 WHERE Col1 = '""&G14&""'"",0),""NO APLICA"")"),"NO APLICA") -> NO APLICA
A15: 5 | B15: TRUE | C15: TRUE | D15: BIEN | E15: EQUIPOS | F15: COM-110 | G15: COM-110-Y | H15: BALANZA DIGITAL | I15: =SUMIFS('Hoja 10'!$O:$O,'Hoja 10'!$F:$F,$G15) -> 8 | J15: =IFERROR(__xludf.DUMMYFUNCTION("VLOOKUP(G15,IMPORTRANGE(""https://docs.google.com/spreadsheets/d/12RxCea4e5ggM7QGn1XE3FbLQa_-QbCNdBi90OdPjRqg/edit?gid=1692403370#gid=1692403370"", ""'Plan de Compras'!D4:2432""), 8,0)"),8.0) -> 8 | K15: =IF( C15=TRUE, IF(I15=J15,"SI","NO"), "-") -> SI | L15: INDUSTRIA ALIMENTARIA | M15: 12 Taller_Industria_Alimentaria_Firmado.pdf | O15: =VLOOKUP($G15,'Hoja 10'!$F$4:$AA478, 19,0) -> Torrey | P15: =VLOOKUP($G15,'Hoja 10'!$F$4:$AA478, 20,0) -> PCR – 40T | Q15: =VLOOKUP($G15,'Hoja 10'!$F$4:$AA478, 21,0) -> https://balanzasprecisur.com/balanzas-comerciales/balanza-torrey-pcr-40t-de-40-kilos/ | R15: COM-110-Y BALANZA DIGITAL - CET | S15: TRUE | T15: =IFERROR(__xludf.DUMMYFUNCTION(" IF ( VLOOKUP($G15,IMPORTRANGE(""https://docs.google.com/spreadsheets/d/1Gpl6jkTg7sL4VDNimUm3S9Vi1i95esohXCF3wuKOE8c"", ""'CONSOLIDADO'!G5:AB""), 10, 0) <> 0, IFERROR(VLOOKUP($G15,IMPORTRANGE(""https://docs.google.com/spreadsheets/d/1Gpl6jkTg7sL4VDNimUm3"&"S9Vi1i95esohXCF3wuKOE8c"", ""'CONSOLIDADO'!G5:AB""), 17, 0), ""-""), """" )"),"Torrey") -> Torrey | U15: =IFERROR(__xludf.DUMMYFUNCTION(" IF ( VLOOKUP($G15,IMPORTRANGE(""https://docs.google.com/spreadsheets/d/1Gpl6jkTg7sL4VDNimUm3S9Vi1i95esohXCF3wuKOE8c"", ""'CONSOLIDADO'!G5:AB""), 10, 0) <> 0, IFERROR(VLOOKUP($G15,IMPORTRANGE(""https://docs.google.com/spreadsheets/d/1Gpl6jkTg7sL4VDNimUm3"&"S9Vi1i95esohXCF3wuKOE8c"", ""'CONSOLIDADO'!G5:AB""), 18, 0), ""-""), """" )"),"PCR – 40T") -> PCR – 40T | V15: =IFERROR(__xludf.DUMMYFUNCTION(" IF ( VLOOKUP($G15,IMPORTRANGE(""https://docs.google.com/spreadsheets/d/1Gpl6jkTg7sL4VDNimUm3S9Vi1i95esohXCF3wuKOE8c"", ""'CONSOLIDADO'!G5:AB""), 10, 0) <> 0, IFERROR(VLOOKUP($G15,IMPORTRANGE(""https://docs.google.com/spreadsheets/d/1Gpl6jkTg7sL4VDNimUm3"&"S9Vi1i95esohXCF3wuKOE8c"", ""'CONSOLIDADO'!G5:AB""), 19, 0), ""-""), """" )"),"https://balanzasprecisur.com/balanzas-comerciales/balanza-torrey-pcr-40t-de-40-kilos/") -> https://balanzasprecisur.com/balanzas-comerciales/balanza-torrey-pcr-40t-de-40-kilos/ | W15: =IFERROR(__xludf.DUMMYFUNCTION("IFERROR(VLOOKUP(G15,IMPORTRANGE(""https://docs.google.com/spreadsheets/d/12RxCea4e5ggM7QGn1XE3FbLQa_-QbCNdBi90OdPjRqg"", ""'Plan de Compras'!D4:Q""), 12, 0), ""NO ESTÁ EN REQ"")"),"Técnica") -> Técnica | X15: =IFERROR(__xludf.DUMMYFUNCTION("IFERROR(VLOOKUP(G15,IMPORTRANGE(""https://docs.google.com/spreadsheets/d/12RxCea4e5ggM7QGn1XE3FbLQa_-QbCNdBi90OdPjRqg"", ""'Plan de Compras'!D4:Q""), 13, 0), """")"),"NACIONAL") -> NACIONAL | Y15: =IFERROR(__xludf.DUMMYFUNCTION("IFERROR(VLOOKUP(G15,IMPORTRANGE(""https://docs.google.com/spreadsheets/d/12RxCea4e5ggM7QGn1XE3FbLQa_-QbCNdBi90OdPjRqg"", ""'Plan de Compras'!D4:Q""), 14, 0), """")"),"ANGIE") -> ANGIE | Z15: =IFERROR(__xludf.DUMMYFUNCTION("IFERROR(VLOOKUP(G15,IMPORTRANGE(""https://docs.google.com/spreadsheets/d/12RxCea4e5ggM7QGn1XE3FbLQa_-QbCNdBi90OdPjRqg"", ""'Plan de Compras'!D4:Q""), 4, 0), """")"),"BALANZA DIGITAL") -> BALANZA DIGITAL | AA15: =IF(H15=Z15,"TRUE", "FALSE") -> TRUE | AB15: =IFERROR(__xludf.DUMMYFUNCTION("IFERROR(IF(OR(C15=TRUE,C15=""""),VLOOKUP(G15,IMPORTRANGE(""https://docs.google.com/spreadsheets/d/1z9A1Wq-kKrhRNG5RS2a2fKpY1wIhSVz2ZNmP2mOl588/edit?usp=sharing"",""REQ VF!E4:H""),4,0),""NO APLICA""),""GENERAR REQ"")"),"GENERAR REQ") -> GENERAR REQ | AC15: =IFERROR(__xludf.DUMMYFUNCTION("IFERROR(QUERY(IMPORTRANGE(""https://docs.google.com/spreadsheets/d/1z9A1Wq-kKrhRNG5RS2a2fKpY1wIhSVz2ZNmP2mOl588/edit?usp=sharing"",""REQ VF!E4:Q""),""SELECT Col10, Col11, Col12 WHERE Col1 = '""&G15&""'"",0),""NO APLICA"")"),"NO APLICA") -> NO APLICA | AF15: C
C16: TRUE | D16: ACCESORIO | E16: EQUIPOS | F16: COM-110 | G16: COM-110-Y.1 | H16: BALANZA DIGITAL | I16: =$I$15 -> 8 | J16: =IFERROR(__xludf.DUMMYFUNCTION("VLOOKUP(G16,IMPORTRANGE(""https://docs.google.com/spreadsheets/d/12RxCea4e5ggM7QGn1XE3FbLQa_-QbCNdBi90OdPjRqg/edit?gid=1692403370#gid=1692403370"", ""'Plan de Compras'!D4:2432""), 8,0)"),8.0) -> 8 | K16: =IF( C16=TRUE, IF(I16=J16,"SI","NO"), "-") -> SI | N16: CON PROVEEDOR EXTERNO | P16: 360 x 435 x 365 mm | S16: TRUE | T16: GENERICO | U16: FUNDAS IMPERMEABLES 48 CM X 42 CM X 40 CM PARA BALANZA DIGITAL | W16: =IFERROR(__xludf.DUMMYFUNCTION("IFERROR(VLOOKUP(G16,IMPORTRANGE(""https://docs.google.com/spreadsheets/d/12RxCea4e5ggM7QGn1XE3FbLQa_-QbCNdBi90OdPjRqg"", ""'Plan de Compras'!D4:Q""), 12, 0), ""NO ESTÁ EN REQ"")"),"Simple") -> Simple | X16: =IFERROR(__xludf.DUMMYFUNCTION("IFERROR(VLOOKUP(G16,IMPORTRANGE(""https://docs.google.com/spreadsheets/d/12RxCea4e5ggM7QGn1XE3FbLQa_-QbCNdBi90OdPjRqg"", ""'Plan de Compras'!D4:Q""), 13, 0), """")"),"NACIONAL") -> NACIONAL | Y16: =IFERROR(__xludf.DUMMYFUNCTION("IFERROR(VLOOKUP(G16,IMPORTRANGE(""https://docs.google.com/spreadsheets/d/12RxCea4e5ggM7QGn1XE3FbLQa_-QbCNdBi90OdPjRqg"", ""'Plan de Compras'!D4:Q""), 14, 0), """")"),"ANGIE") -> ANGIE | Z16: =IFERROR(__xludf.DUMMYFUNCTION("IFERROR(VLOOKUP(G16,IMPORTRANGE(""https://docs.google.com/spreadsheets/d/12RxCea4e5ggM7QGn1XE3FbLQa_-QbCNdBi90OdPjRqg"", ""'Plan de Compras'!D4:Q""), 4, 0), """")"),"FUNDA IMPERMEABLE (1 UND)") -> FUNDA IMPERMEABLE (1 UND) | AA16: =IF(H16=Z16,"TRUE", "FALSE") -> FALSE | AB16: =IFERROR(__xludf.DUMMYFUNCTION("IFERROR(IF(OR(C16=TRUE,C16=""""),VLOOKUP(G16,IMPORTRANGE(""https://docs.google.com/spreadsheets/d/1z9A1Wq-kKrhRNG5RS2a2fKpY1wIhSVz2ZNmP2mOl588/edit?usp=sharing"",""REQ VF!E4:H""),4,0),""NO APLICA""),""GENERAR REQ"")"),"GENERAR REQ") -> GENERAR REQ | AC16: =IFERROR(__xludf.DUMMYFUNCTION("IFERROR(QUERY(IMPORTRANGE(""https://docs.google.com/spreadsheets/d/1z9A1Wq-kKrhRNG5RS2a2fKpY1wIhSVz2ZNmP2mOl588/edit?usp=sharing"",""REQ VF!E4:Q""),""SELECT Col10, Col11, Col12 WHERE Col1 = '""&G16&""'"",0),""NO APLICA"")"),"NO APLICA") -> NO APLICA
A17: 6 | B17: TRUE | C17: TRUE | D17: BIEN | E17: EQUIPOS | F17: COM-111 | G17: COM-111 | H17: BALANZA GRAMERA 500G | I17: =SUMIFS('Hoja 10'!$O:$O,'Hoja 10'!$F:$F,$G17) -> 4 | J17: =IFERROR(__xludf.DUMMYFUNCTION("VLOOKUP(G17,IMPORTRANGE(""https://docs.google.com/spreadsheets/d/12RxCea4e5ggM7QGn1XE3FbLQa_-QbCNdBi90OdPjRqg/edit?gid=1692403370#gid=1692403370"", ""'Plan de Compras'!D4:2432""), 8,0)"),4.0) -> 4 | K17: =IF( C17=TRUE, IF(I17=J17,"SI","NO"), "-") -> SI | L17: INDUSTRIA ALIMENTARIA | M17: 12 Taller_Industria_Alimentaria_Firmado.pdf | O17: =VLOOKUP($G17,'Hoja 10'!$F$4:$AA478, 19,0) -> Truper | P17: =VLOOKUP($G17,'Hoja 10'!$F$4:$AA478, 20,0) -> Báscula electrónica de precisión, de bolsillo, 500 g | Q17: =VLOOKUP($G17,'Hoja 10'!$F$4:$AA478, 21,0) -> https://www.truper.com/ficha_tecnica/Bascula-digital-de-precision-de-bolsillo-500g-Truper.html?code=102316 | R17: COM-111 BALANZA GRAMERA 500G - CET | S17: TRUE | T17: =IFERROR(__xludf.DUMMYFUNCTION(" IF ( VLOOKUP($G17,IMPORTRANGE(""https://docs.google.com/spreadsheets/d/1Gpl6jkTg7sL4VDNimUm3S9Vi1i95esohXCF3wuKOE8c"", ""'CONSOLIDADO'!G5:AB""), 10, 0) <> 0, IFERROR(VLOOKUP($G17,IMPORTRANGE(""https://docs.google.com/spreadsheets/d/1Gpl6jkTg7sL4VDNimUm3"&"S9Vi1i95esohXCF3wuKOE8c"", ""'CONSOLIDADO'!G5:AB""), 17, 0), ""-""), """" )"),"TRUPER ") -> TRUPER | U17: =IFERROR(__xludf.DUMMYFUNCTION(" IF ( VLOOKUP($G17,IMPORTRANGE(""https://docs.google.com/spreadsheets/d/1Gpl6jkTg7sL4VDNimUm3S9Vi1i95esohXCF3wuKOE8c"", ""'CONSOLIDADO'!G5:AB""), 10, 0) <> 0, IFERROR(VLOOKUP($G17,IMPORTRANGE(""https://docs.google.com/spreadsheets/d/1Gpl6jkTg7sL4VDNimUm3"&"S9Vi1i95esohXCF3wuKOE8c"", ""'CONSOLIDADO'!G5:AB""), 18, 0), ""-""), """" )"),"BASE-05B") -> BASE-05B | V17: =IFERROR(__xludf.DUMMYFUNCTION(" IF ( VLOOKUP($G17,IMPORTRANGE(""https://docs.google.com/spreadsheets/d/1Gpl6jkTg7sL4VDNimUm3S9Vi1i95esohXCF3wuKOE8c"", ""'CONSOLIDADO'!G5:AB""), 10, 0) <> 0, IFERROR(VLOOKUP($G17,IMPORTRANGE(""https://docs.google.com/spreadsheets/d/1Gpl6jkTg7sL4VDNimUm3"&"S9Vi1i95esohXCF3wuKOE8c"", ""'CONSOLIDADO'!G5:AB""), 19, 0), ""-""), """" )"),"https://www.truper.com/ficha_tecnica/Bascula-digital-de-precision-de-bolsillo-500g-Truper.html?code=102316") -> https://www.truper.com/ficha_tecnica/Bascula-digital-de-precision-de-bolsillo-500g-Truper.html?code=102316 | W17: =IFERROR(__xludf.DUMMYFUNCTION("IFERROR(VLOOKUP(G17,IMPORTRANGE(""https://docs.google.com/spreadsheets/d/12RxCea4e5ggM7QGn1XE3FbLQa_-QbCNdBi90OdPjRqg"", ""'Plan de Compras'!D4:Q""), 12, 0), ""NO ESTÁ EN REQ"")"),"Técnica") -> Técnica | X17: =IFERROR(__xludf.DUMMYFUNCTION("IFERROR(VLOOKUP(G17,IMPORTRANGE(""https://docs.google.com/spreadsheets/d/12RxCea4e5ggM7QGn1XE3FbLQa_-QbCNdBi90OdPjRqg"", ""'Plan de Compras'!D4:Q""), 13, 0), """")"),"NACIONAL") -> NACIONAL | Y17: =IFERROR(__xludf.DUMMYFUNCTION("IFERROR(VLOOKUP(G17,IMPORTRANGE(""https://docs.google.com/spreadsheets/d/12RxCea4e5ggM7QGn1XE3FbLQa_-QbCNdBi90OdPjRqg"", ""'Plan de Compras'!D4:Q""), 14, 0), """")"),"ANGIE") -> ANGIE | Z17: =IFERROR(__xludf.DUMMYFUNCTION("IFERROR(VLOOKUP(G17,IMPORTRANGE(""https://docs.google.com/spreadsheets/d/12RxCea4e5ggM7QGn1XE3FbLQa_-QbCNdBi90OdPjRqg"", ""'Plan de Compras'!D4:Q""), 4, 0), """")"),"BALANZA GRAMERA 500G") -> BALANZA GRAMERA 500G | AA17: =IF(H17=Z17,"TRUE", "FALSE") -> TRUE | AB17: =IFERROR(__xludf.DUMMYFUNCTION("IFERROR(IF(OR(C17=TRUE,C17=""""),VLOOKUP(G17,IMPORTRANGE(""https://docs.google.com/spreadsheets/d/1z9A1Wq-kKrhRNG5RS2a2fKpY1wIhSVz2ZNmP2mOl588/edit?usp=sharing"",""REQ VF!E4:H""),4,0),""NO APLICA""),""GENERAR REQ"")"),"GENERAR REQ") -> GENERAR REQ | AC17: =IFERROR(__xludf.DUMMYFUNCTION("IFERROR(QUERY(IMPORTRANGE(""https://docs.google.com/spreadsheets/d/1z9A1Wq-kKrhRNG5RS2a2fKpY1wIhSVz2ZNmP2mOl588/edit?usp=sharing"",""REQ VF!E4:Q""),""SELECT Col10, Col11, Col12 WHERE Col1 = '""&G17&""'"",0),""NO APLICA"")"),"NO APLICA") -> NO APLICA | AF17: C
A18: 7 | B18: TRUE | C18: FALSE | D18: BIEN | E18: EQUIPOS | F18: COM-123 | G18: COM-123 | H18: CABINA DE SOLDAR CON MESA DE TRABAJO | I18: =SUMIFS('Hoja 10'!$O:$O,'Hoja 10'!$F:$F,$G18) -> 4 | J18: =IFERROR(__xludf.DUMMYFUNCTION("VLOOKUP(G18,IMPORTRANGE(""https://docs.google.com/spreadsheets/d/12RxCea4e5ggM7QGn1XE3FbLQa_-QbCNdBi90OdPjRqg/edit?gid=1692403370#gid=1692403370"", ""'Plan de Compras'!D4:2432""), 8,0)"),"#N/A") -> #N/A | K18: =IF( C18=TRUE, IF(I18=J18,"SI","NO"), "-") -> - | L18: CONSTRUCCIONES METÁLICAS | M18: 16 Taller_Construcciones Metálicas_Firmado.pdf | N18: SE MANDA A FABRICAR | O18: =VLOOKUP($G18,'Hoja 10'!$F$4:$AA478, 19,0) -> NUPRINOX | P18: =VLOOKUP($G18,'Hoja 10'!$F$4:$AA478, 20,0) -> A medida | Q18: =VLOOKUP($G18,'Hoja 10'!$F$4:$AA478, 21,0) -> https://www.amazon.com/-/es/soldadura-pulgadas-industrial-capacidad-port%C3%A1til/dp/B0DDPVR3L1 | R18: COM-123 CABINA DE SOLDAR CON MESA DE TRABAJO - CET | S18: TRUE | T18: =IFERROR(__xludf.DUMMYFUNCTION(" IF ( VLOOKUP($G18,IMPORTRANGE(""https://docs.google.com/spreadsheets/d/1Gpl6jkTg7sL4VDNimUm3S9Vi1i95esohXCF3wuKOE8c"", ""'CONSOLIDADO'!G5:AB""), 10, 0) <> 0, IFERROR(VLOOKUP($G18,IMPORTRANGE(""https://docs.google.com/spreadsheets/d/1Gpl6jkTg7sL4VDNimUm3"&"S9Vi1i95esohXCF3wuKOE8c"", ""'CONSOLIDADO'!G5:AB""), 17, 0), ""-""), """" )"),"A MEDIDA HUGO") -> A MEDIDA HUGO | U18: =IFERROR(__xludf.DUMMYFUNCTION(" IF ( VLOOKUP($G18,IMPORTRANGE(""https://docs.google.com/spreadsheets/d/1Gpl6jkTg7sL4VDNimUm3S9Vi1i95esohXCF3wuKOE8c"", ""'CONSOLIDADO'!G5:AB""), 10, 0) <> 0, IFERROR(VLOOKUP($G18,IMPORTRANGE(""https://docs.google.com/spreadsheets/d/1Gpl6jkTg7sL4VDNimUm3"&"S9Vi1i95esohXCF3wuKOE8c"", ""'CONSOLIDADO'!G5:AB""), 18, 0), ""-""), """" )"),"A MEDIDA") -> A MEDIDA | V18: =IFERROR(__xludf.DUMMYFUNCTION(" IF ( VLOOKUP($G18,IMPORTRANGE(""https://docs.google.com/spreadsheets/d/1Gpl6jkTg7sL4VDNimUm3S9Vi1i95esohXCF3wuKOE8c"", ""'CONSOLIDADO'!G5:AB""), 10, 0) <> 0, IFERROR(VLOOKUP($G18,IMPORTRANGE(""https://docs.google.com/spreadsheets/d/1Gpl6jkTg7sL4VDNimUm3"&"S9Vi1i95esohXCF3wuKOE8c"", ""'CONSOLIDADO'!G5:AB""), 19, 0), ""-""), """" )"),"") | W18: =IFERROR(__xludf.DUMMYFUNCTION("IFERROR(VLOOKUP(G18,IMPORTRANGE(""https://docs.google.com/spreadsheets/d/12RxCea4e5ggM7QGn1XE3FbLQa_-QbCNdBi90OdPjRqg"", ""'Plan de Compras'!D4:Q""), 12, 0), ""NO ESTÁ EN REQ"")"),"NO ESTÁ EN REQ") -> NO ESTÁ EN REQ | X18: =IFERROR(__xludf.DUMMYFUNCTION("IFERROR(VLOOKUP(G18,IMPORTRANGE(""https://docs.google.com/spreadsheets/d/12RxCea4e5ggM7QGn1XE3FbLQa_-QbCNdBi90OdPjRqg"", ""'Plan de Compras'!D4:Q""), 13, 0), """")"),"") | Y18: =IFERROR(__xludf.DUMMYFUNCTION("IFERROR(VLOOKUP(G18,IMPORTRANGE(""https://docs.google.com/spreadsheets/d/12RxCea4e5ggM7QGn1XE3FbLQa_-QbCNdBi90OdPjRqg"", ""'Plan de Compras'!D4:Q""), 14, 0), """")"),"") | Z18: =IFERROR(__xludf.DUMMYFUNCTION("IFERROR(VLOOKUP(G18,IMPORTRANGE(""https://docs.google.com/spreadsheets/d/12RxCea4e5ggM7QGn1XE3FbLQa_-QbCNdBi90OdPjRqg"", ""'Plan de Compras'!D4:Q""), 4, 0), """")"),"") | AB18: =IFERROR(__xludf.DUMMYFUNCTION("IFERROR(IF(OR(C18=TRUE,C18=""""),VLOOKUP(G18,IMPORTRANGE(""https://docs.google.com/spreadsheets/d/1z9A1Wq-kKrhRNG5RS2a2fKpY1wIhSVz2ZNmP2mOl588/edit?usp=sharing"",""REQ VF!E4:H""),4,0),""NO APLICA""),""GENERAR REQ"")"),"NO APLICA") -> NO APLICA | AC18: =IFERROR(__xludf.DUMMYFUNCTION("IFERROR(QUERY(IMPORTRANGE(""https://docs.google.com/spreadsheets/d/1z9A1Wq-kKrhRNG5RS2a2fKpY1wIhSVz2ZNmP2mOl588/edit?usp=sharing"",""REQ VF!E4:Q""),""SELECT Col10, Col11, Col12 WHERE Col1 = '""&G18&""'"",0),""NO APLICA"")"),"NO APLICA") -> NO APLICA
C19: TRUE | D19: COMPONENTE | E19: EQUIPOS | F19: COM-123 | G19: COM-123.1 | H19: CABINA DE SOLDAR 2.20 X 0.90 X 0.90 M (1 UND) | I19: =$I$18 -> 4 | J19: =IFERROR(__xludf.DUMMYFUNCTION("VLOOKUP(G19,IMPORTRANGE(""https://docs.google.com/spreadsheets/d/12RxCea4e5ggM7QGn1XE3FbLQa_-QbCNdBi90OdPjRqg/edit?gid=1692403370#gid=1692403370"", ""'Plan de Compras'!D4:2432""), 8,0)"),4.0) -> 4 | K19: =IF( C19=TRUE, IF(I19=J19,"SI","NO"), "-") -> SI | S19: TRUE | T19: HUGO | U19: A MEDIDA | W19: =IFERROR(__xludf.DUMMYFUNCTION("IFERROR(VLOOKUP(G19,IMPORTRANGE(""https://docs.google.com/spreadsheets/d/12RxCea4e5ggM7QGn1XE3FbLQa_-QbCNdBi90OdPjRqg"", ""'Plan de Compras'!D4:Q""), 12, 0), ""NO ESTÁ EN REQ"")"),"Técnica") -> Técnica | X19: =IFERROR(__xludf.DUMMYFUNCTION("IFERROR(VLOOKUP(G19,IMPORTRANGE(""https://docs.google.com/spreadsheets/d/12RxCea4e5ggM7QGn1XE3FbLQa_-QbCNdBi90OdPjRqg"", ""'Plan de Compras'!D4:Q""), 13, 0), """")"),"NACIONAL") -> NACIONAL | Y19: =IFERROR(__xludf.DUMMYFUNCTION("IFERROR(VLOOKUP(G19,IMPORTRANGE(""https://docs.google.com/spreadsheets/d/12RxCea4e5ggM7QGn1XE3FbLQa_-QbCNdBi90OdPjRqg"", ""'Plan de Compras'!D4:Q""), 14, 0), """")"),"OMAR") -> OMAR | Z19: =IFERROR(__xludf.DUMMYFUNCTION("IFERROR(VLOOKUP(G19,IMPORTRANGE(""https://docs.google.com/spreadsheets/d/12RxCea4e5ggM7QGn1XE3FbLQa_-QbCNdBi90OdPjRqg"", ""'Plan de Compras'!D4:Q""), 4, 0), """")"),"CABINA DE SOLDAR 2.20 X 0.90 X 0.90 M (1 UND)") -> CABINA DE SOLDAR 2.20 X 0.90 X 0.90 M (1 UND) | AA19: =IF(H19=Z19,"TRUE", "FALSE") -> TRUE | AB19: =IFERROR(__xludf.DUMMYFUNCTION("IFERROR(IF(OR(C19=TRUE,C19=""""),VLOOKUP(G19,IMPORTRANGE(""https://docs.google.com/spreadsheets/d/1z9A1Wq-kKrhRNG5RS2a2fKpY1wIhSVz2ZNmP2mOl588/edit?usp=sharing"",""REQ VF!E4:H""),4,0),""NO APLICA""),""GENERAR REQ"")"),"GENERAR REQ") -> GENERAR REQ | AC19: =IFERROR(__xludf.DUMMYFUNCTION("IFERROR(QUERY(IMPORTRANGE(""https://docs.google.com/spreadsheets/d/1z9A1Wq-kKrhRNG5RS2a2fKpY1wIhSVz2ZNmP2mOl588/edit?usp=sharing"",""REQ VF!E4:Q""),""SELECT Col10, Col11, Col12 WHERE Col1 = '""&G19&""'"",0),""NO APLICA"")"),"NO APLICA") -> NO APLICA
C20: TRUE | D20: COMPONENTE | E20: EQUIPOS | F20: COM-123 | G20: COM-123.2 | H20: MESA DE SOLDADURA MÓVIL 0.80 X 0.60 X 0.75 M (1 UND) | I20: =$I$18 -> 4 | J20: =IFERROR(__xludf.DUMMYFUNCTION("VLOOKUP(G20,IMPORTRANGE(""https://docs.google.com/spreadsheets/d/12RxCea4e5ggM7QGn1XE3FbLQa_-QbCNdBi90OdPjRqg/edit?gid=1692403370#gid=1692403370"", ""'Plan de Compras'!D4:2432""), 8,0)"),4.0) -> 4 | K20: =IF( C20=TRUE, IF(I20=J20,"SI","NO"), "-") -> SI | N20: SE MANDA A FABRICAR | S20: TRUE | T20: HUGO | U20: A MEDIDA | W20: =IFERROR(__xludf.DUMMYFUNCTION("IFERROR(VLOOKUP(G20,IMPORTRANGE(""https://docs.google.com/spreadsheets/d/12RxCea4e5ggM7QGn1XE3FbLQa_-QbCNdBi90OdPjRqg"", ""'Plan de Compras'!D4:Q""), 12, 0), ""NO ESTÁ EN REQ"")"),"Técnica") -> Técnica | X20: =IFERROR(__xludf.DUMMYFUNCTION("IFERROR(VLOOKUP(G20,IMPORTRANGE(""https://docs.google.com/spreadsheets/d/12RxCea4e5ggM7QGn1XE3FbLQa_-QbCNdBi90OdPjRqg"", ""'Plan de Compras'!D4:Q""), 13, 0), """")"),"NACIONAL") -> NACIONAL | Y20: =IFERROR(__xludf.DUMMYFUNCTION("IFERROR(VLOOKUP(G20,IMPORTRANGE(""https://docs.google.com/spreadsheets/d/12RxCea4e5ggM7QGn1XE3FbLQa_-QbCNdBi90OdPjRqg"", ""'Plan de Compras'!D4:Q""), 14, 0), """")"),"OMAR") -> OMAR | Z20: =IFERROR(__xludf.DUMMYFUNCTION("IFERROR(VLOOKUP(G20,IMPORTRANGE(""https://docs.google.com/spreadsheets/d/12RxCea4e5ggM7QGn1XE3FbLQa_-QbCNdBi90OdPjRqg"", ""'Plan de Compras'!D4:Q""), 4, 0), """")"),"MESA DE SOLDADURA MÓVIL 0.80 X 0.60 X 0.75 M (1 UND)") -> MESA DE SOLDADURA MÓVIL 0.80 X 0.60 X 0.75 M (1 UND) | AA20: =IF(H20=Z20,"TRUE", "FALSE") -> TRUE | AB20: =IFERROR(__xludf.DUMMYFUNCTION("IFERROR(IF(OR(C20=TRUE,C20=""""),VLOOKUP(G20,IMPORTRANGE(""https://docs.google.com/spreadsheets/d/1z9A1Wq-kKrhRNG5RS2a2fKpY1wIhSVz2ZNmP2mOl588/edit?usp=sharing"",""REQ VF!E4:H""),4,0),""NO APLICA""),""GENERAR REQ"")"),"GENERAR REQ") -> GENERAR REQ | AC20: =IFERROR(__xludf.DUMMYFUNCTION("IFERROR(QUERY(IMPORTRANGE(""https://docs.google.com/spreadsheets/d/1z9A1Wq-kKrhRNG5RS2a2fKpY1wIhSVz2ZNmP2mOl588/edit?usp=sharing"",""REQ VF!E4:Q""),""SELECT Col10, Col11, Col12 WHERE Col1 = '""&G20&""'"",0),""NO APLICA"")"),"NO APLICA") -> NO APLICA
A21: 8 | B21: TRUE | C21: TRUE | D21: BIEN | E21: EQUIPOS | F21: ESP-103 | G21: ESP-103 | H21: AMOLADORA | I21: =SUMIFS('Hoja 10'!$O:$O,'Hoja 10'!$F:$F,$G21) -> 4 | J21: =IFERROR(__xludf.DUMMYFUNCTION("VLOOKUP(G21,IMPORTRANGE(""https://docs.google.com/spreadsheets/d/12RxCea4e5ggM7QGn1XE3FbLQa_-QbCNdBi90OdPjRqg/edit?gid=1692403370#gid=1692403370"", ""'Plan de Compras'!D4:2432""), 8,0)"),4.0) -> 4 | K21: =IF( C21=TRUE, IF(I21=J21,"SI","NO"), "-") -> SI | L21: MECÁNICA AUTOMOTRÍZ, CONSTRUCCIONES METÁLICAS | M21: 1 Taller_Mecanica_Automotriz_Firmado.pdf | O21: =VLOOKUP($G21,'Hoja 10'!$F$4:$AA478, 19,0) -> BOSCH | P21: =VLOOKUP($G21,'Hoja 10'!$F$4:$AA478, 20,0) -> GWS 9-125 P | Q21: =VLOOKUP($G21,'Hoja 10'!$F$4:$AA478, 21,0) -> https://soelco.co/producto/mini-pulidora-angular-segura-900-w-125-mm-110-v-bosch/?srsltid=AfmBOorerIGp1jcFwSUGxZb2mjq5MenuM3THMVYyN7v09ItDhlwh_pEr | R21: ESP-103 AMOLADORA - CET | S21: TRUE | T21: =IFERROR(__xludf.DUMMYFUNCTION(" IF ( VLOOKUP($G21,IMPORTRANGE(""https://docs.google.com/spreadsheets/d/1Gpl6jkTg7sL4VDNimUm3S9Vi1i95esohXCF3wuKOE8c"", ""'CONSOLIDADO'!G5:AB""), 10, 0) <> 0, IFERROR(VLOOKUP($G21,IMPORTRANGE(""https://docs.google.com/spreadsheets/d/1Gpl6jkTg7sL4VDNimUm3"&"S9Vi1i95esohXCF3wuKOE8c"", ""'CONSOLIDADO'!G5:AB""), 17, 0), ""-""), """" )"),"BOSCH") -> BOSCH | U21: =IFERROR(__xludf.DUMMYFUNCTION(" IF ( VLOOKUP($G21,IMPORTRANGE(""https://docs.google.com/spreadsheets/d/1Gpl6jkTg7sL4VDNimUm3S9Vi1i95esohXCF3wuKOE8c"", ""'CONSOLIDADO'!G5:AB""), 10, 0) <> 0, IFERROR(VLOOKUP($G21,IMPORTRANGE(""https://docs.google.com/spreadsheets/d/1Gpl6jkTg7sL4VDNimUm3"&"S9Vi1i95esohXCF3wuKOE8c"", ""'CONSOLIDADO'!G5:AB""), 18, 0), ""-""), """" )"),"GWS 12-125 P") -> GWS 12-125 P | V21: =IFERROR(__xludf.DUMMYFUNCTION(" IF ( VLOOKUP($G21,IMPORTRANGE(""https://docs.google.com/spreadsheets/d/1Gpl6jkTg7sL4VDNimUm3S9Vi1i95esohXCF3wuKOE8c"", ""'CONSOLIDADO'!G5:AB""), 10, 0) <> 0, IFERROR(VLOOKUP($G21,IMPORTRANGE(""https://docs.google.com/spreadsheets/d/1Gpl6jkTg7sL4VDNimUm3"&"S9Vi1i95esohXCF3wuKOE8c"", ""'CONSOLIDADO'!G5:AB""), 19, 0), ""-""), """" )"),"https://www.bosch-professional.com/pe/es/products/gws-12-125-p-06013A62E0") -> https://www.bosch-professional.com/pe/es/products/gws-12-125-p-06013A62E0 | W21: =IFERROR(__xludf.DUMMYFUNCTION("IFERROR(VLOOKUP(G21,IMPORTRANGE(""https://docs.google.com/spreadsheets/d/12RxCea4e5ggM7QGn1XE3FbLQa_-QbCNdBi90OdPjRqg"", ""'Plan de Compras'!D4:Q""), 12, 0), ""NO ESTÁ EN REQ"")"),"Técnica") -> Técnica | X21: =IFERROR(__xludf.DUMMYFUNCTION("IFERROR(VLOOKUP(G21,IMPORTRANGE(""https://docs.google.com/spreadsheets/d/12RxCea4e5ggM7QGn1XE3FbLQa_-QbCNdBi90OdPjRqg"", ""'Plan de Compras'!D4:Q""), 13, 0), """")"),"NACIONAL") -> NACIONAL | Y21: =IFERROR(__xludf.DUMMYFUNCTION("IFERROR(VLOOKUP(G21,IMPORTRANGE(""https://docs.google.com/spreadsheets/d/12RxCea4e5ggM7QGn1XE3FbLQa_-QbCNdBi90OdPjRqg"", ""'Plan de Compras'!D4:Q""), 14, 0), """")"),"JESSICA") -> JESSICA | Z21: =IFERROR(__xludf.DUMMYFUNCTION("IFERROR(VLOOKUP(G21,IMPORTRANGE(""https://docs.google.com/spreadsheets/d/12RxCea4e5ggM7QGn1XE3FbLQa_-QbCNdBi90OdPjRqg"", ""'Plan de Compras'!D4:Q""), 4, 0), """")"),"AMOLADORA") -> AMOLADORA | AA21: =IF(H21=Z21,"TRUE", "FALSE") -> TRUE | AB21: =IFERROR(__xludf.DUMMYFUNCTION("IFERROR(IF(OR(C21=TRUE,C21=""""),VLOOKUP(G21,IMPORTRANGE(""https://docs.google.com/spreadsheets/d/1z9A1Wq-kKrhRNG5RS2a2fKpY1wIhSVz2ZNmP2mOl588/edit?usp=sharing"",""REQ VF!E4:H""),4,0),""NO APLICA""),""GENERAR REQ"")"),"GENERAR REQ") -> GENERAR REQ | AC21: =IFERROR(__xludf.DUMMYFUNCTION("IFERROR(QUERY(IMPORTRANGE(""https://docs.google.com/spreadsheets/d/1z9A1Wq-kKrhRNG5RS2a2fKpY1wIhSVz2ZNmP2mOl588/edit?usp=sharing"",""REQ VF!E4:Q""),""SELECT Col10, Col11, Col12 WHERE Col1 = '""&G21&""'"",0),""NO APLICA"")"),"NO APLICA") -> NO APLICA | AF21: C
C22: TRUE | D22: ACCESORIO | E22: EQUIPOS | F22: ESP-103 | G22: ESP-103.1 | H22: DISCO DIAMANTADO 125 MM (5 UND) | I22: =$I$21*5 -> 20 | J22: =IFERROR(__xludf.DUMMYFUNCTION("VLOOKUP(G22,IMPORTRANGE(""https://docs.google.com/spreadsheets/d/12RxCea4e5ggM7QGn1XE3FbLQa_-QbCNdBi90OdPjRqg/edit?gid=1692403370#gid=1692403370"", ""'Plan de Compras'!D4:2432""), 8,0)"),20.0) -> 20 | K22: =IF( C22=TRUE, IF(I22=J22,"SI","NO"), "-") -> SI | N22: DISCO DIAMANTADO DE 125 mm | Q22: https://www.maqcenter.pe/product/vaso-diamantado-para-concreto-segmentado-125-x-22-23mm-bosch-2608-601-762 | S22: TRUE | T22: BOSCH | U22: 2608.601.762-000 | V22: https://drive.google.com/file/d/1V2qh049uZB1V53EYh7eIWzBpKuZA9Hec/view?usp=sharing | W22: =IFERROR(__xludf.DUMMYFUNCTION("IFERROR(VLOOKUP(G22,IMPORTRANGE(""https://docs.google.com/spreadsheets/d/12RxCea4e5ggM7QGn1XE3FbLQa_-QbCNdBi90OdPjRqg"", ""'Plan de Compras'!D4:Q""), 12, 0), ""NO ESTÁ EN REQ"")"),"Simple") -> Simple | X22: =IFERROR(__xludf.DUMMYFUNCTION("IFERROR(VLOOKUP(G22,IMPORTRANGE(""https://docs.google.com/spreadsheets/d/12RxCea4e5ggM7QGn1XE3FbLQa_-QbCNdBi90OdPjRqg"", ""'Plan de Compras'!D4:Q""), 13, 0), """")"),"NACIONAL") -> NACIONAL | Y22: =IFERROR(__xludf.DUMMYFUNCTION("IFERROR(VLOOKUP(G22,IMPORTRANGE(""https://docs.google.com/spreadsheets/d/12RxCea4e5ggM7QGn1XE3FbLQa_-QbCNdBi90OdPjRqg"", ""'Plan de Compras'!D4:Q""), 14, 0), """")"),"JESSICA") -> JESSICA | Z22: =IFERROR(__xludf.DUMMYFUNCTION("IFERROR(VLOOKUP(G22,IMPORTRANGE(""https://docs.google.com/spreadsheets/d/12RxCea4e5ggM7QGn1XE3FbLQa_-QbCNdBi90OdPjRqg"", ""'Plan de Compras'!D4:Q""), 4, 0), """")"),"DISCO DIAMANTADO 125 MM (5 UND)") -> DISCO DIAMANTADO 125 MM (5 UND) | AA22: =IF(H22=Z22,"TRUE", "FALSE") -> TRUE | AB22: =IFERROR(__xludf.DUMMYFUNCTION("IFERROR(IF(OR(C22=TRUE,C22=""""),VLOOKUP(G22,IMPORTRANGE(""https://docs.google.com/spreadsheets/d/1z9A1Wq-kKrhRNG5RS2a2fKpY1wIhSVz2ZNmP2mOl588/edit?usp=sharing"",""REQ VF!E4:H""),4,0),""NO APLICA""),""GENERAR REQ"")"),"GENERAR REQ") -> GENERAR REQ | AC22: =IFERROR(__xludf.DUMMYFUNCTION("IFERROR(QUERY(IMPORTRANGE(""https://docs.google.com/spreadsheets/d/1z9A1Wq-kKrhRNG5RS2a2fKpY1wIhSVz2ZNmP2mOl588/edit?usp=sharing"",""REQ VF!E4:Q""),""SELECT Col10, Col11, Col12 WHERE Col1 = '""&G22&""'"",0),""NO APLICA"")"),"NO APLICA") -> NO APLICA
C23: TRUE | D23: ACCESORIO | E23: EQUIPOS | F23: ESP-103 | G23: ESP-103.2 | H23: FUNDA DE POLIAMIDA (1 UND) | I23: 4 | J23: =IFERROR(__xludf.DUMMYFUNCTION("VLOOKUP(G23,IMPORTRANGE(""https://docs.google.com/spreadsheets/d/12RxCea4e5ggM7QGn1XE3FbLQa_-QbCNdBi90OdPjRqg/edit?gid=1692403370#gid=1692403370"", ""'Plan de Compras'!D4:2432""), 8,0)"),4.0) -> 4 | K23: =IF( C23=TRUE, IF(I23=J23,"SI","NO"), "-") -> SI | S23: TRUE | T23: GENERICO | U23: FUNDAS DE POLIAMIDAS 35.2 CM x 31.5 CM x 15.8 CM PARA AMOLADORA | W23: =IFERROR(__xludf.DUMMYFUNCTION("IFERROR(VLOOKUP(G23,IMPORTRANGE(""https://docs.google.com/spreadsheets/d/12RxCea4e5ggM7QGn1XE3FbLQa_-QbCNdBi90OdPjRqg"", ""'Plan de Compras'!D4:Q""), 12, 0), ""NO ESTÁ EN REQ"")"),"Simple") -> Simple | X23: =IFERROR(__xludf.DUMMYFUNCTION("IFERROR(VLOOKUP(G23,IMPORTRANGE(""https://docs.google.com/spreadsheets/d/12RxCea4e5ggM7QGn1XE3FbLQa_-QbCNdBi90OdPjRqg"", ""'Plan de Compras'!D4:Q""), 13, 0), """")"),"NACIONAL") -> NACIONAL | Y23: =IFERROR(__xludf.DUMMYFUNCTION("IFERROR(VLOOKUP(G23,IMPORTRANGE(""https://docs.google.com/spreadsheets/d/12RxCea4e5ggM7QGn1XE3FbLQa_-QbCNdBi90OdPjRqg"", ""'Plan de Compras'!D4:Q""), 14, 0), """")"),"ANGIE") -> ANGIE | Z23: =IFERROR(__xludf.DUMMYFUNCTION("IFERROR(VLOOKUP(G23,IMPORTRANGE(""https://docs.google.com/spreadsheets/d/12RxCea4e5ggM7QGn1XE3FbLQa_-QbCNdBi90OdPjRqg"", ""'Plan de Compras'!D4:Q""), 4, 0), """")"),"FUNDA DE POLIAMIDA (1 UND)") -> FUNDA DE POLIAMIDA (1 UND) | AB23: =IFERROR(__xludf.DUMMYFUNCTION("IFERROR(IF(OR(C23=TRUE,C23=""""),VLOOKUP(G23,IMPORTRANGE(""https://docs.google.com/spreadsheets/d/1z9A1Wq-kKrhRNG5RS2a2fKpY1wIhSVz2ZNmP2mOl588/edit?usp=sharing"",""REQ VF!E4:H""),4,0),""NO APLICA""),""GENERAR REQ"")"),"GENERAR REQ") -> GENERAR REQ | AC23: =IFERROR(__xludf.DUMMYFUNCTION("IFERROR(QUERY(IMPORTRANGE(""https://docs.google.com/spreadsheets/d/1z9A1Wq-kKrhRNG5RS2a2fKpY1wIhSVz2ZNmP2mOl588/edit?usp=sharing"",""REQ VF!E4:Q""),""SELECT Col10, Col11, Col12 WHERE Col1 = '""&G23&""'"",0),""NO APLICA"")"),"NO APLICA") -> NO APLICA
C24: FALSE | D24: ACCESORIO | E24: EQUIPOS | F24: ESP-103 | G24: ESP-103.3 | H24: MANUAL DE INSTRUCCIONES (1 UND) | I24: 0 | J24: =IFERROR(__xludf.DUMMYFUNCTION("VLOOKUP(G24,IMPORTRANGE(""https://docs.google.com/spreadsheets/d/12RxCea4e5ggM7QGn1XE3FbLQa_-QbCNdBi90OdPjRqg/edit?gid=1692403370#gid=1692403370"", ""'Plan de Compras'!D4:2432""), 8,0)"),"#N/A") -> #N/A | K24: =IF( C24=TRUE, IF(I24=J24,"SI","NO"), "-") -> - | S24: TRUE | T24: BOSCH | U24: INCLUÍDO | W24: =IFERROR(__xludf.DUMMYFUNCTION("IFERROR(VLOOKUP(G24,IMPORTRANGE(""https://docs.google.com/spreadsheets/d/12RxCea4e5ggM7QGn1XE3FbLQa_-QbCNdBi90OdPjRqg"", ""'Plan de Compras'!D4:Q""), 12, 0), ""NO ESTÁ EN REQ"")"),"NO ESTÁ EN REQ") -> NO ESTÁ EN REQ | X24: =IFERROR(__xludf.DUMMYFUNCTION("IFERROR(VLOOKUP(G24,IMPORTRANGE(""https://docs.google.com/spreadsheets/d/12RxCea4e5ggM7QGn1XE3FbLQa_-QbCNdBi90OdPjRqg"", ""'Plan de Compras'!D4:Q""), 13, 0), """")"),"") | Y24: =IFERROR(__xludf.DUMMYFUNCTION("IFERROR(VLOOKUP(G24,IMPORTRANGE(""https://docs.google.com/spreadsheets/d/12RxCea4e5ggM7QGn1XE3FbLQa_-QbCNdBi90OdPjRqg"", ""'Plan de Compras'!D4:Q""), 14, 0), """")"),"") | Z24: =IFERROR(__xludf.DUMMYFUNCTION("IFERROR(VLOOKUP(G24,IMPORTRANGE(""https://docs.google.com/spreadsheets/d/12RxCea4e5ggM7QGn1XE3FbLQa_-QbCNdBi90OdPjRqg"", ""'Plan de Compras'!D4:Q""), 4, 0), """")"),"") | AB24: =IFERROR(__xludf.DUMMYFUNCTION("IFERROR(IF(OR(C24=TRUE,C24=""""),VLOOKUP(G24,IMPORTRANGE(""https://docs.google.com/spreadsheets/d/1z9A1Wq-kKrhRNG5RS2a2fKpY1wIhSVz2ZNmP2mOl588/edit?usp=sharing"",""REQ VF!E4:H""),4,0),""NO APLICA""),""GENERAR REQ"")"),"NO APLICA") -> NO APLICA | AC24: =IFERROR(__xludf.DUMMYFUNCTION("IFERROR(QUERY(IMPORTRANGE(""https://docs.google.com/spreadsheets/d/1z9A1Wq-kKrhRNG5RS2a2fKpY1wIhSVz2ZNmP2mOl588/edit?usp=sharing"",""REQ VF!E4:Q""),""SELECT Col10, Col11, Col12 WHERE Col1 = '""&G24&""'"",0),""NO APLICA"")"),"NO APLICA") -> NO APLICA
A25: 9 | B25: TRUE | C25: TRUE | D25: BIEN | E25: EQUIPOS | F25: ESP-104 | G25: ESP-104 | H25: ANALIZADOR DE ESPECTRO | I25: =SUMIFS('Hoja 10'!$O:$O,'Hoja 10'!$F:$F,$G25) -> 4 | J25: =IFERROR(__xludf.DUMMYFUNCTION("VLOOKUP(G25,IMPORTRANGE(""https://docs.google.com/spreadsheets/d/12RxCea4e5ggM7QGn1XE3FbLQa_-QbCNdBi90OdPjRqg/edit?gid=1692403370#gid=1692403370"", ""'Plan de Compras'!D4:2432""), 8,0)"),4.0) -> 4 | K25: =IF( C25=TRUE, IF(I25=J25,"SI","NO"), "-") -> SI | L25: ELECTRÓNICA | M25: 11 Taller_Electrónica_Firmado.pdf | O25: =VLOOKUP($G25,'Hoja 10'!$F$4:$AA478, 19,0) -> Gwinstek | P25: =VLOOKUP($G25,'Hoja 10'!$F$4:$AA478, 20,0) -> GSP-730 | Q25: =VLOOKUP($G25,'Hoja 10'!$F$4:$AA478, 21,0) -> https://www.gwinstek.com/en-US/products/detail/GSP-730 | R25: ESP-104 ANALIZADOR DE ESPECTRO - CET | S25: TRUE | T25: =IFERROR(__xludf.DUMMYFUNCTION(" IF ( VLOOKUP($G25,IMPORTRANGE(""https://docs.google.com/spreadsheets/d/1Gpl6jkTg7sL4VDNimUm3S9Vi1i95esohXCF3wuKOE8c"", ""'CONSOLIDADO'!G5:AB""), 10, 0) <> 0, IFERROR(VLOOKUP($G25,IMPORTRANGE(""https://docs.google.com/spreadsheets/d/1Gpl6jkTg7sL4VDNimUm3"&"S9Vi1i95esohXCF3wuKOE8c"", ""'CONSOLIDADO'!G5:AB""), 17, 0), ""-""), """" )"),"GW INSTEK") -> GW INSTEK | U25: =IFERROR(__xludf.DUMMYFUNCTION(" IF ( VLOOKUP($G25,IMPORTRANGE(""https://docs.google.com/spreadsheets/d/1Gpl6jkTg7sL4VDNimUm3S9Vi1i95esohXCF3wuKOE8c"", ""'CONSOLIDADO'!G5:AB""), 10, 0) <> 0, IFERROR(VLOOKUP($G25,IMPORTRANGE(""https://docs.google.com/spreadsheets/d/1Gpl6jkTg7sL4VDNimUm3"&"S9Vi1i95esohXCF3wuKOE8c"", ""'CONSOLIDADO'!G5:AB""), 18, 0), ""-""), """" )"),"GSP-730") -> GSP-730 | V25: =IFERROR(__xludf.DUMMYFUNCTION(" IF ( VLOOKUP($G25,IMPORTRANGE(""https://docs.google.com/spreadsheets/d/1Gpl6jkTg7sL4VDNimUm3S9Vi1i95esohXCF3wuKOE8c"", ""'CONSOLIDADO'!G5:AB""), 10, 0) <> 0, IFERROR(VLOOKUP($G25,IMPORTRANGE(""https://docs.google.com/spreadsheets/d/1Gpl6jkTg7sL4VDNimUm3"&"S9Vi1i95esohXCF3wuKOE8c"", ""'CONSOLIDADO'!G5:AB""), 19, 0), ""-""), """" )"),"https://www.gwinstek.com/en-US/products/detail/GSP-730") -> https://www.gwinstek.com/en-US/products/detail/GSP-730 | W25: =IFERROR(__xludf.DUMMYFUNCTION("IFERROR(VLOOKUP(G25,IMPORTRANGE(""https://docs.google.com/spreadsheets/d/12RxCea4e5ggM7QGn1XE3FbLQa_-QbCNdBi90OdPjRqg"", ""'Plan de Compras'!D4:Q""), 12, 0), ""NO ESTÁ EN REQ"")"),"Técnica") -> Técnica | X25: =IFERROR(__xludf.DUMMYFUNCTION("IFERROR(VLOOKUP(G25,IMPORTRANGE(""https://docs.google.com/spreadsheets/d/12RxCea4e5ggM7QGn1XE3FbLQa_-QbCNdBi90OdPjRqg"", ""'Plan de Compras'!D4:Q""), 13, 0), """")"),"INTERNACIONAL") -> INTERNACIONAL | Y25: =IFERROR(__xludf.DUMMYFUNCTION("IFERROR(VLOOKUP(G25,IMPORTRANGE(""https://docs.google.com/spreadsheets/d/12RxCea4e5ggM7QGn1XE3FbLQa_-QbCNdBi90OdPjRqg"", ""'Plan de Compras'!D4:Q""), 14, 0), """")"),"GEYDI") -> GEYDI | Z25: =IFERROR(__xludf.DUMMYFUNCTION("IFERROR(VLOOKUP(G25,IMPORTRANGE(""https://docs.google.com/spreadsheets/d/12RxCea4e5ggM7QGn1XE3FbLQa_-QbCNdBi90OdPjRqg"", ""'Plan de Compras'!D4:Q""), 4, 0), """")"),"ANALIZADOR DE ESPECTRO") -> ANALIZADOR DE ESPECTRO | AA25: =IF(H25=Z25,"TRUE", "FALSE") -> TRUE | AB25: =IFERROR(__xludf.DUMMYFUNCTION("IFERROR(IF(OR(C25=TRUE,C25=""""),VLOOKUP(G25,IMPORTRANGE(""https://docs.google.com/spreadsheets/d/1z9A1Wq-kKrhRNG5RS2a2fKpY1wIhSVz2ZNmP2mOl588/edit?usp=sharing"",""REQ VF!E4:H""),4,0),""NO APLICA""),""GENERAR REQ"")"),"GENERAR REQ") -> GENERAR REQ | AC25: =IFERROR(__xludf.DUMMYFUNCTION("IFERROR(QUERY(IMPORTRANGE(""https://docs.google.com/spreadsheets/d/1z9A1Wq-kKrhRNG5RS2a2fKpY1wIhSVz2ZNmP2mOl588/edit?usp=sharing"",""REQ VF!E4:Q""),""SELECT Col10, Col11, Col12 WHERE Col1 = '""&G25&""'"",0),""NO APLICA"")"),"NO APLICA") -> NO APLICA | AF25: C
A26: 10 | B26: TRUE | C26: TRUE | D26: BIEN | E26: EQUIPOS | F26: ESP-105 | G26: ESP-105 | H26: ANALIZADOR DE GAS DE ESCAPE | I26: =SUMIFS('Hoja 10'!$O:$O,'Hoja 10'!$F:$F,$G26) -> 3 | J26: =IFERROR(__xludf.DUMMYFUNCTION("VLOOKUP(G26,IMPORTRANGE(""https://docs.google.com/spreadsheets/d/12RxCea4e5ggM7QGn1XE3FbLQa_-QbCNdBi90OdPjRqg/edit?gid=1692403370#gid=1692403370"", ""'Plan de Compras'!D4:2432""), 8,0)"),3.0) -> 3 | K26: =IF( C26=TRUE, IF(I26=J26,"SI","NO"), "-") -> SI | L26: MECÁNICA AUTOMOTRÍZ | M26: 1 Taller_Mecanica_Automotriz_Firmado.pdf | O26: =VLOOKUP($G26,'Hoja 10'!$F$4:$AA478, 19,0) -> BRAIN BEE | P26: =VLOOKUP($G26,'Hoja 10'!$F$4:$AA478, 20,0) -> AGS-688 | Q26: =VLOOKUP($G26,'Hoja 10'!$F$4:$AA478, 21,0) -> google.com/search?q=BRAIN+BEE+AGS-688&rlz=1C1CHBD_esPE1168PE1168&oq=BRAIN+BEE+AGS-688&gs_lcrp=EgZjaHJvbWUyBggAEEUYOTIICAEQABgWGB4yCAgCEAAYFhgeMggIAxAAGBYYHjIICAQQABgWGB4yBggFEEUYPDIGCAYQRRg8MgYIBxBFGD3SAQgxMzcwajBqN6gCALACAA&sourceid=chrome&ie=UTF-8 | R26: ESP-105 ANALIZADOR DE GAS DE ESCAPE - CET | S26: TRUE | T26: =IFERROR(__xludf.DUMMYFUNCTION(" IF ( VLOOKUP($G26,IMPORTRANGE(""https://docs.google.com/spreadsheets/d/1Gpl6jkTg7sL4VDNimUm3S9Vi1i95esohXCF3wuKOE8c"", ""'CONSOLIDADO'!G5:AB""), 10, 0) <> 0, IFERROR(VLOOKUP($G26,IMPORTRANGE(""https://docs.google.com/spreadsheets/d/1Gpl6jkTg7sL4VDNimUm3"&"S9Vi1i95esohXCF3wuKOE8c"", ""'CONSOLIDADO'!G5:AB""), 17, 0), ""-""), """" )"),"MAHLE") -> MAHLE | U26: =IFERROR(__xludf.DUMMYFUNCTION(" IF ( VLOOKUP($G26,IMPORTRANGE(""https://docs.google.com/spreadsheets/d/1Gpl6jkTg7sL4VDNimUm3S9Vi1i95esohXCF3wuKOE8c"", ""'CONSOLIDADO'!G5:AB""), 10, 0) <> 0, IFERROR(VLOOKUP($G26,IMPORTRANGE(""https://docs.google.com/spreadsheets/d/1Gpl6jkTg7sL4VDNimUm3"&"S9Vi1i95esohXCF3wuKOE8c"", ""'CONSOLIDADO'!G5:AB""), 18, 0), ""-""), """" )"),"BMU 688") -> BMU 688 | V26: =IFERROR(__xludf.DUMMYFUNCTION(" IF ( VLOOKUP($G26,IMPORTRANGE(""https://docs.google.com/spreadsheets/d/1Gpl6jkTg7sL4VDNimUm3S9Vi1i95esohXCF3wuKOE8c"", ""'CONSOLIDADO'!G5:AB""), 10, 0) <> 0, IFERROR(VLOOKUP($G26,IMPORTRANGE(""https://docs.google.com/spreadsheets/d/1Gpl6jkTg7sL4VDNimUm3"&"S9Vi1i95esohXCF3wuKOE8c"", ""'CONSOLIDADO'!G5:AB""), 19, 0), ""-""), """" )"),"https://www.servicesolutions.mahle.com/eu/es/product-lines/emissionpro/bmu-688/") -> https://www.servicesolutions.mahle.com/eu/es/product-lines/emissionpro/bmu-688/ | W26: =IFERROR(__xludf.DUMMYFUNCTION("IFERROR(VLOOKUP(G26,IMPORTRANGE(""https://docs.google.com/spreadsheets/d/12RxCea4e5ggM7QGn1XE3FbLQa_-QbCNdBi90OdPjRqg"", ""'Plan de Compras'!D4:Q""), 12, 0), ""NO ESTÁ EN REQ"")"),"Técnica") -> Técnica | X26: =IFERROR(__xludf.DUMMYFUNCTION("IFERROR(VLOOKUP(G26,IMPORTRANGE(""https://docs.google.com/spreadsheets/d/12RxCea4e5ggM7QGn1XE3FbLQa_-QbCNdBi90OdPjRqg"", ""'Plan de Compras'!D4:Q""), 13, 0), """")"),"INTERNACIONAL") -> INTERNACIONAL | Y26: =IFERROR(__xludf.DUMMYFUNCTION("IFERROR(VLOOKUP(G26,IMPORTRANGE(""https://docs.google.com/spreadsheets/d/12RxCea4e5ggM7QGn1XE3FbLQa_-QbCNdBi90OdPjRqg"", ""'Plan de Compras'!D4:Q""), 14, 0), """")"),"VICTOR") -> VICTOR | Z26: =IFERROR(__xludf.DUMMYFUNCTION("IFERROR(VLOOKUP(G26,IMPORTRANGE(""https://docs.google.com/spreadsheets/d/12RxCea4e5ggM7QGn1XE3FbLQa_-QbCNdBi90OdPjRqg"", ""'Plan de Compras'!D4:Q""), 4, 0), """")"),"ANALIZADOR DE GAS DE ESCAPE") -> ANALIZADOR DE GAS DE ESCAPE | AA26: =IF(H26=Z26,"TRUE", "FALSE") -> TRUE | AB26: =IFERROR(__xludf.DUMMYFUNCTION("IFERROR(IF(OR(C26=TRUE,C26=""""),VLOOKUP(G26,IMPORTRANGE(""https://docs.google.com/spreadsheets/d/1z9A1Wq-kKrhRNG5RS2a2fKpY1wIhSVz2ZNmP2mOl588/edit?usp=sharing"",""REQ VF!E4:H""),4,0),""NO APLICA""),""GENERAR REQ"")"),"GENERAR REQ") -> GENERAR REQ | AC26: =IFERROR(__xludf.DUMMYFUNCTION("IFERROR(QUERY(IMPORTRANGE(""https://docs.google.com/spreadsheets/d/1z9A1Wq-kKrhRNG5RS2a2fKpY1wIhSVz2ZNmP2mOl588/edit?usp=sharing"",""REQ VF!E4:Q""),""SELECT Col10, Col11, Col12 WHERE Col1 = '""&G26&""'"",0),""NO APLICA"")"),"NO APLICA") -> NO APLICA | AF26: C
C27: TRUE | D27: ACCESORIO | E27: EQUIPOS | F27: ESP-105 | G27: ESP-105.1 | H27: CAJA DE ACUMULACIÓN DE GAS (1 UND) | I27: =$I$26 -> 3 | J27: =IFERROR(__xludf.DUMMYFUNCTION("VLOOKUP(G27,IMPORTRANGE(""https://docs.google.com/spreadsheets/d/12RxCea4e5ggM7QGn1XE3FbLQa_-QbCNdBi90OdPjRqg/edit?gid=1692403370#gid=1692403370"", ""'Plan de Compras'!D4:2432""), 8,0)"),3.0) -> 3 | K27: =IF( C27=TRUE, IF(I27=J27,"SI","NO"), "-") -> SI | S27: TRUE | T27: TEDLAR | U27: 1L | W27: =IFERROR(__xludf.DUMMYFUNCTION("IFERROR(VLOOKUP(G27,IMPORTRANGE(""https://docs.google.com/spreadsheets/d/12RxCea4e5ggM7QGn1XE3FbLQa_-QbCNdBi90OdPjRqg"", ""'Plan de Compras'!D4:Q""), 12, 0), ""NO ESTÁ EN REQ"")"),"Técnica") -> Técnica | X27: =IFERROR(__xludf.DUMMYFUNCTION("IFERROR(VLOOKUP(G27,IMPORTRANGE(""https://docs.google.com/spreadsheets/d/12RxCea4e5ggM7QGn1XE3FbLQa_-QbCNdBi90OdPjRqg"", ""'Plan de Compras'!D4:Q""), 13, 0), """")"),"INTERNACIONAL") -> INTERNACIONAL | Y27: =IFERROR(__xludf.DUMMYFUNCTION("IFERROR(VLOOKUP(G27,IMPORTRANGE(""https://docs.google.com/spreadsheets/d/12RxCea4e5ggM7QGn1XE3FbLQa_-QbCNdBi90OdPjRqg"", ""'Plan de Compras'!D4:Q""), 14, 0), """")"),"GEYDI") -> GEYDI | Z27: =IFERROR(__xludf.DUMMYFUNCTION("IFERROR(VLOOKUP(G27,IMPORTRANGE(""https://docs.google.com/spreadsheets/d/12RxCea4e5ggM7QGn1XE3FbLQa_-QbCNdBi90OdPjRqg"", ""'Plan de Compras'!D4:Q""), 4, 0), """")"),"CAJA DE ACUMULACIÓN DE GAS (1 UND)") -> CAJA DE ACUMULACIÓN DE GAS (1 UND) | AA27: =IF(H27=Z27,"TRUE", "FALSE") -> TRUE | AB27: =IFERROR(__xludf.DUMMYFUNCTION("IFERROR(IF(OR(C27=TRUE,C27=""""),VLOOKUP(G27,IMPORTRANGE(""https://docs.google.com/spreadsheets/d/1z9A1Wq-kKrhRNG5RS2a2fKpY1wIhSVz2ZNmP2mOl588/edit?usp=sharing"",""REQ VF!E4:H""),4,0),""NO APLICA""),""GENERAR REQ"")"),"GENERAR REQ") -> GENERAR REQ | AC27: =IFERROR(__xludf.DUMMYFUNCTION("IFERROR(QUERY(IMPORTRANGE(""https://docs.google.com/spreadsheets/d/1z9A1Wq-kKrhRNG5RS2a2fKpY1wIhSVz2ZNmP2mOl588/edit?usp=sharing"",""REQ VF!E4:Q""),""SELECT Col10, Col11, Col12 WHERE Col1 = '""&G27&""'"",0),""NO APLICA"")"),"NO APLICA") -> NO APLICA
C28: FALSE | D28: ACCESORIO | E28: EQUIPOS | F28: ESP-105 | G28: ESP-105.2 | H28: BOMBA DE PULSOS (1 UND) | I28: 0 | J28: =IFERROR(__xludf.DUMMYFUNCTION("VLOOKUP(G28,IMPORTRANGE(""https://docs.google.com/spreadsheets/d/12RxCea4e5ggM7QGn1XE3FbLQa_-QbCNdBi90OdPjRqg/edit?gid=1692403370#gid=1692403370"", ""'Plan de Compras'!D4:2432""), 8,0)"),"#N/A") -> #N/A | K28: =IF( C28=TRUE, IF(I28=J28,"SI","NO"), "-") -> - | S28: TRUE | T28: MAHLE | U28: INCLUÍDO | W28: =IFERROR(__xludf.DUMMYFUNCTION("IFERROR(VLOOKUP(G28,IMPORTRANGE(""https://docs.google.com/spreadsheets/d/12RxCea4e5ggM7QGn1XE3FbLQa_-QbCNdBi90OdPjRqg"", ""'Plan de Compras'!D4:Q""), 12, 0), ""NO ESTÁ EN REQ"")"),"NO ESTÁ EN REQ") -> NO ESTÁ EN REQ | X28: =IFERROR(__xludf.DUMMYFUNCTION("IFERROR(VLOOKUP(G28,IMPORTRANGE(""https://docs.google.com/spreadsheets/d/12RxCea4e5ggM7QGn1XE3FbLQa_-QbCNdBi90OdPjRqg"", ""'Plan de Compras'!D4:Q""), 13, 0), """")"),"") | Y28: =IFERROR(__xludf.DUMMYFUNCTION("IFERROR(VLOOKUP(G28,IMPORTRANGE(""https://docs.google.com/spreadsheets/d/12RxCea4e5ggM7QGn1XE3FbLQa_-QbCNdBi90OdPjRqg"", ""'Plan de Compras'!D4:Q""), 14, 0), """")"),"") | Z28: =IFERROR(__xludf.DUMMYFUNCTION("IFERROR(VLOOKUP(G28,IMPORTRANGE(""https://docs.google.com/spreadsheets/d/12RxCea4e5ggM7QGn1XE3FbLQa_-QbCNdBi90OdPjRqg"", ""'Plan de Compras'!D4:Q""), 4, 0), """")"),"") | AB28: =IFERROR(__xludf.DUMMYFUNCTION("IFERROR(IF(OR(C28=TRUE,C28=""""),VLOOKUP(G28,IMPORTRANGE(""https://docs.google.com/spreadsheets/d/1z9A1Wq-kKrhRNG5RS2a2fKpY1wIhSVz2ZNmP2mOl588/edit?usp=sharing"",""REQ VF!E4:H""),4,0),""NO APLICA""),""GENERAR REQ"")"),"NO APLICA") -> NO APLICA | AC28: =IFERROR(__xludf.DUMMYFUNCTION("IFERROR(QUERY(IMPORTRANGE(""https://docs.google.com/spreadsheets/d/1z9A1Wq-kKrhRNG5RS2a2fKpY1wIhSVz2ZNmP2mOl588/edit?usp=sharing"",""REQ VF!E4:Q""),""SELECT Col10, Col11, Col12 WHERE Col1 = '""&G28&""'"",0),""NO APLICA"")"),"NO APLICA") -> NO APLICA
C29: FALSE | D29: ACCESORIO | E29: EQUIPOS | F29: ESP-105 | G29: ESP-105.3 | H29: DECANTADOR DE AGUA (1 UND) | I29: 0 | J29: =IFERROR(__xludf.DUMMYFUNCTION("VLOOKUP(G29,IMPORTRANGE(""https://docs.google.com/spreadsheets/d/12RxCea4e5ggM7QGn1XE3FbLQa_-QbCNdBi90OdPjRqg/edit?gid=1692403370#gid=1692403370"", ""'Plan de Compras'!D4:2432""), 8,0)"),"#N/A") -> #N/A | K29: =IF( C29=TRUE, IF(I29=J29,"SI","NO"), "-") -> - | S29: TRUE | T29: MAHLE | U29: INCLUÍDO | W29: =IFERROR(__xludf.DUMMYFUNCTION("IFERROR(VLOOKUP(G29,IMPORTRANGE(""https://docs.google.com/spreadsheets/d/12RxCea4e5ggM7QGn1XE3FbLQa_-QbCNdBi90OdPjRqg"", ""'Plan de Compras'!D4:Q""), 12, 0), ""NO ESTÁ EN REQ"")"),"NO ESTÁ EN REQ") -> NO ESTÁ EN REQ | X29: =IFERROR(__xludf.DUMMYFUNCTION("IFERROR(VLOOKUP(G29,IMPORTRANGE(""https://docs.google.com/spreadsheets/d/12RxCea4e5ggM7QGn1XE3FbLQa_-QbCNdBi90OdPjRqg"", ""'Plan de Compras'!D4:Q""), 13, 0), """")"),"") | Y29: =IFERROR(__xludf.DUMMYFUNCTION("IFERROR(VLOOKUP(G29,IMPORTRANGE(""https://docs.google.com/spreadsheets/d/12RxCea4e5ggM7QGn1XE3FbLQa_-QbCNdBi90OdPjRqg"", ""'Plan de Compras'!D4:Q""), 14, 0), """")"),"") | Z29: =IFERROR(__xludf.DUMMYFUNCTION("IFERROR(VLOOKUP(G29,IMPORTRANGE(""https://docs.google.com/spreadsheets/d/12RxCea4e5ggM7QGn1XE3FbLQa_-QbCNdBi90OdPjRqg"", ""'Plan de Compras'!D4:Q""), 4, 0), """")"),"") | AB29: =IFERROR(__xludf.DUMMYFUNCTION("IFERROR(IF(OR(C29=TRUE,C29=""""),VLOOKUP(G29,IMPORTRANGE(""https://docs.google.com/spreadsheets/d/1z9A1Wq-kKrhRNG5RS2a2fKpY1wIhSVz2ZNmP2mOl588/edit?usp=sharing"",""REQ VF!E4:H""),4,0),""NO APLICA""),""GENERAR REQ"")"),"NO APLICA") -> NO APLICA | AC29: =IFERROR(__xludf.DUMMYFUNCTION("IFERROR(QUERY(IMPORTRANGE(""https://docs.google.com/spreadsheets/d/1z9A1Wq-kKrhRNG5RS2a2fKpY1wIhSVz2ZNmP2mOl588/edit?usp=sharing"",""REQ VF!E4:Q""),""SELECT Col10, Col11, Col12 WHERE Col1 = '""&G29&""'"",0),""NO APLICA"")"),"NO APLICA") -> NO APLICA
C30: FALSE | D30: ACCESORIO | E30: EQUIPOS | F30: ESP-105 | G30: ESP-105.4 | H30: SONDA DE PRUEBA CON MUELLES DE FIJACIÓN (1 UND) | I30: 0 | J30: =IFERROR(__xludf.DUMMYFUNCTION("VLOOKUP(G30,IMPORTRANGE(""https://docs.google.com/spreadsheets/d/12RxCea4e5ggM7QGn1XE3FbLQa_-QbCNdBi90OdPjRqg/edit?gid=1692403370#gid=1692403370"", ""'Plan de Compras'!D4:2432""), 8,0)"),"#N/A") -> #N/A | K30: =IF( C30=TRUE, IF(I30=J30,"SI","NO"), "-") -> - | S30: TRUE | T30: MAHLE | U30: INCLUÍDO | W30: =IFERROR(__xludf.DUMMYFUNCTION("IFERROR(VLOOKUP(G30,IMPORTRANGE(""https://docs.google.com/spreadsheets/d/12RxCea4e5ggM7QGn1XE3FbLQa_-QbCNdBi90OdPjRqg"", ""'Plan de Compras'!D4:Q""), 12, 0), ""NO ESTÁ EN REQ"")"),"NO ESTÁ EN REQ") -> NO ESTÁ EN REQ | X30: =IFERROR(__xludf.DUMMYFUNCTION("IFERROR(VLOOKUP(G30,IMPORTRANGE(""https://docs.google.com/spreadsheets/d/12RxCea4e5ggM7QGn1XE3FbLQa_-QbCNdBi90OdPjRqg"", ""'Plan de Compras'!D4:Q""), 13, 0), """")"),"") | Y30: =IFERROR(__xludf.DUMMYFUNCTION("IFERROR(VLOOKUP(G30,IMPORTRANGE(""https://docs.google.com/spreadsheets/d/12RxCea4e5ggM7QGn1XE3FbLQa_-QbCNdBi90OdPjRqg"", ""'Plan de Compras'!D4:Q""), 14, 0), """")"),"") | Z30: =IFERROR(__xludf.DUMMYFUNCTION("IFERROR(VLOOKUP(G30,IMPORTRANGE(""https://docs.google.com/spreadsheets/d/12RxCea4e5ggM7QGn1XE3FbLQa_-QbCNdBi90OdPjRqg"", ""'Plan de Compras'!D4:Q""), 4, 0), """")"),"") | AB30: =IFERROR(__xludf.DUMMYFUNCTION("IFERROR(IF(OR(C30=TRUE,C30=""""),VLOOKUP(G30,IMPORTRANGE(""https://docs.google.com/spreadsheets/d/1z9A1Wq-kKrhRNG5RS2a2fKpY1wIhSVz2ZNmP2mOl588/edit?usp=sharing"",""REQ VF!E4:H""),4,0),""NO APLICA""),""GENERAR REQ"")"),"NO APLICA") -> NO APLICA | AC30: =IFERROR(__xludf.DUMMYFUNCTION("IFERROR(QUERY(IMPORTRANGE(""https://docs.google.com/spreadsheets/d/1z9A1Wq-kKrhRNG5RS2a2fKpY1wIhSVz2ZNmP2mOl588/edit?usp=sharing"",""REQ VF!E4:Q""),""SELECT Col10, Col11, Col12 WHERE Col1 = '""&G30&""'"",0),""NO APLICA"")"),"NO APLICA") -> NO APLICA
C31: TRUE | D31: ACCESORIO | E31: EQUIPOS | F31: ESP-105 | G31: ESP-105.5 | H31: TUBOS FLEXIBLES (3 UND) | I31: =3*I26 -> 9 | J31: =IFERROR(__xludf.DUMMYFUNCTION("VLOOKUP(G31,IMPORTRANGE(""https://docs.google.com/spreadsheets/d/12RxCea4e5ggM7QGn1XE3FbLQa_-QbCNdBi90OdPjRqg/edit?gid=1692403370#gid=1692403370"", ""'Plan de Compras'!D4:2432""), 8,0)"),9.0) -> 9 | K31: =IF( C31=TRUE, IF(I31=J31,"SI","NO"), "-") -> SI | S31: FALSE | T31: COMEX | U31: POR CONFIRMAR | W31: =IFERROR(__xludf.DUMMYFUNCTION("IFERROR(VLOOKUP(G31,IMPORTRANGE(""https://docs.google.com/spreadsheets/d/12RxCea4e5ggM7QGn1XE3FbLQa_-QbCNdBi90OdPjRqg"", ""'Plan de Compras'!D4:Q""), 12, 0), ""NO ESTÁ EN REQ"")"),"Técnica") -> Técnica | X31: =IFERROR(__xludf.DUMMYFUNCTION("IFERROR(VLOOKUP(G31,IMPORTRANGE(""https://docs.google.com/spreadsheets/d/12RxCea4e5ggM7QGn1XE3FbLQa_-QbCNdBi90OdPjRqg"", ""'Plan de Compras'!D4:Q""), 13, 0), """")"),"INTERNACIONAL") -> INTERNACIONAL | Y31: =IFERROR(__xludf.DUMMYFUNCTION("IFERROR(VLOOKUP(G31,IMPORTRANGE(""https://docs.google.com/spreadsheets/d/12RxCea4e5ggM7QGn1XE3FbLQa_-QbCNdBi90OdPjRqg"", ""'Plan de Compras'!D4:Q""), 14, 0), """")"),"GEYDI") -> GEYDI | Z31: =IFERROR(__xludf.DUMMYFUNCTION("IFERROR(VLOOKUP(G31,IMPORTRANGE(""https://docs.google.com/spreadsheets/d/12RxCea4e5ggM7QGn1XE3FbLQa_-QbCNdBi90OdPjRqg"", ""'Plan de Compras'!D4:Q""), 4, 0), """")"),"TUBOS FLEXIBLES (3 UND)") -> TUBOS FLEXIBLES (3 UND) | AA31: =IF(H31=Z31,"TRUE", "FALSE") -> TRUE | AB31: =IFERROR(__xludf.DUMMYFUNCTION("IFERROR(IF(OR(C31=TRUE,C31=""""),VLOOKUP(G31,IMPORTRANGE(""https://docs.google.com/spreadsheets/d/1z9A1Wq-kKrhRNG5RS2a2fKpY1wIhSVz2ZNmP2mOl588/edit?usp=sharing"",""REQ VF!E4:H""),4,0),""NO APLICA""),""GENERAR REQ"")"),"GENERAR REQ") -> GENERAR REQ | AC31: =IFERROR(__xludf.DUMMYFUNCTION("IFERROR(QUERY(IMPORTRANGE(""https://docs.google.com/spreadsheets/d/1z9A1Wq-kKrhRNG5RS2a2fKpY1wIhSVz2ZNmP2mOl588/edit?usp=sharing"",""REQ VF!E4:Q""),""SELECT Col10, Col11, Col12 WHERE Col1 = '""&G31&""'"",0),""NO APLICA"")"),"NO APLICA") -> NO APLICA
A32: 11 | B32: TRUE | C32: TRUE | D32: BIEN | E32: EQUIPOS | F32: ESP-109 | G32: ESP-109 | H32: ATORNILLADOR PORTÁTIL | I32: =SUMIFS('Hoja 10'!$O:$O,'Hoja 10'!$F:$F,$G32) -> 3 | J32: =IFERROR(__xludf.DUMMYFUNCTION("VLOOKUP(G32,IMPORTRANGE(""https://docs.google.com/spreadsheets/d/12RxCea4e5ggM7QGn1XE3FbLQa_-QbCNdBi90OdPjRqg/edit?gid=1692403370#gid=1692403370"", ""'Plan de Compras'!D4:2432""), 8,0)"),3.0) -> 3 | K32: =IF( C32=TRUE, IF(I32=J32,"SI","NO"), "-") -> SI | L32: ELECTRÓNICA | M32: 11 Taller_Electrónica_Firmado.pdf | O32: =VLOOKUP($G32,'Hoja 10'!$F$4:$AA478, 19,0) -> Bosch | P32: =VLOOKUP($G32,'Hoja 10'!$F$4:$AA478, 20,0) -> Taladro percutor 3/8" Bosch GSB 12V-30 | Q32: =VLOOKUP($G32,'Hoja 10'!$F$4:$AA478, 21,0) -> https://www.pe.tiendaboschonline.com/taladro-percutor-3-8-bosch-gsb-12v-30-12v-2-baterias-y-maletin/p | R32: ESP-109 ATORNILLADOR PORTÁTIL - CET | S32: TRUE | T32: =IFERROR(__xludf.DUMMYFUNCTION(" IF ( VLOOKUP($G32,IMPORTRANGE(""https://docs.google.com/spreadsheets/d/1Gpl6jkTg7sL4VDNimUm3S9Vi1i95esohXCF3wuKOE8c"", ""'CONSOLIDADO'!G5:AB""), 10, 0) <> 0, IFERROR(VLOOKUP($G32,IMPORTRANGE(""https://docs.google.com/spreadsheets/d/1Gpl6jkTg7sL4VDNimUm3"&"S9Vi1i95esohXCF3wuKOE8c"", ""'CONSOLIDADO'!G5:AB""), 17, 0), ""-""), """" )"),"BOSCH") -> BOSCH | U32: =IFERROR(__xludf.DUMMYFUNCTION(" IF ( VLOOKUP($G32,IMPORTRANGE(""https://docs.google.com/spreadsheets/d/1Gpl6jkTg7sL4VDNimUm3S9Vi1i95esohXCF3wuKOE8c"", ""'CONSOLIDADO'!G5:AB""), 10, 0) <> 0, IFERROR(VLOOKUP($G32,IMPORTRANGE(""https://docs.google.com/spreadsheets/d/1Gpl6jkTg7sL4VDNimUm3"&"S9Vi1i95esohXCF3wuKOE8c"", ""'CONSOLIDADO'!G5:AB""), 18, 0), ""-""), """" )"),"GSB 12V-30") -> GSB 12V-30 | V32: =IFERROR(__xludf.DUMMYFUNCTION(" IF ( VLOOKUP($G32,IMPORTRANGE(""https://docs.google.com/spreadsheets/d/1Gpl6jkTg7sL4VDNimUm3S9Vi1i95esohXCF3wuKOE8c"", ""'CONSOLIDADO'!G5:AB""), 10, 0) <> 0, IFERROR(VLOOKUP($G32,IMPORTRANGE(""https://docs.google.com/spreadsheets/d/1Gpl6jkTg7sL4VDNimUm3"&"S9Vi1i95esohXCF3wuKOE8c"", ""'CONSOLIDADO'!G5:AB""), 19, 0), ""-""), """" )"),"https://www.bosch-professional.com/pe/es/products/gsb-12v-30-06019G91E0") -> https://www.bosch-professional.com/pe/es/products/gsb-12v-30-06019G91E0 | W32: =IFERROR(__xludf.DUMMYFUNCTION("IFERROR(VLOOKUP(G32,IMPORTRANGE(""https://docs.google.com/spreadsheets/d/12RxCea4e5ggM7QGn1XE3FbLQa_-QbCNdBi90OdPjRqg"", ""'Plan de Compras'!D4:Q""), 12, 0), ""NO ESTÁ EN REQ"")"),"Técnica") -> Técnica | X32: =IFERROR(__xludf.DUMMYFUNCTION("IFERROR(VLOOKUP(G32,IMPORTRANGE(""https://docs.google.com/spreadsheets/d/12RxCea4e5ggM7QGn1XE3FbLQa_-QbCNdBi90OdPjRqg"", ""'Plan de Compras'!D4:Q""), 13, 0), """")"),"NACIONAL") -> NACIONAL | Y32: =IFERROR(__xludf.DUMMYFUNCTION("IFERROR(VLOOKUP(G32,IMPORTRANGE(""https://docs.google.com/spreadsheets/d/12RxCea4e5ggM7QGn1XE3FbLQa_-QbCNdBi90OdPjRqg"", ""'Plan de Compras'!D4:Q""), 14, 0), """")"),"DIANA") -> DIANA | Z32: =IFERROR(__xludf.DUMMYFUNCTION("IFERROR(VLOOKUP(G32,IMPORTRANGE(""https://docs.google.com/spreadsheets/d/12RxCea4e5ggM7QGn1XE3FbLQa_-QbCNdBi90OdPjRqg"", ""'Plan de Compras'!D4:Q""), 4, 0), """")"),"ATORNILLADOR PORTÁTIL") -> ATORNILLADOR PORTÁTIL | AA32: =IF(H32=Z32,"TRUE", "FALSE") -> TRUE | AB32: =IFERROR(__xludf.DUMMYFUNCTION("IFERROR(IF(OR(C32=TRUE,C32=""""),VLOOKUP(G32,IMPORTRANGE(""https://docs.google.com/spreadsheets/d/1z9A1Wq-kKrhRNG5RS2a2fKpY1wIhSVz2ZNmP2mOl588/edit?usp=sharing"",""REQ VF!E4:H""),4,0),""NO APLICA""),""GENERAR REQ"")"),"GENERAR REQ") -> GENERAR REQ | AC32: =IFERROR(__xludf.DUMMYFUNCTION("IFERROR(QUERY(IMPORTRANGE(""https://docs.google.com/spreadsheets/d/1z9A1Wq-kKrhRNG5RS2a2fKpY1wIhSVz2ZNmP2mOl588/edit?usp=sharing"",""REQ VF!E4:Q""),""SELECT Col10, Col11, Col12 WHERE Col1 = '""&G32&""'"",0),""NO APLICA"")"),"NO APLICA") -> NO APLICA | AF32: C
C33: TRUE | D33: ACCESORIO | E33: EQUIPOS | F33: ESP-109 | G33: ESP-109.1 | H33: SET DE PUNTAS PARA ATORNILLAR (1 UND) | I33: =$I$32 -> 3 | J33: =IFERROR(__xludf.DUMMYFUNCTION("VLOOKUP(G33,IMPORTRANGE(""https://docs.google.com/spreadsheets/d/12RxCea4e5ggM7QGn1XE3FbLQa_-QbCNdBi90OdPjRqg/edit?gid=1692403370#gid=1692403370"", ""'Plan de Compras'!D4:2432""), 8,0)"),3.0) -> 3 | K33: =IF( C33=TRUE, IF(I33=J33,"SI","NO"), "-") -> SI | N33: SET DE PUNTAS ACERO 32 UNIDADES | Q33: https://www.sodimac.com.pe/sodimac-pe/articulo/113087606/Set-de-Puntas-Acero-para-Atornillar-Bosch-con-32-unidades-Bosch/113087607?kid=goosho_669250&shop=googleShopping&gad_source=1&gad_campaignid=21524717227&gbraid=0AAAAADOx_19QnkfZPbdxei_TpLGi7HszI&gclid=CjwKCAjwgeLHBhBuEiwAL5gNEZ-XjHjVC9IjY67qaivgGJdKhSDsaUhylrIK2eg9zPYLMWI4EHfypRoCUMUQAvD_BwE | S33: TRUE | T33: BOSCH | U33: Kit de puntas para atornillar Bosch con 32 unidades | V33: https://www.pe.tiendaboschonline.com/kit-de-puntas-para-atornillar-bosch-con-32-unidades/p | W33: =IFERROR(__xludf.DUMMYFUNCTION("IFERROR(VLOOKUP(G33,IMPORTRANGE(""https://docs.google.com/spreadsheets/d/12RxCea4e5ggM7QGn1XE3FbLQa_-QbCNdBi90OdPjRqg"", ""'Plan de Compras'!D4:Q""), 12, 0), ""NO ESTÁ EN REQ"")"),"Simple") -> Simple | X33: =IFERROR(__xludf.DUMMYFUNCTION("IFERROR(VLOOKUP(G33,IMPORTRANGE(""https://docs.google.com/spreadsheets/d/12RxCea4e5ggM7QGn1XE3FbLQa_-QbCNdBi90OdPjRqg"", ""'Plan de Compras'!D4:Q""), 13, 0), """")"),"NACIONAL") -> NACIONAL | Y33: =IFERROR(__xludf.DUMMYFUNCTION("IFERROR(VLOOKUP(G33,IMPORTRANGE(""https://docs.google.com/spreadsheets/d/12RxCea4e5ggM7QGn1XE3FbLQa_-QbCNdBi90OdPjRqg"", ""'Plan de Compras'!D4:Q""), 14, 0), """")"),"DIANA") -> DIANA | Z33: =IFERROR(__xludf.DUMMYFUNCTION("IFERROR(VLOOKUP(G33,IMPORTRANGE(""https://docs.google.com/spreadsheets/d/12RxCea4e5ggM7QGn1XE3FbLQa_-QbCNdBi90OdPjRqg"", ""'Plan de Compras'!D4:Q""), 4, 0), """")"),"SET DE PUNTAS PARA ATORNILLAR (1 UND)") -> SET DE PUNTAS PARA ATORNILLAR (1 UND) | AA33: =IF(H33=Z33,"TRUE", "FALSE") -> TRUE | AB33: =IFERROR(__xludf.DUMMYFUNCTION("IFERROR(IF(OR(C33=TRUE,C33=""""),VLOOKUP(G33,IMPORTRANGE(""https://docs.google.com/spreadsheets/d/1z9A1Wq-kKrhRNG5RS2a2fKpY1wIhSVz2ZNmP2mOl588/edit?usp=sharing"",""REQ VF!E4:H""),4,0),""NO APLICA""),""GENERAR REQ"")"),"GENERAR REQ") -> GENERAR REQ | AC33: =IFERROR(__xludf.DUMMYFUNCTION("IFERROR(QUERY(IMPORTRANGE(""https://docs.google.com/spreadsheets/d/1z9A1Wq-kKrhRNG5RS2a2fKpY1wIhSVz2ZNmP2mOl588/edit?usp=sharing"",""REQ VF!E4:Q""),""SELECT Col10, Col11, Col12 WHERE Col1 = '""&G33&""'"",0),""NO APLICA"")"),"NO APLICA") -> NO APLICA
A34: 12 | B34: TRUE | C34: TRUE | D34: BIEN | E34: EQUIPOS | F34: ESP-110 | G34: ESP-110 | H34: AUTOCLAVE 18 LITROS (ESTERILIZACIÓN) | I34: =SUMIFS('Hoja 10'!$O:$O,'Hoja 10'!$F:$F,$G34) -> 4 | J34: =IFERROR(__xludf.DUMMYFUNCTION("VLOOKUP(G34,IMPORTRANGE(""https://docs.google.com/spreadsheets/d/12RxCea4e5ggM7QGn1XE3FbLQa_-QbCNdBi90OdPjRqg/edit?gid=1692403370#gid=1692403370"", ""'Plan de Compras'!D4:2432""), 8,0)"),4.0) -> 4 | K34: =IF( C34=TRUE, IF(I34=J34,"SI","NO"), "-") -> SI | L34: INDUSTRIA ALIMENTARIA | M34: 12 Taller_Industria_Alimentaria_Firmado.pdf | O34: =VLOOKUP($G34,'Hoja 10'!$F$4:$AA478, 19,0) -> JAMPAR | P34: =VLOOKUP($G34,'Hoja 10'!$F$4:$AA478, 20,0) -> FSF-18LDJ | Q34: =VLOOKUP($G34,'Hoja 10'!$F$4:$AA478, 21,0) -> https://www.appsheet.com/template/gettablefileurl?appName=APPDISTRIBUIDORES-2753577&tableName=RECURSOS&fileName=RECURSOS_Files_%2F186040010.DOC_INSERTO_SAP.140232.pdf | R34: ESP-110 AUTOCLAVE 18 LITROS (ESTERILIZACIÓN) - CET | S34: TRUE | T34: =IFERROR(__xludf.DUMMYFUNCTION(" IF ( VLOOKUP($G34,IMPORTRANGE(""https://docs.google.com/spreadsheets/d/1Gpl6jkTg7sL4VDNimUm3S9Vi1i95esohXCF3wuKOE8c"", ""'CONSOLIDADO'!G5:AB""), 10, 0) <> 0, IFERROR(VLOOKUP($G34,IMPORTRANGE(""https://docs.google.com/spreadsheets/d/1Gpl6jkTg7sL4VDNimUm3"&"S9Vi1i95esohXCF3wuKOE8c"", ""'CONSOLIDADO'!G5:AB""), 17, 0), ""-""), """" )"),"KELING") -> KELING | U34: =IFERROR(__xludf.DUMMYFUNCTION(" IF ( VLOOKUP($G34,IMPORTRANGE(""https://docs.google.com/spreadsheets/d/1Gpl6jkTg7sL4VDNimUm3S9Vi1i95esohXCF3wuKOE8c"", ""'CONSOLIDADO'!G5:AB""), 10, 0) <> 0, IFERROR(VLOOKUP($G34,IMPORTRANGE(""https://docs.google.com/spreadsheets/d/1Gpl6jkTg7sL4VDNimUm3"&"S9Vi1i95esohXCF3wuKOE8c"", ""'CONSOLIDADO'!G5:AB""), 18, 0), ""-""), """" )"),"YX-18HDD") -> YX-18HDD | V34: =IFERROR(__xludf.DUMMYFUNCTION(" IF ( VLOOKUP($G34,IMPORTRANGE(""https://docs.google.com/spreadsheets/d/1Gpl6jkTg7sL4VDNimUm3S9Vi1i95esohXCF3wuKOE8c"", ""'CONSOLIDADO'!G5:AB""), 10, 0) <> 0, IFERROR(VLOOKUP($G34,IMPORTRANGE(""https://docs.google.com/spreadsheets/d/1Gpl6jkTg7sL4VDNimUm3"&"S9Vi1i95esohXCF3wuKOE8c"", ""'CONSOLIDADO'!G5:AB""), 19, 0), ""-""), """" )"),"https://drive.google.com/file/d/1U_uJU9R50XlPQgpfVCk9PcUTLsSI2Cdj/view?usp=drive_link") -> https://drive.google.com/file/d/1U_uJU9R50XlPQgpfVCk9PcUTLsSI2Cdj/view?usp=drive_link | W34: =IFERROR(__xludf.DUMMYFUNCTION("IFERROR(VLOOKUP(G34,IMPORTRANGE(""https://docs.google.com/spreadsheets/d/12RxCea4e5ggM7QGn1XE3FbLQa_-QbCNdBi90OdPjRqg"", ""'Plan de Compras'!D4:Q""), 12, 0), ""NO ESTÁ EN REQ"")"),"Técnica") -> Técnica | X34: =IFERROR(__xludf.DUMMYFUNCTION("IFERROR(VLOOKUP(G34,IMPORTRANGE(""https://docs.google.com/spreadsheets/d/12RxCea4e5ggM7QGn1XE3FbLQa_-QbCNdBi90OdPjRqg"", ""'Plan de Compras'!D4:Q""), 13, 0), """")"),"NACIONAL") -> NACIONAL | Y34: =IFERROR(__xludf.DUMMYFUNCTION("IFERROR(VLOOKUP(G34,IMPORTRANGE(""https://docs.google.com/spreadsheets/d/12RxCea4e5ggM7QGn1XE3FbLQa_-QbCNdBi90OdPjRqg"", ""'Plan de Compras'!D4:Q""), 14, 0), """")"),"ALFIO") -> ALFIO | Z34: =IFERROR(__xludf.DUMMYFUNCTION("IFERROR(VLOOKUP(G34,IMPORTRANGE(""https://docs.google.com/spreadsheets/d/12RxCea4e5ggM7QGn1XE3FbLQa_-QbCNdBi90OdPjRqg"", ""'Plan de Compras'!D4:Q""), 4, 0), """")"),"AUTOCLAVE 18 LITROS (ESTERILIZACIÓN)") -> AUTOCLAVE 18 LITROS (ESTERILIZACIÓN) | AA34: =IF(H34=Z34,"TRUE", "FALSE") -> TRUE | AB34: =IFERROR(__xludf.DUMMYFUNCTION("IFERROR(IF(OR(C34=TRUE,C34=""""),VLOOKUP(G34,IMPORTRANGE(""https://docs.google.com/spreadsheets/d/1z9A1Wq-kKrhRNG5RS2a2fKpY1wIhSVz2ZNmP2mOl588/edit?usp=sharing"",""REQ VF!E4:H""),4,0),""NO APLICA""),""GENERAR REQ"")"),"GENERAR REQ") -> GENERAR REQ | AC34: =IFERROR(__xludf.DUMMYFUNCTION("IFERROR(QUERY(IMPORTRANGE(""https://docs.google.com/spreadsheets/d/1z9A1Wq-kKrhRNG5RS2a2fKpY1wIhSVz2ZNmP2mOl588/edit?usp=sharing"",""REQ VF!E4:Q""),""SELECT Col10, Col11, Col12 WHERE Col1 = '""&G34&""'"",0),""NO APLICA"")"),"NO APLICA") -> NO APLICA | AF34: C
C35: TRUE | D35: ACCESORIO | E35: EQUIPOS | F35: ESP-110 | G35: ESP-110.1 | H35: FUNDA IMPERMEABLE (1 UND) | I35: =$I$34 -> 4 | J35: =IFERROR(__xludf.DUMMYFUNCTION("VLOOKUP(G35,IMPORTRANGE(""https://docs.google.com/spreadsheets/d/12RxCea4e5ggM7QGn1XE3FbLQa_-QbCNdBi90OdPjRqg/edit?gid=1692403370#gid=1692403370"", ""'Plan de Compras'!D4:2432""), 8,0)"),4.0) -> 4 | K35: =IF( C35=TRUE, IF(I35=J35,"SI","NO"), "-") -> SI | N35: CON PROVEEDOR EXTERNO | P35: 410 x 410 x 520 mm | S35: TRUE | T35: GENÉRICO | U35: FUNDAS IMPERMEABLES 49 CM X 47 CM X 68 CM PARA AUTOCLAVE 18 LITROS (ESTERILIZACIÓN) | W35: =IFERROR(__xludf.DUMMYFUNCTION("IFERROR(VLOOKUP(G35,IMPORTRANGE(""https://docs.google.com/spreadsheets/d/12RxCea4e5ggM7QGn1XE3FbLQa_-QbCNdBi90OdPjRqg"", ""'Plan de Compras'!D4:Q""), 12, 0), ""NO ESTÁ EN REQ"")"),"Simple") -> Simple | X35: =IFERROR(__xludf.DUMMYFUNCTION("IFERROR(VLOOKUP(G35,IMPORTRANGE(""https://docs.google.com/spreadsheets/d/12RxCea4e5ggM7QGn1XE3FbLQa_-QbCNdBi90OdPjRqg"", ""'Plan de Compras'!D4:Q""), 13, 0), """")"),"NACIONAL") -> NACIONAL | Y35: =IFERROR(__xludf.DUMMYFUNCTION("IFERROR(VLOOKUP(G35,IMPORTRANGE(""https://docs.google.com/spreadsheets/d/12RxCea4e5ggM7QGn1XE3FbLQa_-QbCNdBi90OdPjRqg"", ""'Plan de Compras'!D4:Q""), 14, 0), """")"),"ANGIE") -> ANGIE | Z35: =IFERROR(__xludf.DUMMYFUNCTION("IFERROR(VLOOKUP(G35,IMPORTRANGE(""https://docs.google.com/spreadsheets/d/12RxCea4e5ggM7QGn1XE3FbLQa_-QbCNdBi90OdPjRqg"", ""'Plan de Compras'!D4:Q""), 4, 0), """")"),"FUNDA IMPERMEABLE (1 UND)") -> FUNDA IMPERMEABLE (1 UND) | AA35: =IF(H35=Z35,"TRUE", "FALSE") -> TRUE | AB35: =IFERROR(__xludf.DUMMYFUNCTION("IFERROR(IF(OR(C35=TRUE,C35=""""),VLOOKUP(G35,IMPORTRANGE(""https://docs.google.com/spreadsheets/d/1z9A1Wq-kKrhRNG5RS2a2fKpY1wIhSVz2ZNmP2mOl588/edit?usp=sharing"",""REQ VF!E4:H""),4,0),""NO APLICA""),""GENERAR REQ"")"),"GENERAR REQ") -> GENERAR REQ | AC35: =IFERROR(__xludf.DUMMYFUNCTION("IFERROR(QUERY(IMPORTRANGE(""https://docs.google.com/spreadsheets/d/1z9A1Wq-kKrhRNG5RS2a2fKpY1wIhSVz2ZNmP2mOl588/edit?usp=sharing"",""REQ VF!E4:Q""),""SELECT Col10, Col11, Col12 WHERE Col1 = '""&G35&""'"",0),""NO APLICA"")"),"NO APLICA") -> NO APLICA
A36: 13 | B36: TRUE | C36: TRUE | D36: BIEN | E36: EQUIPOS | F36: ESP-111 | G36: ESP-111 | H36: BATIDORA | I36: =SUMIFS('Hoja 10'!$O:$O,'Hoja 10'!$F:$F,$G36) -> 1 | J36: =IFERROR(__xludf.DUMMYFUNCTION("VLOOKUP(G36,IMPORTRANGE(""https://docs.google.com/spreadsheets/d/12RxCea4e5ggM7QGn1XE3FbLQa_-QbCNdBi90OdPjRqg/edit?gid=1692403370#gid=1692403370"", ""'Plan de Compras'!D4:2432""), 8,0)"),1.0) -> 1 | K36: =IF( C36=TRUE, IF(I36=J36,"SI","NO"), "-") -> SI | L36: COCINA Y REPOSTERÍA | M36: 5 Taller_Cocina y Respostería_Firmado.pdf | O36: =VLOOKUP($G36,'Hoja 10'!$F$4:$AA478, 19,0) -> SINMAG | P36: =VLOOKUP($G36,'Hoja 10'!$F$4:$AA478, 20,0) -> SM-401 | Q36: =VLOOKUP($G36,'Hoja 10'!$F$4:$AA478, 21,0) -> https://www.sinmag.com/en/prodetails/136/511.html | R36: ESP-111 BATIDORA - CET | S36: TRUE | T36: =IFERROR(__xludf.DUMMYFUNCTION(" IF ( VLOOKUP($G36,IMPORTRANGE(""https://docs.google.com/spreadsheets/d/1Gpl6jkTg7sL4VDNimUm3S9Vi1i95esohXCF3wuKOE8c"", ""'CONSOLIDADO'!G5:AB""), 10, 0) <> 0, IFERROR(VLOOKUP($G36,IMPORTRANGE(""https://docs.google.com/spreadsheets/d/1Gpl6jkTg7sL4VDNimUm3"&"S9Vi1i95esohXCF3wuKOE8c"", ""'CONSOLIDADO'!G5:AB""), 17, 0), ""-""), """" )"),"SINMAG") -> SINMAG | U36: =IFERROR(__xludf.DUMMYFUNCTION(" IF ( VLOOKUP($G36,IMPORTRANGE(""https://docs.google.com/spreadsheets/d/1Gpl6jkTg7sL4VDNimUm3S9Vi1i95esohXCF3wuKOE8c"", ""'CONSOLIDADO'!G5:AB""), 10, 0) <> 0, IFERROR(VLOOKUP($G36,IMPORTRANGE(""https://docs.google.com/spreadsheets/d/1Gpl6jkTg7sL4VDNimUm3"&"S9Vi1i95esohXCF3wuKOE8c"", ""'CONSOLIDADO'!G5:AB""), 18, 0), ""-""), """" )"),"SM - 401") -> SM - 401 | V36: =IFERROR(__xludf.DUMMYFUNCTION(" IF ( VLOOKUP($G36,IMPORTRANGE(""https://docs.google.com/spreadsheets/d/1Gpl6jkTg7sL4VDNimUm3S9Vi1i95esohXCF3wuKOE8c"", ""'CONSOLIDADO'!G5:AB""), 10, 0) <> 0, IFERROR(VLOOKUP($G36,IMPORTRANGE(""https://docs.google.com/spreadsheets/d/1Gpl6jkTg7sL4VDNimUm3"&"S9Vi1i95esohXCF3wuKOE8c"", ""'CONSOLIDADO'!G5:AB""), 19, 0), ""-""), """" )"),"https://www.sinmag.com/en/prodetails/136/511.html") -> https://www.sinmag.com/en/prodetails/136/511.html | W36: =IFERROR(__xludf.DUMMYFUNCTION("IFERROR(VLOOKUP(G36,IMPORTRANGE(""https://docs.google.com/spreadsheets/d/12RxCea4e5ggM7QGn1XE3FbLQa_-QbCNdBi90OdPjRqg"", ""'Plan de Compras'!D4:Q""), 12, 0), ""NO ESTÁ EN REQ"")"),"Técnica") -> Técnica | X36: =IFERROR(__xludf.DUMMYFUNCTION("IFERROR(VLOOKUP(G36,IMPORTRANGE(""https://docs.google.com/spreadsheets/d/12RxCea4e5ggM7QGn1XE3FbLQa_-QbCNdBi90OdPjRqg"", ""'Plan de Compras'!D4:Q""), 13, 0), """")"),"NACIONAL") -> NACIONAL | Y36: =IFERROR(__xludf.DUMMYFUNCTION("IFERROR(VLOOKUP(G36,IMPORTRANGE(""https://docs.google.com/spreadsheets/d/12RxCea4e5ggM7QGn1XE3FbLQa_-QbCNdBi90OdPjRqg"", ""'Plan de Compras'!D4:Q""), 14, 0), """")"),"GEANFRANCO") -> GEANFRANCO | Z36: =IFERROR(__xludf.DUMMYFUNCTION("IFERROR(VLOOKUP(G36,IMPORTRANGE(""https://docs.google.com/spreadsheets/d/12RxCea4e5ggM7QGn1XE3FbLQa_-QbCNdBi90OdPjRqg"", ""'Plan de Compras'!D4:Q""), 4, 0), """")"),"BATIDORA") -> BATIDORA | AA36: =IF(H36=Z36,"TRUE", "FALSE") -> TRUE | AB36: =IFERROR(__xludf.DUMMYFUNCTION("IFERROR(IF(OR(C36=TRUE,C36=""""),VLOOKUP(G36,IMPORTRANGE(""https://docs.google.com/spreadsheets/d/1z9A1Wq-kKrhRNG5RS2a2fKpY1wIhSVz2ZNmP2mOl588/edit?usp=sharing"",""REQ VF!E4:H""),4,0),""NO APLICA""),""GENERAR REQ"")"),"GENERAR REQ") -> GENERAR REQ | AC36: =IFERROR(__xludf.DUMMYFUNCTION("IFERROR(QUERY(IMPORTRANGE(""https://docs.google.com/spreadsheets/d/1z9A1Wq-kKrhRNG5RS2a2fKpY1wIhSVz2ZNmP2mOl588/edit?usp=sharing"",""REQ VF!E4:Q""),""SELECT Col10, Col11, Col12 WHERE Col1 = '""&G36&""'"",0),""NO APLICA"")"),"NO APLICA") -> NO APLICA | AF36: C
A37: 14 | B37: TRUE | C37: TRUE | D37: BIEN | E37: EQUIPOS | F37: ESP-112 | G37: ESP-112 | H37: BATIDORA AMASADORA MEZCLADORA 5 LT | I37: =SUMIFS('Hoja 10'!$O:$O,'Hoja 10'!$F:$F,$G37) -> 4 | J37: =IFERROR(__xludf.DUMMYFUNCTION("VLOOKUP(G37,IMPORTRANGE(""https://docs.google.com/spreadsheets/d/12RxCea4e5ggM7QGn1XE3FbLQa_-QbCNdBi90OdPjRqg/edit?gid=1692403370#gid=1692403370"", ""'Plan de Compras'!D4:2432""), 8,0)"),4.0) -> 4 | K37: =IF( C37=TRUE, IF(I37=J37,"SI","NO"), "-") -> SI | L37: INDUSTRIA ALIMENTARIA | M37: 12 Taller_Industria_Alimentaria_Firmado.pdf | O37: =VLOOKUP($G37,'Hoja 10'!$F$4:$AA478, 19,0) -> VIKALE | P37: =VLOOKUP($G37,'Hoja 10'!$F$4:$AA478, 20,0) -> B5HH-983 | Q37: =VLOOKUP($G37,'Hoja 10'!$F$4:$AA478, 21,0) -> https://www.maquinaelectroperu.com/vikale-b5hh-983/vikale-b5hh-983/ | R37: ESP-112 BATIDORA AMASADORA MEZCLADORA 5 LT - CET | S37: TRUE | T37: =IFERROR(__xludf.DUMMYFUNCTION(" IF ( VLOOKUP($G37,IMPORTRANGE(""https://docs.google.com/spreadsheets/d/1Gpl6jkTg7sL4VDNimUm3S9Vi1i95esohXCF3wuKOE8c"", ""'CONSOLIDADO'!G5:AB""), 10, 0) <> 0, IFERROR(VLOOKUP($G37,IMPORTRANGE(""https://docs.google.com/spreadsheets/d/1Gpl6jkTg7sL4VDNimUm3"&"S9Vi1i95esohXCF3wuKOE8c"", ""'CONSOLIDADO'!G5:AB""), 17, 0), ""-""), """" )"),"VIKALE") -> VIKALE | U37: =IFERROR(__xludf.DUMMYFUNCTION(" IF ( VLOOKUP($G37,IMPORTRANGE(""https://docs.google.com/spreadsheets/d/1Gpl6jkTg7sL4VDNimUm3S9Vi1i95esohXCF3wuKOE8c"", ""'CONSOLIDADO'!G5:AB""), 10, 0) <> 0, IFERROR(VLOOKUP($G37,IMPORTRANGE(""https://docs.google.com/spreadsheets/d/1Gpl6jkTg7sL4VDNimUm3"&"S9Vi1i95esohXCF3wuKOE8c"", ""'CONSOLIDADO'!G5:AB""), 18, 0), ""-""), """" )"),"B5HH-983") -> B5HH-983 | V37: =IFERROR(__xludf.DUMMYFUNCTION(" IF ( VLOOKUP($G37,IMPORTRANGE(""https://docs.google.com/spreadsheets/d/1Gpl6jkTg7sL4VDNimUm3S9Vi1i95esohXCF3wuKOE8c"", ""'CONSOLIDADO'!G5:AB""), 10, 0) <> 0, IFERROR(VLOOKUP($G37,IMPORTRANGE(""https://docs.google.com/spreadsheets/d/1Gpl6jkTg7sL4VDNimUm3"&"S9Vi1i95esohXCF3wuKOE8c"", ""'CONSOLIDADO'!G5:AB""), 19, 0), ""-""), """" )"),"https://www.maquinaelectroperu.com/vikale-b5hh-983/vikale-b5hh-983/") -> https://www.maquinaelectroperu.com/vikale-b5hh-983/vikale-b5hh-983/ | W37: =IFERROR(__xludf.DUMMYFUNCTION("IFERROR(VLOOKUP(G37,IMPORTRANGE(""https://docs.google.com/spreadsheets/d/12RxCea4e5ggM7QGn1XE3FbLQa_-QbCNdBi90OdPjRqg"", ""'Plan de Compras'!D4:Q""), 12, 0), ""NO ESTÁ EN REQ"")"),"Técnica") -> Técnica | X37: =IFERROR(__xludf.DUMMYFUNCTION("IFERROR(VLOOKUP(G37,IMPORTRANGE(""https://docs.google.com/spreadsheets/d/12RxCea4e5ggM7QGn1XE3FbLQa_-QbCNdBi90OdPjRqg"", ""'Plan de Compras'!D4:Q""), 13, 0), """")"),"NACIONAL") -> NACIONAL | Y37: =IFERROR(__xludf.DUMMYFUNCTION("IFERROR(VLOOKUP(G37,IMPORTRANGE(""https://docs.google.com/spreadsheets/d/12RxCea4e5ggM7QGn1XE3FbLQa_-QbCNdBi90OdPjRqg"", ""'Plan de Compras'!D4:Q""), 14, 0), """")"),"DIANA") -> DIANA | Z37: =IFERROR(__xludf.DUMMYFUNCTION("IFERROR(VLOOKUP(G37,IMPORTRANGE(""https://docs.google.com/spreadsheets/d/12RxCea4e5ggM7QGn1XE3FbLQa_-QbCNdBi90OdPjRqg"", ""'Plan de Compras'!D4:Q""), 4, 0), """")"),"BATIDORA AMASADORA MEZCLADORA 5 LT") -> BATIDORA AMASADORA MEZCLADORA 5 LT | AA37: =IF(H37=Z37,"TRUE", "FALSE") -> TRUE | AB37: =IFERROR(__xludf.DUMMYFUNCTION("IFERROR(IF(OR(C37=TRUE,C37=""""),VLOOKUP(G37,IMPORTRANGE(""https://docs.google.com/spreadsheets/d/1z9A1Wq-kKrhRNG5RS2a2fKpY1wIhSVz2ZNmP2mOl588/edit?usp=sharing"",""REQ VF!E4:H""),4,0),""NO APLICA""),""GENERAR REQ"")"),"GENERAR REQ") -> GENERAR REQ | AC37: =IFERROR(__xludf.DUMMYFUNCTION("IFERROR(QUERY(IMPORTRANGE(""https://docs.google.com/spreadsheets/d/1z9A1Wq-kKrhRNG5RS2a2fKpY1wIhSVz2ZNmP2mOl588/edit?usp=sharing"",""REQ VF!E4:Q""),""SELECT Col10, Col11, Col12 WHERE Col1 = '""&G37&""'"",0),""NO APLICA"")"),"NO APLICA") -> NO APLICA
C38: TRUE | D38: ACCESORIO | E38: EQUIPOS | F38: ESP-112 | G38: ESP-112.1 | H38: FUNDA IMPERMEABLE (1 UND) | I38: =$I$37 -> 4 | J38: =IFERROR(__xludf.DUMMYFUNCTION("VLOOKUP(G38,IMPORTRANGE(""https://docs.google.com/spreadsheets/d/12RxCea4e5ggM7QGn1XE3FbLQa_-QbCNdBi90OdPjRqg/edit?gid=1692403370#gid=1692403370"", ""'Plan de Compras'!D4:2432""), 8,0)"),4.0) -> 4 | K38: =IF( C38=TRUE, IF(I38=J38,"SI","NO"), "-") -> SI | N38: CON PROVEEDOR O EXTERNO | P38: 435 X 266 X 435 | S38: TRUE | T38: GENÉRICO | U38: FUNDAS IMPERMEABLES 43,5 CM X 26,6 CM X 43,5 CM PARA BATIDORA AMASADORA MEZCLADORA 5 LT | W38: =IFERROR(__xludf.DUMMYFUNCTION("IFERROR(VLOOKUP(G38,IMPORTRANGE(""https://docs.google.com/spreadsheets/d/12RxCea4e5ggM7QGn1XE3FbLQa_-QbCNdBi90OdPjRqg"", ""'Plan de Compras'!D4:Q""), 12, 0), ""NO ESTÁ EN REQ"")"),"Simple") -> Simple | X38: =IFERROR(__xludf.DUMMYFUNCTION("IFERROR(VLOOKUP(G38,IMPORTRANGE(""https://docs.google.com/spreadsheets/d/12RxCea4e5ggM7QGn1XE3FbLQa_-QbCNdBi90OdPjRqg"", ""'Plan de Compras'!D4:Q""), 13, 0), """")"),"NACIONAL") -> NACIONAL | Y38: =IFERROR(__xludf.DUMMYFUNCTION("IFERROR(VLOOKUP(G38,IMPORTRANGE(""https://docs.google.com/spreadsheets/d/12RxCea4e5ggM7QGn1XE3FbLQa_-QbCNdBi90OdPjRqg"", ""'Plan de Compras'!D4:Q""), 14, 0), """")"),"ANGIE") -> ANGIE | Z38: =IFERROR(__xludf.DUMMYFUNCTION("IFERROR(VLOOKUP(G38,IMPORTRANGE(""https://docs.google.com/spreadsheets/d/12RxCea4e5ggM7QGn1XE3FbLQa_-QbCNdBi90OdPjRqg"", ""'Plan de Compras'!D4:Q""), 4, 0), """")"),"FUNDA IMPERMEABLE (1 UND)") -> FUNDA IMPERMEABLE (1 UND) | AA38: =IF(H38=Z38,"TRUE", "FALSE") -> TRUE | AB38: =IFERROR(__xludf.DUMMYFUNCTION("IFERROR(IF(OR(C38=TRUE,C38=""""),VLOOKUP(G38,IMPORTRANGE(""https://docs.google.com/spreadsheets/d/1z9A1Wq-kKrhRNG5RS2a2fKpY1wIhSVz2ZNmP2mOl588/edit?usp=sharing"",""REQ VF!E4:H""),4,0),""NO APLICA""),""GENERAR REQ"")"),"GENERAR REQ") -> GENERAR REQ | AC38: =IFERROR(__xludf.DUMMYFUNCTION("IFERROR(QUERY(IMPORTRANGE(""https://docs.google.com/spreadsheets/d/1z9A1Wq-kKrhRNG5RS2a2fKpY1wIhSVz2ZNmP2mOl588/edit?usp=sharing"",""REQ VF!E4:Q""),""SELECT Col10, Col11, Col12 WHERE Col1 = '""&G38&""'"",0),""NO APLICA"")"),"NO APLICA") -> NO APLICA
A39: 15 | B39: TRUE | C39: TRUE | D39: BIEN | E39: EQUIPOS | F39: ESP-113 | G39: ESP-113 | H39: BATIDORA MULTIFUNCIONAL | I39: =SUMIFS('Hoja 10'!$O:$O,'Hoja 10'!$F:$F,$G39) -> 4 | J39: =IFERROR(__xludf.DUMMYFUNCTION("VLOOKUP(G39,IMPORTRANGE(""https://docs.google.com/spreadsheets/d/12RxCea4e5ggM7QGn1XE3FbLQa_-QbCNdBi90OdPjRqg/edit?gid=1692403370#gid=1692403370"", ""'Plan de Compras'!D4:2432""), 8,0)"),4.0) -> 4 | K39: =IF( C39=TRUE, IF(I39=J39,"SI","NO"), "-") -> SI | L39: INDUSTRIA ALIMENTARIA | M39: 12 Taller_Industria_Alimentaria_Firmado.pdf | O39: =VLOOKUP($G39,'Hoja 10'!$F$4:$AA478, 19,0) -> BIOLOMIX | P39: =VLOOKUP($G39,'Hoja 10'!$F$4:$AA478, 20,0) -> BM601 | Q39: =VLOOKUP($G39,'Hoja 10'!$F$4:$AA478, 21,0) -> https://drive.google.com/file/d/1Ti61n5CvjYbERQd_WBKo61P__TL78SWh/view?usp=sharing | R39: ESP-113 BATIDORA MULTIFUNCIONAL - CET | S39: TRUE | T39: =IFERROR(__xludf.DUMMYFUNCTION(" IF ( VLOOKUP($G39,IMPORTRANGE(""https://docs.google.com/spreadsheets/d/1Gpl6jkTg7sL4VDNimUm3S9Vi1i95esohXCF3wuKOE8c"", ""'CONSOLIDADO'!G5:AB""), 10, 0) <> 0, IFERROR(VLOOKUP($G39,IMPORTRANGE(""https://docs.google.com/spreadsheets/d/1Gpl6jkTg7sL4VDNimUm3"&"S9Vi1i95esohXCF3wuKOE8c"", ""'CONSOLIDADO'!G5:AB""), 17, 0), ""-""), """" )"),"BIOLOMIX") -> BIOLOMIX | U39: =IFERROR(__xludf.DUMMYFUNCTION(" IF ( VLOOKUP($G39,IMPORTRANGE(""https://docs.google.com/spreadsheets/d/1Gpl6jkTg7sL4VDNimUm3S9Vi1i95esohXCF3wuKOE8c"", ""'CONSOLIDADO'!G5:AB""), 10, 0) <> 0, IFERROR(VLOOKUP($G39,IMPORTRANGE(""https://docs.google.com/spreadsheets/d/1Gpl6jkTg7sL4VDNimUm3"&"S9Vi1i95esohXCF3wuKOE8c"", ""'CONSOLIDADO'!G5:AB""), 18, 0), ""-""), """" )"),"BM601") -> BM601 | V39: =IFERROR(__xludf.DUMMYFUNCTION(" IF ( VLOOKUP($G39,IMPORTRANGE(""https://docs.google.com/spreadsheets/d/1Gpl6jkTg7sL4VDNimUm3S9Vi1i95esohXCF3wuKOE8c"", ""'CONSOLIDADO'!G5:AB""), 10, 0) <> 0, IFERROR(VLOOKUP($G39,IMPORTRANGE(""https://docs.google.com/spreadsheets/d/1Gpl6jkTg7sL4VDNimUm3"&"S9Vi1i95esohXCF3wuKOE8c"", ""'CONSOLIDADO'!G5:AB""), 19, 0), ""-""), """" )"),"https://spanish.alibaba.com/product-detail/Professional-Brushless-DC-Motor-Kitchen-Electric-1600490581343.html?chatToken=TDFKeWNGRlpkWFZTWmtkNFRYRnZjVWxhVTBsU2RVcHNkRVpKVTJsMlRteERiM0ZyWlhrM2VHMXhZeTkwTVVSb2RIQnFRMGxKTmtONE9GSllWWFFyVG5Ka1lWUlpTSEY0V1RoTV"&"JHMXBPVlpMYW1Nd1lsVjNkSFpzYkVoeFRXMXFSREV6V1N0cU5tc3pNa3B3TVM5MGFIaHBaVmx5ZEVkVlQwaGxOaTh4ZURRclJuSnNha3RDTTFaeE5HOHJlRlJxZUhsRFpXTktiMmRyYzBac2VHdFJWVUYzY0hOU09FMTZTMHR6UFE9PSZ2ZXJzaW9uPTIuMC4w&encryptTargetLoginId=8pctgRBMALMsBw%2FYN3uRQusHZH2EmvrO") -> https://spanish.alibaba.com/product-detail/Professional-Brushless-DC-Motor-Kitchen-Electric-1600490581343.html?chatToken=TDFKeWNGRlpkWFZTWmtkNFRYRnZjVWxhVTBsU2RVcHNkRVpKVTJsMlRteERiM0ZyWlhrM2VHMXhZeTkwTVVSb2RIQnFRMGxKTmtONE9GSllWWFFyVG5Ka1lWUlpTSEY0V1RoTVJHMXBPVlpMYW1Nd1lsVjNkSFpzYkVoeFRXMXFSREV6V1N0cU5tc3pNa3B3TVM5MGFIaHBaVmx5ZEVkVlQwaGxOaTh4ZURRclJuSnNha3RDTTFaeE5HOHJlRlJxZUhsRFpXTktiMmRyYzBac2VHdFJWVUYzY0hOU09FMTZTMHR6UFE9PSZ2ZXJzaW9uPTIuMC4w&encryptTargetLoginId=8pctgRBMALMsBw%2FYN3uRQusHZH2EmvrO | W39: =IFERROR(__xludf.DUMMYFUNCTION("IFERROR(VLOOKUP(G39,IMPORTRANGE(""https://docs.google.com/spreadsheets/d/12RxCea4e5ggM7QGn1XE3FbLQa_-QbCNdBi90OdPjRqg"", ""'Plan de Compras'!D4:Q""), 12, 0), ""NO ESTÁ EN REQ"")"),"Técnica") -> Técnica | X39: =IFERROR(__xludf.DUMMYFUNCTION("IFERROR(VLOOKUP(G39,IMPORTRANGE(""https://docs.google.com/spreadsheets/d/12RxCea4e5ggM7QGn1XE3FbLQa_-QbCNdBi90OdPjRqg"", ""'Plan de Compras'!D4:Q""), 13, 0), """")"),"INTERNACIONAL") -> INTERNACIONAL | Y39: =IFERROR(__xludf.DUMMYFUNCTION("IFERROR(VLOOKUP(G39,IMPORTRANGE(""https://docs.google.com/spreadsheets/d/12RxCea4e5ggM7QGn1XE3FbLQa_-QbCNdBi90OdPjRqg"", ""'Plan de Compras'!D4:Q""), 14, 0), """")"),"DIEGO ") -> DIEGO | Z39: =IFERROR(__xludf.DUMMYFUNCTION("IFERROR(VLOOKUP(G39,IMPORTRANGE(""https://docs.google.com/spreadsheets/d/12RxCea4e5ggM7QGn1XE3FbLQa_-QbCNdBi90OdPjRqg"", ""'Plan de Compras'!D4:Q""), 4, 0), """")"),"BATIDORA MULTIFUNCIONAL") -> BATIDORA MULTIFUNCIONAL | AA39: =IF(H39=Z39,"TRUE", "FALSE") -> TRUE | AB39: =IFERROR(__xludf.DUMMYFUNCTION("IFERROR(IF(OR(C39=TRUE,C39=""""),VLOOKUP(G39,IMPORTRANGE(""https://docs.google.com/spreadsheets/d/1z9A1Wq-kKrhRNG5RS2a2fKpY1wIhSVz2ZNmP2mOl588/edit?usp=sharing"",""REQ VF!E4:H""),4,0),""NO APLICA""),""GENERAR REQ"")"),"GENERAR REQ") -> GENERAR REQ | AC39: =IFERROR(__xludf.DUMMYFUNCTION("IFERROR(QUERY(IMPORTRANGE(""https://docs.google.com/spreadsheets/d/1z9A1Wq-kKrhRNG5RS2a2fKpY1wIhSVz2ZNmP2mOl588/edit?usp=sharing"",""REQ VF!E4:Q""),""SELECT Col10, Col11, Col12 WHERE Col1 = '""&G39&""'"",0),""NO APLICA"")"),"NO APLICA") -> NO APLICA | AF39: C
C40: TRUE | D40: ACCESORIO | E40: EQUIPOS | F40: ESP-113 | G40: ESP-113.1 | H40: FUNDA IMPERMEABLE (1 UND) | I40: =$I$39 -> 4 | J40: =IFERROR(__xludf.DUMMYFUNCTION("VLOOKUP(G40,IMPORTRANGE(""https://docs.google.com/spreadsheets/d/12RxCea4e5ggM7QGn1XE3FbLQa_-QbCNdBi90OdPjRqg/edit?gid=1692403370#gid=1692403370"", ""'Plan de Compras'!D4:2432""), 8,0)"),4.0) -> 4 | K40: =IF( C40=TRUE, IF(I40=J40,"SI","NO"), "-") -> SI | N40: CON PROVEEDOR O EXTERNO | P40: 435 x 266 x 435 mm | S40: TRUE | T40: GENÉRICO | U40: FUNDAS IMPERMEABLES 32 CM X 17 CM X 31,5 CM PARA BATIDORA MULTIFUNCIONAL | W40: =IFERROR(__xludf.DUMMYFUNCTION("IFERROR(VLOOKUP(G40,IMPORTRANGE(""https://docs.google.com/spreadsheets/d/12RxCea4e5ggM7QGn1XE3FbLQa_-QbCNdBi90OdPjRqg"", ""'Plan de Compras'!D4:Q""), 12, 0), ""NO ESTÁ EN REQ"")"),"Simple") -> Simple | X40: =IFERROR(__xludf.DUMMYFUNCTION("IFERROR(VLOOKUP(G40,IMPORTRANGE(""https://docs.google.com/spreadsheets/d/12RxCea4e5ggM7QGn1XE3FbLQa_-QbCNdBi90OdPjRqg"", ""'Plan de Compras'!D4:Q""), 13, 0), """")"),"NACIONAL") -> NACIONAL | Y40: =IFERROR(__xludf.DUMMYFUNCTION("IFERROR(VLOOKUP(G40,IMPORTRANGE(""https://docs.google.com/spreadsheets/d/12RxCea4e5ggM7QGn1XE3FbLQa_-QbCNdBi90OdPjRqg"", ""'Plan de Compras'!D4:Q""), 14, 0), """")"),"ANGIE") -> ANGIE | Z40: =IFERROR(__xludf.DUMMYFUNCTION("IFERROR(VLOOKUP(G40,IMPORTRANGE(""https://docs.google.com/spreadsheets/d/12RxCea4e5ggM7QGn1XE3FbLQa_-QbCNdBi90OdPjRqg"", ""'Plan de Compras'!D4:Q""), 4, 0), """")"),"FUNDA IMPERMEABLE (1 UND)") -> FUNDA IMPERMEABLE (1 UND) | AA40: =IF(H40=Z40,"TRUE", "FALSE") -> TRUE | AB40: =IFERROR(__xludf.DUMMYFUNCTION("IFERROR(IF(OR(C40=TRUE,C40=""""),VLOOKUP(G40,IMPORTRANGE(""https://docs.google.com/spreadsheets/d/1z9A1Wq-kKrhRNG5RS2a2fKpY1wIhSVz2ZNmP2mOl588/edit?usp=sharing"",""REQ VF!E4:H""),4,0),""NO APLICA""),""GENERAR REQ"")"),"GENERAR REQ") -> GENERAR REQ | AC40: =IFERROR(__xludf.DUMMYFUNCTION("IFERROR(QUERY(IMPORTRANGE(""https://docs.google.com/spreadsheets/d/1z9A1Wq-kKrhRNG5RS2a2fKpY1wIhSVz2ZNmP2mOl588/edit?usp=sharing"",""REQ VF!E4:Q""),""SELECT Col10, Col11, Col12 WHERE Col1 = '""&G40&""'"",0),""NO APLICA"")"),"NO APLICA") -> NO APLICA
B41: FALSE | C41: FALSE | D41: ACCESORIO | E41: EQUIPOS | F41: ESP-113 | G41: ESP-113.2 | H41: MANUAL DE INSTRUCCIONES (1 UND) | I41: =1*I40 -> 4 | J41: =IFERROR(__xludf.DUMMYFUNCTION("VLOOKUP(G41,IMPORTRANGE(""https://docs.google.com/spreadsheets/d/12RxCea4e5ggM7QGn1XE3FbLQa_-QbCNdBi90OdPjRqg/edit?gid=1692403370#gid=1692403370"", ""'Plan de Compras'!D4:2432""), 8,0)"),"#N/A") -> #N/A | K41: =IF( C41=TRUE, IF(I41=J41,"SI","NO"), "-") -> - | S41: TRUE | T41: GENÉRICO | U41: INCLUÍDO (en inglés)
A42: 16 | B42: TRUE | C42: TRUE | D42: BIEN | E42: EQUIPOS | F42: ESP-114 | G42: ESP-114 | H42: BLOCK DE CONTACTORES AUXILIAR NC - NO | I42: =SUMIFS('Hoja 10'!$O:$O,'Hoja 10'!$F:$F,$G42) -> 12 | J42: =IFERROR(__xludf.DUMMYFUNCTION("VLOOKUP(G42,IMPORTRANGE(""https://docs.google.com/spreadsheets/d/12RxCea4e5ggM7QGn1XE3FbLQa_-QbCNdBi90OdPjRqg/edit?gid=1692403370#gid=1692403370"", ""'Plan de Compras'!D4:2432""), 8,0)"),12.0) -> 12 | K42: =IF( C42=TRUE, IF(I42=J42,"SI","NO"), "-") -> SI | L42: ELECTRICIDAD | M42: 15 Taller_Electricidad_Firmado.pdf | O42: =VLOOKUP($G42,'Hoja 10'!$F$4:$AA478, 19,0) -> Schneider Electric | P42: =VLOOKUP($G42,'Hoja 10'!$F$4:$AA478, 20,0) -> LADN40 | Q42: =VLOOKUP($G42,'Hoja 10'!$F$4:$AA478, 21,0) -> https://www.se.com/pe/es/product/LADN40/bloque-de-contacto-auxiliar-tesys-d-4-na-terminales-de-abrazaderas-de-tornillo/ | R42: ESP-114 BLOCK DE CONTACTORES AUXILIAR NC - NO - CET | S42: TRUE | T42: =IFERROR(__xludf.DUMMYFUNCTION(" IF ( VLOOKUP($G42,IMPORTRANGE(""https://docs.google.com/spreadsheets/d/1Gpl6jkTg7sL4VDNimUm3S9Vi1i95esohXCF3wuKOE8c"", ""'CONSOLIDADO'!G5:AB""), 10, 0) <> 0, IFERROR(VLOOKUP($G42,IMPORTRANGE(""https://docs.google.com/spreadsheets/d/1Gpl6jkTg7sL4VDNimUm3"&"S9Vi1i95esohXCF3wuKOE8c"", ""'CONSOLIDADO'!G5:AB""), 17, 0), ""-""), """" )"),"SCHNEIDER ELECTRIC") -> SCHNEIDER ELECTRIC | U42: =IFERROR(__xludf.DUMMYFUNCTION(" IF ( VLOOKUP($G42,IMPORTRANGE(""https://docs.google.com/spreadsheets/d/1Gpl6jkTg7sL4VDNimUm3S9Vi1i95esohXCF3wuKOE8c"", ""'CONSOLIDADO'!G5:AB""), 10, 0) <> 0, IFERROR(VLOOKUP($G42,IMPORTRANGE(""https://docs.google.com/spreadsheets/d/1Gpl6jkTg7sL4VDNimUm3"&"S9Vi1i95esohXCF3wuKOE8c"", ""'CONSOLIDADO'!G5:AB""), 18, 0), ""-""), """" )"),"LADN40") -> LADN40 | V42: =IFERROR(__xludf.DUMMYFUNCTION(" IF ( VLOOKUP($G42,IMPORTRANGE(""https://docs.google.com/spreadsheets/d/1Gpl6jkTg7sL4VDNimUm3S9Vi1i95esohXCF3wuKOE8c"", ""'CONSOLIDADO'!G5:AB""), 10, 0) <> 0, IFERROR(VLOOKUP($G42,IMPORTRANGE(""https://docs.google.com/spreadsheets/d/1Gpl6jkTg7sL4VDNimUm3"&"S9Vi1i95esohXCF3wuKOE8c"", ""'CONSOLIDADO'!G5:AB""), 19, 0), ""-""), """" )"),"https://www.se.com/pe/es/product/LADN40/bloque-de-contacto-auxiliar-tesys-d-4-na-terminales-de-abrazaderas-de-tornillo/") -> https://www.se.com/pe/es/product/LADN40/bloque-de-contacto-auxiliar-tesys-d-4-na-terminales-de-abrazaderas-de-tornillo/ | W42: =IFERROR(__xludf.DUMMYFUNCTION("IFERROR(VLOOKUP(G42,IMPORTRANGE(""https://docs.google.com/spreadsheets/d/12RxCea4e5ggM7QGn1XE3FbLQa_-QbCNdBi90OdPjRqg"", ""'Plan de Compras'!D4:Q""), 12, 0), ""NO ESTÁ EN REQ"")"),"Técnica") -> Técnica | X42: =IFERROR(__xludf.DUMMYFUNCTION("IFERROR(VLOOKUP(G42,IMPORTRANGE(""https://docs.google.com/spreadsheets/d/12RxCea4e5ggM7QGn1XE3FbLQa_-QbCNdBi90OdPjRqg"", ""'Plan de Compras'!D4:Q""), 13, 0), """")"),"NACIONAL") -> NACIONAL | Y42: =IFERROR(__xludf.DUMMYFUNCTION("IFERROR(VLOOKUP(G42,IMPORTRANGE(""https://docs.google.com/spreadsheets/d/12RxCea4e5ggM7QGn1XE3FbLQa_-QbCNdBi90OdPjRqg"", ""'Plan de Compras'!D4:Q""), 14, 0), """")"),"ALFIO") -> ALFIO | Z42: =IFERROR(__xludf.DUMMYFUNCTION("IFERROR(VLOOKUP(G42,IMPORTRANGE(""https://docs.google.com/spreadsheets/d/12RxCea4e5ggM7QGn1XE3FbLQa_-QbCNdBi90OdPjRqg"", ""'Plan de Compras'!D4:Q""), 4, 0), """")"),"BLOCK DE CONTACTORES AUXILIAR NC - NO") -> BLOCK DE CONTACTORES AUXILIAR NC - NO | AA42: =IF(H42=Z42,"TRUE", "FALSE") -> TRUE | AB42: =IFERROR(__xludf.DUMMYFUNCTION("IFERROR(IF(OR(C42=TRUE,C42=""""),VLOOKUP(G42,IMPORTRANGE(""https://docs.google.com/spreadsheets/d/1z9A1Wq-kKrhRNG5RS2a2fKpY1wIhSVz2ZNmP2mOl588/edit?usp=sharing"",""REQ VF!E4:H""),4,0),""NO APLICA""),""GENERAR REQ"")"),"GENERAR REQ") -> GENERAR REQ | AC42: =IFERROR(__xludf.DUMMYFUNCTION("IFERROR(QUERY(IMPORTRANGE(""https://docs.google.com/spreadsheets/d/1z9A1Wq-kKrhRNG5RS2a2fKpY1wIhSVz2ZNmP2mOl588/edit?usp=sharing"",""REQ VF!E4:Q""),""SELECT Col10, Col11, Col12 WHERE Col1 = '""&G42&""'"",0),""NO APLICA"")"),"NO APLICA") -> NO APLICA
A43: 17 | B43: TRUE | C43: TRUE | D43: BIEN | E43: EQUIPOS | F43: ESP-116 | G43: ESP-116 | H43: BORDADORA DOMESTICA DIGITAL, ÁREA DE TRABAJO DE 300 MM X 180 MM | I43: =SUMIFS('Hoja 10'!$O:$O,'Hoja 10'!$F:$F,$G43) -> 9 | J43: =IFERROR(__xludf.DUMMYFUNCTION("VLOOKUP(G43,IMPORTRANGE(""https://docs.google.com/spreadsheets/d/12RxCea4e5ggM7QGn1XE3FbLQa_-QbCNdBi90OdPjRqg/edit?gid=1692403370#gid=1692403370"", ""'Plan de Compras'!D4:2432""), 8,0)"),9.0) -> 9 | K43: =IF( C43=TRUE, IF(I43=J43,"SI","NO"), "-") -> SI | L43: INDUSTRIA DEL VESTIDO | M43: 4 Taller_Industria del vestido_Firmado.pdf | O43: BROTHER | P43: =VLOOKUP($G43,'Hoja 10'!$F$4:$AA478, 20,0) -> Innov-is V5LE | Q43: =VLOOKUP($G43,'Hoja 10'!$F$4:$AA478, 21,0) -> https://sewingcraft.brother.eu/en/products/machines/combination-machines/combination-machines/innov-is-v5le | R43: ESP-116 BORDADORA DOMESTICA DIGITAL, ÁREA DE TRABAJO DE 300 MM X 180 MM - CET | S43: TRUE | T43: =IFERROR(__xludf.DUMMYFUNCTION(" IF ( VLOOKUP($G43,IMPORTRANGE(""https://docs.google.com/spreadsheets/d/1Gpl6jkTg7sL4VDNimUm3S9Vi1i95esohXCF3wuKOE8c"", ""'CONSOLIDADO'!G5:AB""), 10, 0) <> 0, IFERROR(VLOOKUP($G43,IMPORTRANGE(""https://docs.google.com/spreadsheets/d/1Gpl6jkTg7sL4VDNimUm3"&"S9Vi1i95esohXCF3wuKOE8c"", ""'CONSOLIDADO'!G5:AB""), 17, 0), ""-""), """" )"),"BROTHER") -> BROTHER | U43: =IFERROR(__xludf.DUMMYFUNCTION(" IF ( VLOOKUP($G43,IMPORTRANGE(""https://docs.google.com/spreadsheets/d/1Gpl6jkTg7sL4VDNimUm3S9Vi1i95esohXCF3wuKOE8c"", ""'CONSOLIDADO'!G5:AB""), 10, 0) <> 0, IFERROR(VLOOKUP($G43,IMPORTRANGE(""https://docs.google.com/spreadsheets/d/1Gpl6jkTg7sL4VDNimUm3"&"S9Vi1i95esohXCF3wuKOE8c"", ""'CONSOLIDADO'!G5:AB""), 18, 0), ""-""), """" )"),"Innov-is V5LE") -> Innov-is V5LE | V43: =IFERROR(__xludf.DUMMYFUNCTION(" IF ( VLOOKUP($G43,IMPORTRANGE(""https://docs.google.com/spreadsheets/d/1Gpl6jkTg7sL4VDNimUm3S9Vi1i95esohXCF3wuKOE8c"", ""'CONSOLIDADO'!G5:AB""), 10, 0) <> 0, IFERROR(VLOOKUP($G43,IMPORTRANGE(""https://docs.google.com/spreadsheets/d/1Gpl6jkTg7sL4VDNimUm3"&"S9Vi1i95esohXCF3wuKOE8c"", ""'CONSOLIDADO'!G5:AB""), 19, 0), ""-""), """" )"),"https://brotherie.es/brother-v5le/") -> https://brotherie.es/brother-v5le/ | W43: =IFERROR(__xludf.DUMMYFUNCTION("IFERROR(VLOOKUP(G43,IMPORTRANGE(""https://docs.google.com/spreadsheets/d/12RxCea4e5ggM7QGn1XE3FbLQa_-QbCNdBi90OdPjRqg"", ""'Plan de Compras'!D4:Q""), 12, 0), ""NO ESTÁ EN REQ"")"),"Técnica") -> Técnica | X43: =IFERROR(__xludf.DUMMYFUNCTION("IFERROR(VLOOKUP(G43,IMPORTRANGE(""https://docs.google.com/spreadsheets/d/12RxCea4e5ggM7QGn1XE3FbLQa_-QbCNdBi90OdPjRqg"", ""'Plan de Compras'!D4:Q""), 13, 0), """")"),"INTERNACIONAL") -> INTERNACIONAL | Y43: =IFERROR(__xludf.DUMMYFUNCTION("IFERROR(VLOOKUP(G43,IMPORTRANGE(""https://docs.google.com/spreadsheets/d/12RxCea4e5ggM7QGn1XE3FbLQa_-QbCNdBi90OdPjRqg"", ""'Plan de Compras'!D4:Q""), 14, 0), """")"),"GEYDI") -> GEYDI | Z43: =IFERROR(__xludf.DUMMYFUNCTION("IFERROR(VLOOKUP(G43,IMPORTRANGE(""https://docs.google.com/spreadsheets/d/12RxCea4e5ggM7QGn1XE3FbLQa_-QbCNdBi90OdPjRqg"", ""'Plan de Compras'!D4:Q""), 4, 0), """")"),"BORDADORA DOMESTICA DIGITAL, ÁREA DE TRABAJO DE 300 MM X 180 MM") -> BORDADORA DOMESTICA DIGITAL, ÁREA DE TRABAJO DE 300 MM X 180 MM | AA43: =IF(H43=Z43,"TRUE", "FALSE") -> TRUE | AB43: =IFERROR(__xludf.DUMMYFUNCTION("IFERROR(IF(OR(C43=TRUE,C43=""""),VLOOKUP(G43,IMPORTRANGE(""https://docs.google.com/spreadsheets/d/1z9A1Wq-kKrhRNG5RS2a2fKpY1wIhSVz2ZNmP2mOl588/edit?usp=sharing"",""REQ VF!E4:H""),4,0),""NO APLICA""),""GENERAR REQ"")"),"GENERAR REQ") -> GENERAR REQ | AC43: =IFERROR(__xludf.DUMMYFUNCTION("IFERROR(QUERY(IMPORTRANGE(""https://docs.google.com/spreadsheets/d/1z9A1Wq-kKrhRNG5RS2a2fKpY1wIhSVz2ZNmP2mOl588/edit?usp=sharing"",""REQ VF!E4:Q""),""SELECT Col10, Col11, Col12 WHERE Col1 = '""&G43&""'"",0),""NO APLICA"")"),"NO APLICA") -> NO APLICA | AF43: C
C44: FALSE | D44: ACCESORIO | E44: EQUIPOS | F44: ESP-116 | G44: ESP-116.1 | H44: PIE DE TRANSPORTE SUPERIOR MOTORIZADO (1 UND) | I44: 0 | J44: =IFERROR(__xludf.DUMMYFUNCTION("VLOOKUP(G44,IMPORTRANGE(""https://docs.google.com/spreadsheets/d/12RxCea4e5ggM7QGn1XE3FbLQa_-QbCNdBi90OdPjRqg/edit?gid=1692403370#gid=1692403370"", ""'Plan de Compras'!D4:2432""), 8,0)"),"#N/A") -> #N/A | K44: =IF( C44=TRUE, IF(I44=J44,"SI","NO"), "-") -> - | N44: ACCESORIO BROTHER - DIRECT DUAL FEED | O44: BROTHER | P44: DIRECT DUAL FEED | Q44: https://sewingcraft.brother.eu/en/products/machines/combination-machines/combination-machines/innov-is-v5le?utm_source=chatgpt.com | S44: TRUE | T44: BROTHER | U44: INCLUÍDO | W44: =IFERROR(__xludf.DUMMYFUNCTION("IFERROR(VLOOKUP(G44,IMPORTRANGE(""https://docs.google.com/spreadsheets/d/12RxCea4e5ggM7QGn1XE3FbLQa_-QbCNdBi90OdPjRqg"", ""'Plan de Compras'!D4:Q""), 12, 0), ""NO ESTÁ EN REQ"")"),"NO ESTÁ EN REQ") -> NO ESTÁ EN REQ | X44: =IFERROR(__xludf.DUMMYFUNCTION("IFERROR(VLOOKUP(G44,IMPORTRANGE(""https://docs.google.com/spreadsheets/d/12RxCea4e5ggM7QGn1XE3FbLQa_-QbCNdBi90OdPjRqg"", ""'Plan de Compras'!D4:Q""), 13, 0), """")"),"") | Y44: =IFERROR(__xludf.DUMMYFUNCTION("IFERROR(VLOOKUP(G44,IMPORTRANGE(""https://docs.google.com/spreadsheets/d/12RxCea4e5ggM7QGn1XE3FbLQa_-QbCNdBi90OdPjRqg"", ""'Plan de Compras'!D4:Q""), 14, 0), """")"),"") | Z44: =IFERROR(__xludf.DUMMYFUNCTION("IFERROR(VLOOKUP(G44,IMPORTRANGE(""https://docs.google.com/spreadsheets/d/12RxCea4e5ggM7QGn1XE3FbLQa_-QbCNdBi90OdPjRqg"", ""'Plan de Compras'!D4:Q""), 4, 0), """")"),"") | AB44: =IFERROR(__xludf.DUMMYFUNCTION("IFERROR(IF(OR(C44=TRUE,C44=""""),VLOOKUP(G44,IMPORTRANGE(""https://docs.google.com/spreadsheets/d/1z9A1Wq-kKrhRNG5RS2a2fKpY1wIhSVz2ZNmP2mOl588/edit?usp=sharing"",""REQ VF!E4:H""),4,0),""NO APLICA""),""GENERAR REQ"")"),"NO APLICA") -> NO APLICA | AC44: =IFERROR(__xludf.DUMMYFUNCTION("IFERROR(QUERY(IMPORTRANGE(""https://docs.google.com/spreadsheets/d/1z9A1Wq-kKrhRNG5RS2a2fKpY1wIhSVz2ZNmP2mOl588/edit?usp=sharing"",""REQ VF!E4:Q""),""SELECT Col10, Col11, Col12 WHERE Col1 = '""&G44&""'"",0),""NO APLICA"")"),"NO APLICA") -> NO APLICA
C45: FALSE | D45: ACCESORIO | E45: EQUIPOS | F45: ESP-116 | G45: ESP-116.2 | H45: PUNTERO LÁSER (1 UND) | I45: 0 | J45: =IFERROR(__xludf.DUMMYFUNCTION("VLOOKUP(G45,IMPORTRANGE(""https://docs.google.com/spreadsheets/d/12RxCea4e5ggM7QGn1XE3FbLQa_-QbCNdBi90OdPjRqg/edit?gid=1692403370#gid=1692403370"", ""'Plan de Compras'!D4:2432""), 8,0)"),"#N/A") -> #N/A | K45: =IF( C45=TRUE, IF(I45=J45,"SI","NO"), "-") -> - | N45: ACCESORIO BROTHER - LED POINTER | O45: BROTHER | P45: LED POINTER | S45: TRUE | T45: BROTHER | U45: INCLUÍDO | W45: =IFERROR(__xludf.DUMMYFUNCTION("IFERROR(VLOOKUP(G45,IMPORTRANGE(""https://docs.google.com/spreadsheets/d/12RxCea4e5ggM7QGn1XE3FbLQa_-QbCNdBi90OdPjRqg"", ""'Plan de Compras'!D4:Q""), 12, 0), ""NO ESTÁ EN REQ"")"),"NO ESTÁ EN REQ") -> NO ESTÁ EN REQ | X45: =IFERROR(__xludf.DUMMYFUNCTION("IFERROR(VLOOKUP(G45,IMPORTRANGE(""https://docs.google.com/spreadsheets/d/12RxCea4e5ggM7QGn1XE3FbLQa_-QbCNdBi90OdPjRqg"", ""'Plan de Compras'!D4:Q""), 13, 0), """")"),"") | Y45: =IFERROR(__xludf.DUMMYFUNCTION("IFERROR(VLOOKUP(G45,IMPORTRANGE(""https://docs.google.com/spreadsheets/d/12RxCea4e5ggM7QGn1XE3FbLQa_-QbCNdBi90OdPjRqg"", ""'Plan de Compras'!D4:Q""), 14, 0), """")"),"") | Z45: =IFERROR(__xludf.DUMMYFUNCTION("IFERROR(VLOOKUP(G45,IMPORTRANGE(""https://docs.google.com/spreadsheets/d/12RxCea4e5ggM7QGn1XE3FbLQa_-QbCNdBi90OdPjRqg"", ""'Plan de Compras'!D4:Q""), 4, 0), """")"),"") | AB45: =IFERROR(__xludf.DUMMYFUNCTION("IFERROR(IF(OR(C45=TRUE,C45=""""),VLOOKUP(G45,IMPORTRANGE(""https://docs.google.com/spreadsheets/d/1z9A1Wq-kKrhRNG5RS2a2fKpY1wIhSVz2ZNmP2mOl588/edit?usp=sharing"",""REQ VF!E4:H""),4,0),""NO APLICA""),""GENERAR REQ"")"),"NO APLICA") -> NO APLICA | AC45: =IFERROR(__xludf.DUMMYFUNCTION("IFERROR(QUERY(IMPORTRANGE(""https://docs.google.com/spreadsheets/d/1z9A1Wq-kKrhRNG5RS2a2fKpY1wIhSVz2ZNmP2mOl588/edit?usp=sharing"",""REQ VF!E4:Q""),""SELECT Col10, Col11, Col12 WHERE Col1 = '""&G45&""'"",0),""NO APLICA"")"),"NO APLICA") -> NO APLICA
C46: FALSE | D46: ACCESORIO | E46: EQUIPOS | F46: ESP-116 | G46: ESP-116.3 | H46: PIE DE BORDADO MARCADO CON LUZ LED (1 UND) | I46: 0 | J46: =IFERROR(__xludf.DUMMYFUNCTION("VLOOKUP(G46,IMPORTRANGE(""https://docs.google.com/spreadsheets/d/12RxCea4e5ggM7QGn1XE3FbLQa_-QbCNdBi90OdPjRqg/edit?gid=1692403370#gid=1692403370"", ""'Plan de Compras'!D4:2432""), 8,0)"),"#N/A") -> #N/A | K46: =IF( C46=TRUE, IF(I46=J46,"SI","NO"), "-") -> - | N46: ACCESORIO BROTHER - EMBROIDERY FOOT WITH LED POINTER FLED1 | O46: BROTHER | P46: EMBROIDERY FOOT WITH LED POINTER FLED1 | Q46: https://sewingcraft.brother.eu/en/accessories/sewing-machine-accessories/fled1 | S46: TRUE | T46: BROTHER | U46: INCLUÍDO | W46: =IFERROR(__xludf.DUMMYFUNCTION("IFERROR(VLOOKUP(G46,IMPORTRANGE(""https://docs.google.com/spreadsheets/d/12RxCea4e5ggM7QGn1XE3FbLQa_-QbCNdBi90OdPjRqg"", ""'Plan de Compras'!D4:Q""), 12, 0), ""NO ESTÁ EN REQ"")"),"NO ESTÁ EN REQ") -> NO ESTÁ EN REQ | X46: =IFERROR(__xludf.DUMMYFUNCTION("IFERROR(VLOOKUP(G46,IMPORTRANGE(""https://docs.google.com/spreadsheets/d/12RxCea4e5ggM7QGn1XE3FbLQa_-QbCNdBi90OdPjRqg"", ""'Plan de Compras'!D4:Q""), 13, 0), """")"),"") | Y46: =IFERROR(__xludf.DUMMYFUNCTION("IFERROR(VLOOKUP(G46,IMPORTRANGE(""https://docs.google.com/spreadsheets/d/12RxCea4e5ggM7QGn1XE3FbLQa_-QbCNdBi90OdPjRqg"", ""'Plan de Compras'!D4:Q""), 14, 0), """")"),"") | Z46: =IFERROR(__xludf.DUMMYFUNCTION("IFERROR(VLOOKUP(G46,IMPORTRANGE(""https://docs.google.com/spreadsheets/d/12RxCea4e5ggM7QGn1XE3FbLQa_-QbCNdBi90OdPjRqg"", ""'Plan de Compras'!D4:Q""), 4, 0), """")"),"") | AB46: =IFERROR(__xludf.DUMMYFUNCTION("IFERROR(IF(OR(C46=TRUE,C46=""""),VLOOKUP(G46,IMPORTRANGE(""https://docs.google.com/spreadsheets/d/1z9A1Wq-kKrhRNG5RS2a2fKpY1wIhSVz2ZNmP2mOl588/edit?usp=sharing"",""REQ VF!E4:H""),4,0),""NO APLICA""),""GENERAR REQ"")"),"NO APLICA") -> NO APLICA | AC46: =IFERROR(__xludf.DUMMYFUNCTION("IFERROR(QUERY(IMPORTRANGE(""https://docs.google.com/spreadsheets/d/1z9A1Wq-kKrhRNG5RS2a2fKpY1wIhSVz2ZNmP2mOl588/edit?usp=sharing"",""REQ VF!E4:Q""),""SELECT Col10, Col11, Col12 WHERE Col1 = '""&G46&""'"",0),""NO APLICA"")"),"NO APLICA") -> NO APLICA
C47: FALSE | D47: ACCESORIO | E47: EQUIPOS | F47: ESP-116 | G47: ESP-116.4 | H47: BASTIDOR 10 X 10 CM (1 UND) | I47: 0 | J47: =IFERROR(__xludf.DUMMYFUNCTION("VLOOKUP(G47,IMPORTRANGE(""https://docs.google.com/spreadsheets/d/12RxCea4e5ggM7QGn1XE3FbLQa_-QbCNdBi90OdPjRqg/edit?gid=1692403370#gid=1692403370"", ""'Plan de Compras'!D4:2432""), 8,0)"),"#N/A") -> #N/A | K47: =IF( C47=TRUE, IF(I47=J47,"SI","NO"), "-") -> - | N47: ACCESORIO BROTHER - BASTIDOR EF74 | O47: BROTHER | P47: BASTIDOR EF74 | Q47: https://sewingcraft.brother.eu/en/accessories/sewing-machine-accessories/ef74 | S47: TRUE | T47: BROTHER | U47: INCLUÍDO | W47: =IFERROR(__xludf.DUMMYFUNCTION("IFERROR(VLOOKUP(G47,IMPORTRANGE(""https://docs.google.com/spreadsheets/d/12RxCea4e5ggM7QGn1XE3FbLQa_-QbCNdBi90OdPjRqg"", ""'Plan de Compras'!D4:Q""), 12, 0), ""NO ESTÁ EN REQ"")"),"NO ESTÁ EN REQ") -> NO ESTÁ EN REQ | X47: =IFERROR(__xludf.DUMMYFUNCTION("IFERROR(VLOOKUP(G47,IMPORTRANGE(""https://docs.google.com/spreadsheets/d/12RxCea4e5ggM7QGn1XE3FbLQa_-QbCNdBi90OdPjRqg"", ""'Plan de Compras'!D4:Q""), 13, 0), """")"),"") | Y47: =IFERROR(__xludf.DUMMYFUNCTION("IFERROR(VLOOKUP(G47,IMPORTRANGE(""https://docs.google.com/spreadsheets/d/12RxCea4e5ggM7QGn1XE3FbLQa_-QbCNdBi90OdPjRqg"", ""'Plan de Compras'!D4:Q""), 14, 0), """")"),"") | Z47: =IFERROR(__xludf.DUMMYFUNCTION("IFERROR(VLOOKUP(G47,IMPORTRANGE(""https://docs.google.com/spreadsheets/d/12RxCea4e5ggM7QGn1XE3FbLQa_-QbCNdBi90OdPjRqg"", ""'Plan de Compras'!D4:Q""), 4, 0), """")"),"") | AB47: =IFERROR(__xludf.DUMMYFUNCTION("IFERROR(IF(OR(C47=TRUE,C47=""""),VLOOKUP(G47,IMPORTRANGE(""https://docs.google.com/spreadsheets/d/1z9A1Wq-kKrhRNG5RS2a2fKpY1wIhSVz2ZNmP2mOl588/edit?usp=sharing"",""REQ VF!E4:H""),4,0),""NO APLICA""),""GENERAR REQ"")"),"NO APLICA") -> NO APLICA | AC47: =IFERROR(__xludf.DUMMYFUNCTION("IFERROR(QUERY(IMPORTRANGE(""https://docs.google.com/spreadsheets/d/1z9A1Wq-kKrhRNG5RS2a2fKpY1wIhSVz2ZNmP2mOl588/edit?usp=sharing"",""REQ VF!E4:Q""),""SELECT Col10, Col11, Col12 WHERE Col1 = '""&G47&""'"",0),""NO APLICA"")"),"NO APLICA") -> NO APLICA
C48: FALSE | D48: ACCESORIO | E48: EQUIPOS | F48: ESP-116 | G48: ESP-116.5 | H48: BASTIDOR 18 X 13 CM (1 UND) | I48: 0 | J48: =IFERROR(__xludf.DUMMYFUNCTION("VLOOKUP(G48,IMPORTRANGE(""https://docs.google.com/spreadsheets/d/12RxCea4e5ggM7QGn1XE3FbLQa_-QbCNdBi90OdPjRqg/edit?gid=1692403370#gid=1692403370"", ""'Plan de Compras'!D4:2432""), 8,0)"),"#N/A") -> #N/A | K48: =IF( C48=TRUE, IF(I48=J48,"SI","NO"), "-") -> - | N48: ACCESORIO BROTHER - BASTIDOR EF75 | O48: BROTHER | P48: BASTIDOR EF75 | Q48: https://sewingcraft.brother.eu/en/accessories/sewing-machine-accessories/ef75 | S48: TRUE | T48: BROTHER | U48: INCLUÍDO | W48: =IFERROR(__xludf.DUMMYFUNCTION("IFERROR(VLOOKUP(G48,IMPORTRANGE(""https://docs.google.com/spreadsheets/d/12RxCea4e5ggM7QGn1XE3FbLQa_-QbCNdBi90OdPjRqg"", ""'Plan de Compras'!D4:Q""), 12, 0), ""NO ESTÁ EN REQ"")"),"NO ESTÁ EN REQ") -> NO ESTÁ EN REQ | X48: =IFERROR(__xludf.DUMMYFUNCTION("IFERROR(VLOOKUP(G48,IMPORTRANGE(""https://docs.google.com/spreadsheets/d/12RxCea4e5ggM7QGn1XE3FbLQa_-QbCNdBi90OdPjRqg"", ""'Plan de Compras'!D4:Q""), 13, 0), """")"),"") | Y48: =IFERROR(__xludf.DUMMYFUNCTION("IFERROR(VLOOKUP(G48,IMPORTRANGE(""https://docs.google.com/spreadsheets/d/12RxCea4e5ggM7QGn1XE3FbLQa_-QbCNdBi90OdPjRqg"", ""'Plan de Compras'!D4:Q""), 14, 0), """")"),"") | Z48: =IFERROR(__xludf.DUMMYFUNCTION("IFERROR(VLOOKUP(G48,IMPORTRANGE(""https://docs.google.com/spreadsheets/d/12RxCea4e5ggM7QGn1XE3FbLQa_-QbCNdBi90OdPjRqg"", ""'Plan de Compras'!D4:Q""), 4, 0), """")"),"") | AB48: =IFERROR(__xludf.DUMMYFUNCTION("IFERROR(IF(OR(C48=TRUE,C48=""""),VLOOKUP(G48,IMPORTRANGE(""https://docs.google.com/spreadsheets/d/1z9A1Wq-kKrhRNG5RS2a2fKpY1wIhSVz2ZNmP2mOl588/edit?usp=sharing"",""REQ VF!E4:H""),4,0),""NO APLICA""),""GENERAR REQ"")"),"NO APLICA") -> NO APLICA | AC48: =IFERROR(__xludf.DUMMYFUNCTION("IFERROR(QUERY(IMPORTRANGE(""https://docs.google.com/spreadsheets/d/1z9A1Wq-kKrhRNG5RS2a2fKpY1wIhSVz2ZNmP2mOl588/edit?usp=sharing"",""REQ VF!E4:Q""),""SELECT Col10, Col11, Col12 WHERE Col1 = '""&G48&""'"",0),""NO APLICA"")"),"NO APLICA") -> NO APLICA
C49: FALSE | D49: ACCESORIO | E49: EQUIPOS | F49: ESP-116 | G49: ESP-116.6 | H49: BASTIDOR 30 X 18 CM (1 UND) | I49: 0 | J49: =IFERROR(__xludf.DUMMYFUNCTION("VLOOKUP(G49,IMPORTRANGE(""https://docs.google.com/spreadsheets/d/12RxCea4e5ggM7QGn1XE3FbLQa_-QbCNdBi90OdPjRqg/edit?gid=1692403370#gid=1692403370"", ""'Plan de Compras'!D4:2432""), 8,0)"),"#N/A") -> #N/A | K49: =IF( C49=TRUE, IF(I49=J49,"SI","NO"), "-") -> - | N49: ACCESORIO BROTHER - BASTIDOR EF76 | O49: BROTHER | P49: BASTIDOR EF76 | Q49: https://sewingcraft.brother.eu/en/accessories/sewing-machine-accessories/ef76 | S49: TRUE | T49: BROTHER | U49: INCLUÍDO | W49: =IFERROR(__xludf.DUMMYFUNCTION("IFERROR(VLOOKUP(G49,IMPORTRANGE(""https://docs.google.com/spreadsheets/d/12RxCea4e5ggM7QGn1XE3FbLQa_-QbCNdBi90OdPjRqg"", ""'Plan de Compras'!D4:Q""), 12, 0), ""NO ESTÁ EN REQ"")"),"NO ESTÁ EN REQ") -> NO ESTÁ EN REQ | X49: =IFERROR(__xludf.DUMMYFUNCTION("IFERROR(VLOOKUP(G49,IMPORTRANGE(""https://docs.google.com/spreadsheets/d/12RxCea4e5ggM7QGn1XE3FbLQa_-QbCNdBi90OdPjRqg"", ""'Plan de Compras'!D4:Q""), 13, 0), """")"),"") | Y49: =IFERROR(__xludf.DUMMYFUNCTION("IFERROR(VLOOKUP(G49,IMPORTRANGE(""https://docs.google.com/spreadsheets/d/12RxCea4e5ggM7QGn1XE3FbLQa_-QbCNdBi90OdPjRqg"", ""'Plan de Compras'!D4:Q""), 14, 0), """")"),"") | Z49: =IFERROR(__xludf.DUMMYFUNCTION("IFERROR(VLOOKUP(G49,IMPORTRANGE(""https://docs.google.com/spreadsheets/d/12RxCea4e5ggM7QGn1XE3FbLQa_-QbCNdBi90OdPjRqg"", ""'Plan de Compras'!D4:Q""), 4, 0), """")"),"") | AB49: =IFERROR(__xludf.DUMMYFUNCTION("IFERROR(IF(OR(C49=TRUE,C49=""""),VLOOKUP(G49,IMPORTRANGE(""https://docs.google.com/spreadsheets/d/1z9A1Wq-kKrhRNG5RS2a2fKpY1wIhSVz2ZNmP2mOl588/edit?usp=sharing"",""REQ VF!E4:H""),4,0),""NO APLICA""),""GENERAR REQ"")"),"NO APLICA") -> NO APLICA | AC49: =IFERROR(__xludf.DUMMYFUNCTION("IFERROR(QUERY(IMPORTRANGE(""https://docs.google.com/spreadsheets/d/1z9A1Wq-kKrhRNG5RS2a2fKpY1wIhSVz2ZNmP2mOl588/edit?usp=sharing"",""REQ VF!E4:Q""),""SELECT Col10, Col11, Col12 WHERE Col1 = '""&G49&""'"",0),""NO APLICA"")"),"NO APLICA") -> NO APLICA
A50: 18 | B50: TRUE | C50: FALSE | D50: BIEN | E50: EQUIPOS | F50: ESP-117 | G50: ESP-117 | H50: BOTÓN PULSADOR INDUSTRIAL (VERDE, AMARILLO, ROJO) | I50: =SUMIFS('Hoja 10'!$O:$O,'Hoja 10'!$F:$F,$G50) -> 36 | J50: =IFERROR(__xludf.DUMMYFUNCTION("VLOOKUP(G50,IMPORTRANGE(""https://docs.google.com/spreadsheets/d/12RxCea4e5ggM7QGn1XE3FbLQa_-QbCNdBi90OdPjRqg/edit?gid=1692403370#gid=1692403370"", ""'Plan de Compras'!D4:2432""), 8,0)"),"#N/A") -> #N/A | K50: =IF( C50=TRUE, IF(I50=J50,"SI","NO"), "-") -> - | L50: ELECTRICIDAD | M50: 15 Taller_Electricidad_Firmado.pdf | N50: UNO ROJO, UNO VERDE, UNO AMARILLO | O50: =VLOOKUP($G50,'Hoja 10'!$F$4:$AA478, 19,0) -> EAO | P50: =VLOOKUP($G50,'Hoja 10'!$F$4:$AA478, 20,0) -> Botón Pulsador Industrial, Serie 45, 22 mm | Q50: =VLOOKUP($G50,'Hoja 10'!$F$4:$AA478, 21,0) -> https://mexico.newark.com/eao/45-1231-31e6-000-101/illum-industrial-pb-sw-spst-10a/dp/98Y4507 | R50: ESP-117 BOTÓN PULSADOR INDUSTRIAL (VERDE, AMARILLO, ROJO) - CET | S50: TRUE | T50: =IFERROR(__xludf.DUMMYFUNCTION(" IF ( VLOOKUP($G50,IMPORTRANGE(""https://docs.google.com/spreadsheets/d/1Gpl6jkTg7sL4VDNimUm3S9Vi1i95esohXCF3wuKOE8c"", ""'CONSOLIDADO'!G5:AB""), 10, 0) <> 0, IFERROR(VLOOKUP($G50,IMPORTRANGE(""https://docs.google.com/spreadsheets/d/1Gpl6jkTg7sL4VDNimUm3"&"S9Vi1i95esohXCF3wuKOE8c"", ""'CONSOLIDADO'!G5:AB""), 17, 0), ""-""), """" )"),"STECK") -> STECK | U50: =IFERROR(__xludf.DUMMYFUNCTION(" IF ( VLOOKUP($G50,IMPORTRANGE(""https://docs.google.com/spreadsheets/d/1Gpl6jkTg7sL4VDNimUm3S9Vi1i95esohXCF3wuKOE8c"", ""'CONSOLIDADO'!G5:AB""), 10, 0) <> 0, IFERROR(VLOOKUP($G50,IMPORTRANGE(""https://docs.google.com/spreadsheets/d/1Gpl6jkTg7sL4VDNimUm3"&"S9Vi1i95esohXCF3wuKOE8c"", ""'CONSOLIDADO'!G5:AB""), 18, 0), ""-""), """" )"),"VARIOS 6") -> VARIOS 6 | V50: =IFERROR(__xludf.DUMMYFUNCTION(" IF ( VLOOKUP($G50,IMPORTRANGE(""https://docs.google.com/spreadsheets/d/1Gpl6jkTg7sL4VDNimUm3S9Vi1i95esohXCF3wuKOE8c"", ""'CONSOLIDADO'!G5:AB""), 10, 0) <> 0, IFERROR(VLOOKUP($G50,IMPORTRANGE(""https://docs.google.com/spreadsheets/d/1Gpl6jkTg7sL4VDNimUm3"&"S9Vi1i95esohXCF3wuKOE8c"", ""'CONSOLIDADO'!G5:AB""), 19, 0), ""-""), """" )"),"https://bucket-site-steck.s3.sa-east-1.amazonaws.com/ProductDocument/317.pdf") -> https://bucket-site-steck.s3.sa-east-1.amazonaws.com/ProductDocument/317.pdf | W50: =IFERROR(__xludf.DUMMYFUNCTION("IFERROR(VLOOKUP(G50,IMPORTRANGE(""https://docs.google.com/spreadsheets/d/12RxCea4e5ggM7QGn1XE3FbLQa_-QbCNdBi90OdPjRqg"", ""'Plan de Compras'!D4:Q""), 12, 0), ""NO ESTÁ EN REQ"")"),"NO ESTÁ EN REQ") -> NO ESTÁ EN REQ | X50: =IFERROR(__xludf.DUMMYFUNCTION("IFERROR(VLOOKUP(G50,IMPORTRANGE(""https://docs.google.com/spreadsheets/d/12RxCea4e5ggM7QGn1XE3FbLQa_-QbCNdBi90OdPjRqg"", ""'Plan de Compras'!D4:Q""), 13, 0), """")"),"") | Y50: =IFERROR(__xludf.DUMMYFUNCTION("IFERROR(VLOOKUP(G50,IMPORTRANGE(""https://docs.google.com/spreadsheets/d/12RxCea4e5ggM7QGn1XE3FbLQa_-QbCNdBi90OdPjRqg"", ""'Plan de Compras'!D4:Q""), 14, 0), """")"),"") | Z50: =IFERROR(__xludf.DUMMYFUNCTION("IFERROR(VLOOKUP(G50,IMPORTRANGE(""https://docs.google.com/spreadsheets/d/12RxCea4e5ggM7QGn1XE3FbLQa_-QbCNdBi90OdPjRqg"", ""'Plan de Compras'!D4:Q""), 4, 0), """")"),"") | AB50: =IFERROR(__xludf.DUMMYFUNCTION("IFERROR(IF(OR(C50=TRUE,C50=""""),VLOOKUP(G50,IMPORTRANGE(""https://docs.google.com/spreadsheets/d/1z9A1Wq-kKrhRNG5RS2a2fKpY1wIhSVz2ZNmP2mOl588/edit?usp=sharing"",""REQ VF!E4:H""),4,0),""NO APLICA""),""GENERAR REQ"")"),"NO APLICA") -> NO APLICA | AC50: =IFERROR(__xludf.DUMMYFUNCTION("IFERROR(QUERY(IMPORTRANGE(""https://docs.google.com/spreadsheets/d/1z9A1Wq-kKrhRNG5RS2a2fKpY1wIhSVz2ZNmP2mOl588/edit?usp=sharing"",""REQ VF!E4:Q""),""SELECT Col10, Col11, Col12 WHERE Col1 = '""&G50&""'"",0),""NO APLICA"")"),"NO APLICA") -> NO APLICA
C51: TRUE | D51: COMPONENTE | E51: EQUIPOS | F51: ESP-117 | G51: ESP-117.1 | H51: BOTÓN PULSADOR INDUSTRIAL VERDE (1 UND) | I51: =$I$50 -> 36 | J51: =IFERROR(__xludf.DUMMYFUNCTION("VLOOKUP(G51,IMPORTRANGE(""https://docs.google.com/spreadsheets/d/12RxCea4e5ggM7QGn1XE3FbLQa_-QbCNdBi90OdPjRqg/edit?gid=1692403370#gid=1692403370"", ""'Plan de Compras'!D4:2432""), 8,0)"),36.0) -> 36 | K51: =IF( C51=TRUE, IF(I51=J51,"SI","NO"), "-") -> SI | S51: TRUE | T51: STECK | U51: VERDE SLMRN2 | W51: =IFERROR(__xludf.DUMMYFUNCTION("IFERROR(VLOOKUP(G51,IMPORTRANGE(""https://docs.google.com/spreadsheets/d/12RxCea4e5ggM7QGn1XE3FbLQa_-QbCNdBi90OdPjRqg"", ""'Plan de Compras'!D4:Q""), 12, 0), ""NO ESTÁ EN REQ"")"),"Técnica") -> Técnica | X51: =IFERROR(__xludf.DUMMYFUNCTION("IFERROR(VLOOKUP(G51,IMPORTRANGE(""https://docs.google.com/spreadsheets/d/12RxCea4e5ggM7QGn1XE3FbLQa_-QbCNdBi90OdPjRqg"", ""'Plan de Compras'!D4:Q""), 13, 0), """")"),"NACIONAL") -> NACIONAL | Y51: =IFERROR(__xludf.DUMMYFUNCTION("IFERROR(VLOOKUP(G51,IMPORTRANGE(""https://docs.google.com/spreadsheets/d/12RxCea4e5ggM7QGn1XE3FbLQa_-QbCNdBi90OdPjRqg"", ""'Plan de Compras'!D4:Q""), 14, 0), """")"),"ALFIO") -> ALFIO | Z51: =IFERROR(__xludf.DUMMYFUNCTION("IFERROR(VLOOKUP(G51,IMPORTRANGE(""https://docs.google.com/spreadsheets/d/12RxCea4e5ggM7QGn1XE3FbLQa_-QbCNdBi90OdPjRqg"", ""'Plan de Compras'!D4:Q""), 4, 0), """")"),"BOTÓN PULSADOR INDUSTRIAL VERDE (1 UND)") -> BOTÓN PULSADOR INDUSTRIAL VERDE (1 UND) | AA51: =IF(H51=Z51,"TRUE", "FALSE") -> TRUE | AB51: =IFERROR(__xludf.DUMMYFUNCTION("IFERROR(IF(OR(C51=TRUE,C51=""""),VLOOKUP(G51,IMPORTRANGE(""https://docs.google.com/spreadsheets/d/1z9A1Wq-kKrhRNG5RS2a2fKpY1wIhSVz2ZNmP2mOl588/edit?usp=sharing"",""REQ VF!E4:H""),4,0),""NO APLICA""),""GENERAR REQ"")"),"GENERAR REQ") -> GENERAR REQ | AC51: =IFERROR(__xludf.DUMMYFUNCTION("IFERROR(QUERY(IMPORTRANGE(""https://docs.google.com/spreadsheets/d/1z9A1Wq-kKrhRNG5RS2a2fKpY1wIhSVz2ZNmP2mOl588/edit?usp=sharing"",""REQ VF!E4:Q""),""SELECT Col10, Col11, Col12 WHERE Col1 = '""&G51&""'"",0),""NO APLICA"")"),"NO APLICA") -> NO APLICA
C52: TRUE | D52: COMPONENTE | E52: EQUIPOS | F52: ESP-117 | G52: ESP-117.2 | H52: BOTÓN PULSADOR INDUSTRIAL AMARILLO (1 UND) | I52: =$I$50 -> 36 | J52: =IFERROR(__xludf.DUMMYFUNCTION("VLOOKUP(G52,IMPORTRANGE(""https://docs.google.com/spreadsheets/d/12RxCea4e5ggM7QGn1XE3FbLQa_-QbCNdBi90OdPjRqg/edit?gid=1692403370#gid=1692403370"", ""'Plan de Compras'!D4:2432""), 8,0)"),36.0) -> 36 | K52: =IF( C52=TRUE, IF(I52=J52,"SI","NO"), "-") -> SI | S52: TRUE | T52: STECK | U52: AMAARILLO SLMRN3 | W52: =IFERROR(__xludf.DUMMYFUNCTION("IFERROR(VLOOKUP(G52,IMPORTRANGE(""https://docs.google.com/spreadsheets/d/12RxCea4e5ggM7QGn1XE3FbLQa_-QbCNdBi90OdPjRqg"", ""'Plan de Compras'!D4:Q""), 12, 0), ""NO ESTÁ EN REQ"")"),"Técnica") -> Técnica | X52: =IFERROR(__xludf.DUMMYFUNCTION("IFERROR(VLOOKUP(G52,IMPORTRANGE(""https://docs.google.com/spreadsheets/d/12RxCea4e5ggM7QGn1XE3FbLQa_-QbCNdBi90OdPjRqg"", ""'Plan de Compras'!D4:Q""), 13, 0), """")"),"NACIONAL") -> NACIONAL | Y52: =IFERROR(__xludf.DUMMYFUNCTION("IFERROR(VLOOKUP(G52,IMPORTRANGE(""https://docs.google.com/spreadsheets/d/12RxCea4e5ggM7QGn1XE3FbLQa_-QbCNdBi90OdPjRqg"", ""'Plan de Compras'!D4:Q""), 14, 0), """")"),"ALFIO") -> ALFIO | Z52: =IFERROR(__xludf.DUMMYFUNCTION("IFERROR(VLOOKUP(G52,IMPORTRANGE(""https://docs.google.com/spreadsheets/d/12RxCea4e5ggM7QGn1XE3FbLQa_-QbCNdBi90OdPjRqg"", ""'Plan de Compras'!D4:Q""), 4, 0), """")"),"BOTÓN PULSADOR INDUSTRIAL AMARILLO (1 UND)") -> BOTÓN PULSADOR INDUSTRIAL AMARILLO (1 UND) | AA52: =IF(H52=Z52,"TRUE", "FALSE") -> TRUE | AB52: =IFERROR(__xludf.DUMMYFUNCTION("IFERROR(IF(OR(C52=TRUE,C52=""""),VLOOKUP(G52,IMPORTRANGE(""https://docs.google.com/spreadsheets/d/1z9A1Wq-kKrhRNG5RS2a2fKpY1wIhSVz2ZNmP2mOl588/edit?usp=sharing"",""REQ VF!E4:H""),4,0),""NO APLICA""),""GENERAR REQ"")"),"GENERAR REQ") -> GENERAR REQ | AC52: =IFERROR(__xludf.DUMMYFUNCTION("IFERROR(QUERY(IMPORTRANGE(""https://docs.google.com/spreadsheets/d/1z9A1Wq-kKrhRNG5RS2a2fKpY1wIhSVz2ZNmP2mOl588/edit?usp=sharing"",""REQ VF!E4:Q""),""SELECT Col10, Col11, Col12 WHERE Col1 = '""&G52&""'"",0),""NO APLICA"")"),"NO APLICA") -> NO APLICA
C53: TRUE | D53: COMPONENTE | E53: EQUIPOS | F53: ESP-117 | G53: ESP-117.3 | H53: BOTÓN PULSADOR INDUSTRIAL ROJO (1 UND) | I53: =$I$50 -> 36 | J53: =IFERROR(__xludf.DUMMYFUNCTION("VLOOKUP(G53,IMPORTRANGE(""https://docs.google.com/spreadsheets/d/12RxCea4e5ggM7QGn1XE3FbLQa_-QbCNdBi90OdPjRqg/edit?gid=1692403370#gid=1692403370"", ""'Plan de Compras'!D4:2432""), 8,0)"),36.0) -> 36 | K53: =IF( C53=TRUE, IF(I53=J53,"SI","NO"), "-") -> SI | S53: TRUE | T53: STECK | U53: ROJO SLMRN1 | W53: =IFERROR(__xludf.DUMMYFUNCTION("IFERROR(VLOOKUP(G53,IMPORTRANGE(""https://docs.google.com/spreadsheets/d/12RxCea4e5ggM7QGn1XE3FbLQa_-QbCNdBi90OdPjRqg"", ""'Plan de Compras'!D4:Q""), 12, 0), ""NO ESTÁ EN REQ"")"),"Técnica") -> Técnica | X53: =IFERROR(__xludf.DUMMYFUNCTION("IFERROR(VLOOKUP(G53,IMPORTRANGE(""https://docs.google.com/spreadsheets/d/12RxCea4e5ggM7QGn1XE3FbLQa_-QbCNdBi90OdPjRqg"", ""'Plan de Compras'!D4:Q""), 13, 0), """")"),"NACIONAL") -> NACIONAL | Y53: =IFERROR(__xludf.DUMMYFUNCTION("IFERROR(VLOOKUP(G53,IMPORTRANGE(""https://docs.google.com/spreadsheets/d/12RxCea4e5ggM7QGn1XE3FbLQa_-QbCNdBi90OdPjRqg"", ""'Plan de Compras'!D4:Q""), 14, 0), """")"),"ALFIO") -> ALFIO | Z53: =IFERROR(__xludf.DUMMYFUNCTION("IFERROR(VLOOKUP(G53,IMPORTRANGE(""https://docs.google.com/spreadsheets/d/12RxCea4e5ggM7QGn1XE3FbLQa_-QbCNdBi90OdPjRqg"", ""'Plan de Compras'!D4:Q""), 4, 0), """")"),"BOTÓN PULSADOR INDUSTRIAL ROJO (1 UND)") -> BOTÓN PULSADOR INDUSTRIAL ROJO (1 UND) | AA53: =IF(H53=Z53,"TRUE", "FALSE") -> TRUE | AB53: =IFERROR(__xludf.DUMMYFUNCTION("IFERROR(IF(OR(C53=TRUE,C53=""""),VLOOKUP(G53,IMPORTRANGE(""https://docs.google.com/spreadsheets/d/1z9A1Wq-kKrhRNG5RS2a2fKpY1wIhSVz2ZNmP2mOl588/edit?usp=sharing"",""REQ VF!E4:H""),4,0),""NO APLICA""),""GENERAR REQ"")"),"GENERAR REQ") -> GENERAR REQ | AC53: =IFERROR(__xludf.DUMMYFUNCTION("IFERROR(QUERY(IMPORTRANGE(""https://docs.google.com/spreadsheets/d/1z9A1Wq-kKrhRNG5RS2a2fKpY1wIhSVz2ZNmP2mOl588/edit?usp=sharing"",""REQ VF!E4:Q""),""SELECT Col10, Col11, Col12 WHERE Col1 = '""&G53&""'"",0),""NO APLICA"")"),"NO APLICA") -> NO APLICA
C54: TRUE | D54: COMPONENTE | E54: EQUIPOS | F54: ESP-117 | G54: ESP-117.4 | H54: BLOQUE DE CONTACTO (3 UND) | I54: =I50*3 -> 108 | J54: =IFERROR(__xludf.DUMMYFUNCTION("VLOOKUP(G54,IMPORTRANGE(""https://docs.google.com/spreadsheets/d/12RxCea4e5ggM7QGn1XE3FbLQa_-QbCNdBi90OdPjRqg/edit?gid=1692403370#gid=1692403370"", ""'Plan de Compras'!D4:2432""), 8,0)"),108.0) -> 108 | K54: =IF( C54=TRUE, IF(I54=J54,"SI","NO"), "-") -> SI | S54: TRUE | T54: STECK | U54: SLPL42 | W54: =IFERROR(__xludf.DUMMYFUNCTION("IFERROR(VLOOKUP(G54,IMPORTRANGE(""https://docs.google.com/spreadsheets/d/12RxCea4e5ggM7QGn1XE3FbLQa_-QbCNdBi90OdPjRqg"", ""'Plan de Compras'!D4:Q""), 12, 0), ""NO ESTÁ EN REQ"")"),"Simple") -> Simple | X54: =IFERROR(__xludf.DUMMYFUNCTION("IFERROR(VLOOKUP(G54,IMPORTRANGE(""https://docs.google.com/spreadsheets/d/12RxCea4e5ggM7QGn1XE3FbLQa_-QbCNdBi90OdPjRqg"", ""'Plan de Compras'!D4:Q""), 13, 0), """")"),"NACIONAL") -> NACIONAL | Y54: =IFERROR(__xludf.DUMMYFUNCTION("IFERROR(VLOOKUP(G54,IMPORTRANGE(""https://docs.google.com/spreadsheets/d/12RxCea4e5ggM7QGn1XE3FbLQa_-QbCNdBi90OdPjRqg"", ""'Plan de Compras'!D4:Q""), 14, 0), """")"),"JESSICA") -> JESSICA | Z54: =IFERROR(__xludf.DUMMYFUNCTION("IFERROR(VLOOKUP(G54,IMPORTRANGE(""https://docs.google.com/spreadsheets/d/12RxCea4e5ggM7QGn1XE3FbLQa_-QbCNdBi90OdPjRqg"", ""'Plan de Compras'!D4:Q""), 4, 0), """")"),"BLOQUE DE CONTACTO (3 UND)") -> BLOQUE DE CONTACTO (3 UND) | AB54: =IFERROR(__xludf.DUMMYFUNCTION("IFERROR(IF(OR(C54=TRUE,C54=""""),VLOOKUP(G54,IMPORTRANGE(""https://docs.google.com/spreadsheets/d/1z9A1Wq-kKrhRNG5RS2a2fKpY1wIhSVz2ZNmP2mOl588/edit?usp=sharing"",""REQ VF!E4:H""),4,0),""NO APLICA""),""GENERAR REQ"")"),"GENERAR REQ") -> GENERAR REQ | AC54: =IFERROR(__xludf.DUMMYFUNCTION("IFERROR(QUERY(IMPORTRANGE(""https://docs.google.com/spreadsheets/d/1z9A1Wq-kKrhRNG5RS2a2fKpY1wIhSVz2ZNmP2mOl588/edit?usp=sharing"",""REQ VF!E4:Q""),""SELECT Col10, Col11, Col12 WHERE Col1 = '""&G54&""'"",0),""NO APLICA"")"),"NO APLICA") -> NO APLICA
A55: 19 | B55: TRUE | C55: TRUE | D55: BIEN | E55: EQUIPOS | F55: ESP-118 | G55: ESP-118 | H55: CAMPANA EXTRACTORA ISLA CON EQUIPOS DE EXTRACCIÓN | I55: =SUMIFS('Hoja 10'!$O:$O,'Hoja 10'!$F:$F,$G55) -> 1 | J55: =IFERROR(__xludf.DUMMYFUNCTION("VLOOKUP(G55,IMPORTRANGE(""https://docs.google.com/spreadsheets/d/12RxCea4e5ggM7QGn1XE3FbLQa_-QbCNdBi90OdPjRqg/edit?gid=1692403370#gid=1692403370"", ""'Plan de Compras'!D4:2432""), 8,0)"),1.0) -> 1 | K55: =IF( C55=TRUE, IF(I55=J55,"SI","NO"), "-") -> SI | L55: COCINA Y REPOSTERÍA | M55: 5 Taller_Cocina y Respostería_Firmado.pdf | O55: =VLOOKUP($G55,'Hoja 10'!$F$4:$AA478, 19,0) -> BOSCH | P55: =VLOOKUP($G55,'Hoja 10'!$F$4:$AA478, 20,0) -> DIB091E50 | Q55: =VLOOKUP($G55,'Hoja 10'!$F$4:$AA478, 21,0) -> https://www.bosch-home.pe/electrodomesticos/DIB091E50#/Tabs=section-technicalspecs/Togglebox=manuals/ | R55: ESP-118 CAMPANA EXTRACTORA ISLA CON EQUIPOS DE EXTRACCIÓN - CET | S55: TRUE | T55: =IFERROR(__xludf.DUMMYFUNCTION(" IF ( VLOOKUP($G55,IMPORTRANGE(""https://docs.google.com/spreadsheets/d/1Gpl6jkTg7sL4VDNimUm3S9Vi1i95esohXCF3wuKOE8c"", ""'CONSOLIDADO'!G5:AB""), 10, 0) <> 0, IFERROR(VLOOKUP($G55,IMPORTRANGE(""https://docs.google.com/spreadsheets/d/1Gpl6jkTg7sL4VDNimUm3"&"S9Vi1i95esohXCF3wuKOE8c"", ""'CONSOLIDADO'!G5:AB""), 17, 0), ""-""), """" )"),"TEKA") -> TEKA | U55: =IFERROR(__xludf.DUMMYFUNCTION(" IF ( VLOOKUP($G55,IMPORTRANGE(""https://docs.google.com/spreadsheets/d/1Gpl6jkTg7sL4VDNimUm3S9Vi1i95esohXCF3wuKOE8c"", ""'CONSOLIDADO'!G5:AB""), 10, 0) <> 0, IFERROR(VLOOKUP($G55,IMPORTRANGE(""https://docs.google.com/spreadsheets/d/1Gpl6jkTg7sL4VDNimUm3"&"S9Vi1i95esohXCF3wuKOE8c"", ""'CONSOLIDADO'!G5:AB""), 18, 0), ""-""), """" )"),"DPL Isla 1180") -> DPL Isla 1180 | V55: =IFERROR(__xludf.DUMMYFUNCTION(" IF ( VLOOKUP($G55,IMPORTRANGE(""https://docs.google.com/spreadsheets/d/1Gpl6jkTg7sL4VDNimUm3S9Vi1i95esohXCF3wuKOE8c"", ""'CONSOLIDADO'!G5:AB""), 10, 0) <> 0, IFERROR(VLOOKUP($G55,IMPORTRANGE(""https://docs.google.com/spreadsheets/d/1Gpl6jkTg7sL4VDNimUm3"&"S9Vi1i95esohXCF3wuKOE8c"", ""'CONSOLIDADO'!G5:AB""), 19, 0), ""-""), """" )"),"https://www.teka.com/es-pe/producto/dpl-isla-1180_40483180/") -> https://www.teka.com/es-pe/producto/dpl-isla-1180_40483180/ | W55: =IFERROR(__xludf.DUMMYFUNCTION("IFERROR(VLOOKUP(G55,IMPORTRANGE(""https://docs.google.com/spreadsheets/d/12RxCea4e5ggM7QGn1XE3FbLQa_-QbCNdBi90OdPjRqg"", ""'Plan de Compras'!D4:Q""), 12, 0), ""NO ESTÁ EN REQ"")"),"Técnica") -> Técnica | X55: =IFERROR(__xludf.DUMMYFUNCTION("IFERROR(VLOOKUP(G55,IMPORTRANGE(""https://docs.google.com/spreadsheets/d/12RxCea4e5ggM7QGn1XE3FbLQa_-QbCNdBi90OdPjRqg"", ""'Plan de Compras'!D4:Q""), 13, 0), """")"),"NACIONAL") -> NACIONAL | Y55: =IFERROR(__xludf.DUMMYFUNCTION("IFERROR(VLOOKUP(G55,IMPORTRANGE(""https://docs.google.com/spreadsheets/d/12RxCea4e5ggM7QGn1XE3FbLQa_-QbCNdBi90OdPjRqg"", ""'Plan de Compras'!D4:Q""), 14, 0), """")"),"JESSICA") -> JESSICA | Z55: =IFERROR(__xludf.DUMMYFUNCTION("IFERROR(VLOOKUP(G55,IMPORTRANGE(""https://docs.google.com/spreadsheets/d/12RxCea4e5ggM7QGn1XE3FbLQa_-QbCNdBi90OdPjRqg"", ""'Plan de Compras'!D4:Q""), 4, 0), """")"),"CAMPANA EXTRACTORA ISLA CON EQUIPOS DE EXTRACCIÓN") -> CAMPANA EXTRACTORA ISLA CON EQUIPOS DE EXTRACCIÓN | AA55: =IF(H55=Z55,"TRUE", "FALSE") -> TRUE | AB55: =IFERROR(__xludf.DUMMYFUNCTION("IFERROR(IF(OR(C55=TRUE,C55=""""),VLOOKUP(G55,IMPORTRANGE(""https://docs.google.com/spreadsheets/d/1z9A1Wq-kKrhRNG5RS2a2fKpY1wIhSVz2ZNmP2mOl588/edit?usp=sharing"",""REQ VF!E4:H""),4,0),""NO APLICA""),""GENERAR REQ"")"),"GENERAR REQ") -> GENERAR REQ | AC55: =IFERROR(__xludf.DUMMYFUNCTION("IFERROR(QUERY(IMPORTRANGE(""https://docs.google.com/spreadsheets/d/1z9A1Wq-kKrhRNG5RS2a2fKpY1wIhSVz2ZNmP2mOl588/edit?usp=sharing"",""REQ VF!E4:Q""),""SELECT Col10, Col11, Col12 WHERE Col1 = '""&G55&""'"",0),""NO APLICA"")"),"NO APLICA") -> NO APLICA
B56: FALSE | C56: TRUE | D56: ACCESORIO | G56: ESP-118.1 | H56: ACCESORIOS DE INSTALACIÓN | I56: 1 | J56: =IFERROR(__xludf.DUMMYFUNCTION("VLOOKUP(G56,IMPORTRANGE(""https://docs.google.com/spreadsheets/d/12RxCea4e5ggM7QGn1XE3FbLQa_-QbCNdBi90OdPjRqg/edit?gid=1692403370#gid=1692403370"", ""'Plan de Compras'!D4:2432""), 8,0)"),"#N/A") -> #N/A | K56: =IF( C56=TRUE, IF(I56=J56,"SI","NO"), "-") -> #N/A | S56: FALSE
A57: 20 | B57: TRUE | C57: TRUE | D57: BIEN | E57: EQUIPOS | F57: ESP-119 | G57: ESP-119 | H57: CAPACÍMETRO DIGITAL | I57: =SUMIFS('Hoja 10'!$O:$O,'Hoja 10'!$F:$F,$G57) -> 4 | J57: =IFERROR(__xludf.DUMMYFUNCTION("VLOOKUP(G57,IMPORTRANGE(""https://docs.google.com/spreadsheets/d/12RxCea4e5ggM7QGn1XE3FbLQa_-QbCNdBi90OdPjRqg/edit?gid=1692403370#gid=1692403370"", ""'Plan de Compras'!D4:2432""), 8,0)"),4.0) -> 4 | K57: =IF( C57=TRUE, IF(I57=J57,"SI","NO"), "-") -> SI | L57: ELECTRÓNICA | M57: 11 Taller_Electrónica_Firmado.pdf | O57: =VLOOKUP($G57,'Hoja 10'!$F$4:$AA478, 19,0) -> B&K Precision | P57: =VLOOKUP($G57,'Hoja 10'!$F$4:$AA478, 20,0) -> 879B | Q57: =VLOOKUP($G57,'Hoja 10'!$F$4:$AA478, 21,0) -> https://www.bkprecision.com/products/component-testers/879B | R57: ESP-119 CAPACÍMETRO DIGITAL - CET | S57: TRUE | T57: =IFERROR(__xludf.DUMMYFUNCTION(" IF ( VLOOKUP($G57,IMPORTRANGE(""https://docs.google.com/spreadsheets/d/1Gpl6jkTg7sL4VDNimUm3S9Vi1i95esohXCF3wuKOE8c"", ""'CONSOLIDADO'!G5:AB""), 10, 0) <> 0, IFERROR(VLOOKUP($G57,IMPORTRANGE(""https://docs.google.com/spreadsheets/d/1Gpl6jkTg7sL4VDNimUm3"&"S9Vi1i95esohXCF3wuKOE8c"", ""'CONSOLIDADO'!G5:AB""), 17, 0), ""-""), """" )"),"BK PRECISION") -> BK PRECISION | U57: =IFERROR(__xludf.DUMMYFUNCTION(" IF ( VLOOKUP($G57,IMPORTRANGE(""https://docs.google.com/spreadsheets/d/1Gpl6jkTg7sL4VDNimUm3S9Vi1i95esohXCF3wuKOE8c"", ""'CONSOLIDADO'!G5:AB""), 10, 0) <> 0, IFERROR(VLOOKUP($G57,IMPORTRANGE(""https://docs.google.com/spreadsheets/d/1Gpl6jkTg7sL4VDNimUm3"&"S9Vi1i95esohXCF3wuKOE8c"", ""'CONSOLIDADO'!G5:AB""), 18, 0), ""-""), """" )"),880.0) -> 880 | V57: =IFERROR(__xludf.DUMMYFUNCTION(" IF ( VLOOKUP($G57,IMPORTRANGE(""https://docs.google.com/spreadsheets/d/1Gpl6jkTg7sL4VDNimUm3S9Vi1i95esohXCF3wuKOE8c"", ""'CONSOLIDADO'!G5:AB""), 10, 0) <> 0, IFERROR(VLOOKUP($G57,IMPORTRANGE(""https://docs.google.com/spreadsheets/d/1Gpl6jkTg7sL4VDNimUm3"&"S9Vi1i95esohXCF3wuKOE8c"", ""'CONSOLIDADO'!G5:AB""), 19, 0), ""-""), """" )"),"https://cl.rsdelivers.com/product/bk-precision/bk880/medidor-lcr-bk-precision-de-mano-bk880-1000-h/20-mf/10-m%CF%89-frecuencia-max-100-khz/1752538") -> https://cl.rsdelivers.com/product/bk-precision/bk880/medidor-lcr-bk-precision-de-mano-bk880-1000-h/20-mf/10-m%CF%89-frecuencia-max-100-khz/1752538 | W57: =IFERROR(__xludf.DUMMYFUNCTION("IFERROR(VLOOKUP(G57,IMPORTRANGE(""https://docs.google.com/spreadsheets/d/12RxCea4e5ggM7QGn1XE3FbLQa_-QbCNdBi90OdPjRqg"", ""'Plan de Compras'!D4:Q""), 12, 0), ""NO ESTÁ EN REQ"")"),"Técnica") -> Técnica | X57: =IFERROR(__xludf.DUMMYFUNCTION("IFERROR(VLOOKUP(G57,IMPORTRANGE(""https://docs.google.com/spreadsheets/d/12RxCea4e5ggM7QGn1XE3FbLQa_-QbCNdBi90OdPjRqg"", ""'Plan de Compras'!D4:Q""), 13, 0), """")"),"INTERNACIONAL") -> INTERNACIONAL | Y57: =IFERROR(__xludf.DUMMYFUNCTION("IFERROR(VLOOKUP(G57,IMPORTRANGE(""https://docs.google.com/spreadsheets/d/12RxCea4e5ggM7QGn1XE3FbLQa_-QbCNdBi90OdPjRqg"", ""'Plan de Compras'!D4:Q""), 14, 0), """")"),"ALEJANDRA") -> ALEJANDRA | Z57: =IFERROR(__xludf.DUMMYFUNCTION("IFERROR(VLOOKUP(G57,IMPORTRANGE(""https://docs.google.com/spreadsheets/d/12RxCea4e5ggM7QGn1XE3FbLQa_-QbCNdBi90OdPjRqg"", ""'Plan de Compras'!D4:Q""), 4, 0), """")"),"CAPACÍMETRO DIGITAL") -> CAPACÍMETRO DIGITAL | AA57: =IF(H57=Z57,"TRUE", "FALSE") -> TRUE | AB57: =IFERROR(__xludf.DUMMYFUNCTION("IFERROR(IF(OR(C57=TRUE,C57=""""),VLOOKUP(G57,IMPORTRANGE(""https://docs.google.com/spreadsheets/d/1z9A1Wq-kKrhRNG5RS2a2fKpY1wIhSVz2ZNmP2mOl588/edit?usp=sharing"",""REQ VF!E4:H""),4,0),""NO APLICA""),""GENERAR REQ"")"),"GENERAR REQ") -> GENERAR REQ | AC57: =IFERROR(__xludf.DUMMYFUNCTION("IFERROR(QUERY(IMPORTRANGE(""https://docs.google.com/spreadsheets/d/1z9A1Wq-kKrhRNG5RS2a2fKpY1wIhSVz2ZNmP2mOl588/edit?usp=sharing"",""REQ VF!E4:Q""),""SELECT Col10, Col11, Col12 WHERE Col1 = '""&G57&""'"",0),""NO APLICA"")"),"NO APLICA") -> NO APLICA
A58: 21 | B58: TRUE | C58: TRUE | D58: BIEN | E58: EQUIPOS | F58: ESP-120 | G58: ESP-120 | H58: CARGADOR DE BATERÍA | I58: =SUMIFS('Hoja 10'!$O:$O,'Hoja 10'!$F:$F,$G58) -> 3 | J58: =IFERROR(__xludf.DUMMYFUNCTION("VLOOKUP(G58,IMPORTRANGE(""https://docs.google.com/spreadsheets/d/12RxCea4e5ggM7QGn1XE3FbLQa_-QbCNdBi90OdPjRqg/edit?gid=1692403370#gid=1692403370"", ""'Plan de Compras'!D4:2432""), 8,0)"),3.0) -> 3 | K58: =IF( C58=TRUE, IF(I58=J58,"SI","NO"), "-") -> SI | L58: MECÁNICA AUTOMOTRÍZ | M58: 1 Taller_Mecanica_Automotriz_Firmado.pdf | O58: =VLOOKUP($G58,'Hoja 10'!$F$4:$AA478, 19,0) -> TELWIN | P58: =VLOOKUP($G58,'Hoja 10'!$F$4:$AA478, 20,0) -> SPRINTER 4000 START 230V 12-24V | Q58: =VLOOKUP($G58,'Hoja 10'!$F$4:$AA478, 21,0) -> https://drive.google.com/file/d/1_jn_UgeZqoo6IhAYYliXXq72AL2uHU93/view?usp=sharing | R58: ESP-120 CARGADOR DE BATERÍA - CET | S58: TRUE | T58: =IFERROR(__xludf.DUMMYFUNCTION(" IF ( VLOOKUP($G58,IMPORTRANGE(""https://docs.google.com/spreadsheets/d/1Gpl6jkTg7sL4VDNimUm3S9Vi1i95esohXCF3wuKOE8c"", ""'CONSOLIDADO'!G5:AB""), 10, 0) <> 0, IFERROR(VLOOKUP($G58,IMPORTRANGE(""https://docs.google.com/spreadsheets/d/1Gpl6jkTg7sL4VDNimUm3"&"S9Vi1i95esohXCF3wuKOE8c"", ""'CONSOLIDADO'!G5:AB""), 17, 0), ""-""), """" )"),"TELWIN") -> TELWIN | U58: =IFERROR(__xludf.DUMMYFUNCTION(" IF ( VLOOKUP($G58,IMPORTRANGE(""https://docs.google.com/spreadsheets/d/1Gpl6jkTg7sL4VDNimUm3S9Vi1i95esohXCF3wuKOE8c"", ""'CONSOLIDADO'!G5:AB""), 10, 0) <> 0, IFERROR(VLOOKUP($G58,IMPORTRANGE(""https://docs.google.com/spreadsheets/d/1Gpl6jkTg7sL4VDNimUm3"&"S9Vi1i95esohXCF3wuKOE8c"", ""'CONSOLIDADO'!G5:AB""), 18, 0), ""-""), """" )"),"SPRINTER 4000 START") -> SPRINTER 4000 START | V58: =IFERROR(__xludf.DUMMYFUNCTION(" IF ( VLOOKUP($G58,IMPORTRANGE(""https://docs.google.com/spreadsheets/d/1Gpl6jkTg7sL4VDNimUm3S9Vi1i95esohXCF3wuKOE8c"", ""'CONSOLIDADO'!G5:AB""), 10, 0) <> 0, IFERROR(VLOOKUP($G58,IMPORTRANGE(""https://docs.google.com/spreadsheets/d/1Gpl6jkTg7sL4VDNimUm3"&"S9Vi1i95esohXCF3wuKOE8c"", ""'CONSOLIDADO'!G5:AB""), 19, 0), ""-""), """" )"),"https://www.telwin.com/intl/es/productos/cargadores-de-bateria-y-arrancadores/829491") -> https://www.telwin.com/intl/es/productos/cargadores-de-bateria-y-arrancadores/829491 | W58: =IFERROR(__xludf.DUMMYFUNCTION("IFERROR(VLOOKUP(G58,IMPORTRANGE(""https://docs.google.com/spreadsheets/d/12RxCea4e5ggM7QGn1XE3FbLQa_-QbCNdBi90OdPjRqg"", ""'Plan de Compras'!D4:Q""), 12, 0), ""NO ESTÁ EN REQ"")"),"Técnica") -> Técnica | X58: =IFERROR(__xludf.DUMMYFUNCTION("IFERROR(VLOOKUP(G58,IMPORTRANGE(""https://docs.google.com/spreadsheets/d/12RxCea4e5ggM7QGn1XE3FbLQa_-QbCNdBi90OdPjRqg"", ""'Plan de Compras'!D4:Q""), 13, 0), """")"),"NACIONAL") -> NACIONAL | Y58: =IFERROR(__xludf.DUMMYFUNCTION("IFERROR(VLOOKUP(G58,IMPORTRANGE(""https://docs.google.com/spreadsheets/d/12RxCea4e5ggM7QGn1XE3FbLQa_-QbCNdBi90OdPjRqg"", ""'Plan de Compras'!D4:Q""), 14, 0), """")"),"ALFIO") -> ALFIO | Z58: =IFERROR(__xludf.DUMMYFUNCTION("IFERROR(VLOOKUP(G58,IMPORTRANGE(""https://docs.google.com/spreadsheets/d/12RxCea4e5ggM7QGn1XE3FbLQa_-QbCNdBi90OdPjRqg"", ""'Plan de Compras'!D4:Q""), 4, 0), """")"),"CARGADOR DE BATERÍA") -> CARGADOR DE BATERÍA | AA58: =IF(H58=Z58,"TRUE", "FALSE") -> TRUE | AB58: =IFERROR(__xludf.DUMMYFUNCTION("IFERROR(IF(OR(C58=TRUE,C58=""""),VLOOKUP(G58,IMPORTRANGE(""https://docs.google.com/spreadsheets/d/1z9A1Wq-kKrhRNG5RS2a2fKpY1wIhSVz2ZNmP2mOl588/edit?usp=sharing"",""REQ VF!E4:H""),4,0),""NO APLICA""),""GENERAR REQ"")"),"GENERAR REQ") -> GENERAR REQ | AC58: =IFERROR(__xludf.DUMMYFUNCTION("IFERROR(QUERY(IMPORTRANGE(""https://docs.google.com/spreadsheets/d/1z9A1Wq-kKrhRNG5RS2a2fKpY1wIhSVz2ZNmP2mOl588/edit?usp=sharing"",""REQ VF!E4:Q""),""SELECT Col10, Col11, Col12 WHERE Col1 = '""&G58&""'"",0),""NO APLICA"")"),"NO APLICA") -> NO APLICA | AF58: C
A59: 22 | B59: TRUE | C59: TRUE | D59: BIEN | E59: EQUIPOS | F59: ESP-121 | G59: ESP-121 | H59: CAUTÍN | I59: =SUMIFS('Hoja 10'!$O:$O,'Hoja 10'!$F:$F,$G59) -> 4 | J59: =IFERROR(__xludf.DUMMYFUNCTION("VLOOKUP(G59,IMPORTRANGE(""https://docs.google.com/spreadsheets/d/12RxCea4e5ggM7QGn1XE3FbLQa_-QbCNdBi90OdPjRqg/edit?gid=1692403370#gid=1692403370"", ""'Plan de Compras'!D4:2432""), 8,0)"),4.0) -> 4 | K59: =IF( C59=TRUE, IF(I59=J59,"SI","NO"), "-") -> SI | L59: ELECTRÓNICA | M59: 11 Taller_Electrónica_Firmado.pdf | O59: =VLOOKUP($G59,'Hoja 10'!$F$4:$AA478, 19,0) -> Promatisa | P59: =VLOOKUP($G59,'Hoja 10'!$F$4:$AA478, 20,0) -> Cautín eléctrico 220V – 30W tipo lapicero de madera | Q59: =VLOOKUP($G59,'Hoja 10'!$F$4:$AA478, 21,0) -> https://www.promart.pe/cautin-electrico-220v-30w-t-lapicero-madera/p | R59: ESP-121 CAUTÍN - CET | S59: TRUE | T59: PROMATISA | U59: Cautín eléctrico 220V-30W T.lápicero madera | V59: https://www.promart.pe/cautin-electrico-220v-30w-t-lapicero-madera/p | W59: =IFERROR(__xludf.DUMMYFUNCTION("IFERROR(VLOOKUP(G59,IMPORTRANGE(""https://docs.google.com/spreadsheets/d/12RxCea4e5ggM7QGn1XE3FbLQa_-QbCNdBi90OdPjRqg"", ""'Plan de Compras'!D4:Q""), 12, 0), ""NO ESTÁ EN REQ"")"),"Simple") -> Simple | X59: =IFERROR(__xludf.DUMMYFUNCTION("IFERROR(VLOOKUP(G59,IMPORTRANGE(""https://docs.google.com/spreadsheets/d/12RxCea4e5ggM7QGn1XE3FbLQa_-QbCNdBi90OdPjRqg"", ""'Plan de Compras'!D4:Q""), 13, 0), """")"),"NACIONAL") -> NACIONAL | Y59: =IFERROR(__xludf.DUMMYFUNCTION("IFERROR(VLOOKUP(G59,IMPORTRANGE(""https://docs.google.com/spreadsheets/d/12RxCea4e5ggM7QGn1XE3FbLQa_-QbCNdBi90OdPjRqg"", ""'Plan de Compras'!D4:Q""), 14, 0), """")"),"OMAR") -> OMAR | Z59: =IFERROR(__xludf.DUMMYFUNCTION("IFERROR(VLOOKUP(G59,IMPORTRANGE(""https://docs.google.com/spreadsheets/d/12RxCea4e5ggM7QGn1XE3FbLQa_-QbCNdBi90OdPjRqg"", ""'Plan de Compras'!D4:Q""), 4, 0), """")"),"CAUTÍN") -> CAUTÍN | AA59: =IF(H59=Z59,"TRUE", "FALSE") -> TRUE | AB59: =IFERROR(__xludf.DUMMYFUNCTION("IFERROR(IF(OR(C59=TRUE,C59=""""),VLOOKUP(G59,IMPORTRANGE(""https://docs.google.com/spreadsheets/d/1z9A1Wq-kKrhRNG5RS2a2fKpY1wIhSVz2ZNmP2mOl588/edit?usp=sharing"",""REQ VF!E4:H""),4,0),""NO APLICA""),""GENERAR REQ"")"),"GENERAR REQ") -> GENERAR REQ | AC59: =IFERROR(__xludf.DUMMYFUNCTION("IFERROR(QUERY(IMPORTRANGE(""https://docs.google.com/spreadsheets/d/1z9A1Wq-kKrhRNG5RS2a2fKpY1wIhSVz2ZNmP2mOl588/edit?usp=sharing"",""REQ VF!E4:Q""),""SELECT Col10, Col11, Col12 WHERE Col1 = '""&G59&""'"",0),""NO APLICA"")"),"NO APLICA") -> NO APLICA | AF59: C
C60: TRUE | D60: ACCESORIO | E60: EQUIPOS | F60: ESP-121 | G60: ESP-121.1 | H60: SOPORTE DE CAUTÍN (1 UND) | I60: =$I$59 -> 4 | J60: =IFERROR(__xludf.DUMMYFUNCTION("VLOOKUP(G60,IMPORTRANGE(""https://docs.google.com/spreadsheets/d/12RxCea4e5ggM7QGn1XE3FbLQa_-QbCNdBi90OdPjRqg/edit?gid=1692403370#gid=1692403370"", ""'Plan de Compras'!D4:2432""), 8,0)"),4.0) -> 4 | K60: =IF( C60=TRUE, IF(I60=J60,"SI","NO"), "-") -> SI | N60: SOPORTE DE CAUTÍN | Q60: https://www.promart.pe/soporte-de-cautin-metal-pesado/p?gad_source=1&gad_campaignid=22932501259&gbraid=0AAAAADJIfAJgSvKabG2GnPwrq3k6Yqddv&gclid=CjwKCAjw6P3GBhBVEiwAJPjmLvm3ljkm0SxQnmi1tkLz487IL7dbrcUNBI-gC94vkstPyfZ7CNI2shoCEQQQAvD_BwE | S60: TRUE | T60: TAKEMA | U60: ZD-10C | V60: https://westor.pe/soporte-para-cautin-con-base-y-esponja-zd-10c-takema/ | W60: =IFERROR(__xludf.DUMMYFUNCTION("IFERROR(VLOOKUP(G60,IMPORTRANGE(""https://docs.google.com/spreadsheets/d/12RxCea4e5ggM7QGn1XE3FbLQa_-QbCNdBi90OdPjRqg"", ""'Plan de Compras'!D4:Q""), 12, 0), ""NO ESTÁ EN REQ"")"),"Simple") -> Simple | X60: =IFERROR(__xludf.DUMMYFUNCTION("IFERROR(VLOOKUP(G60,IMPORTRANGE(""https://docs.google.com/spreadsheets/d/12RxCea4e5ggM7QGn1XE3FbLQa_-QbCNdBi90OdPjRqg"", ""'Plan de Compras'!D4:Q""), 13, 0), """")"),"NACIONAL") -> NACIONAL | Y60: =IFERROR(__xludf.DUMMYFUNCTION("IFERROR(VLOOKUP(G60,IMPORTRANGE(""https://docs.google.com/spreadsheets/d/12RxCea4e5ggM7QGn1XE3FbLQa_-QbCNdBi90OdPjRqg"", ""'Plan de Compras'!D4:Q""), 14, 0), """")"),"OMAR") -> OMAR | Z60: =IFERROR(__xludf.DUMMYFUNCTION("IFERROR(VLOOKUP(G60,IMPORTRANGE(""https://docs.google.com/spreadsheets/d/12RxCea4e5ggM7QGn1XE3FbLQa_-QbCNdBi90OdPjRqg"", ""'Plan de Compras'!D4:Q""), 4, 0), """")"),"SOPORTE DE CAUTÍN (1 UND)") -> SOPORTE DE CAUTÍN (1 UND) | AA60: =IF(H60=Z60,"TRUE", "FALSE") -> TRUE | AB60: =IFERROR(__xludf.DUMMYFUNCTION("IFERROR(IF(OR(C60=TRUE,C60=""""),VLOOKUP(G60,IMPORTRANGE(""https://docs.google.com/spreadsheets/d/1z9A1Wq-kKrhRNG5RS2a2fKpY1wIhSVz2ZNmP2mOl588/edit?usp=sharing"",""REQ VF!E4:H""),4,0),""NO APLICA""),""GENERAR REQ"")"),"GENERAR REQ") -> GENERAR REQ | AC60: =IFERROR(__xludf.DUMMYFUNCTION("IFERROR(QUERY(IMPORTRANGE(""https://docs.google.com/spreadsheets/d/1z9A1Wq-kKrhRNG5RS2a2fKpY1wIhSVz2ZNmP2mOl588/edit?usp=sharing"",""REQ VF!E4:Q""),""SELECT Col10, Col11, Col12 WHERE Col1 = '""&G60&""'"",0),""NO APLICA"")"),"NO APLICA") -> NO APLICA
C61: TRUE | D61: ACCESORIO | E61: EQUIPOS | F61: ESP-121 | G61: ESP-121.2 | H61: LIMPIADOR DE PUNTA (1 UND) | I61: =$I$59 -> 4 | J61: =IFERROR(__xludf.DUMMYFUNCTION("VLOOKUP(G61,IMPORTRANGE(""https://docs.google.com/spreadsheets/d/12RxCea4e5ggM7QGn1XE3FbLQa_-QbCNdBi90OdPjRqg/edit?gid=1692403370#gid=1692403370"", ""'Plan de Compras'!D4:2432""), 8,0)"),4.0) -> 4 | K61: =IF( C61=TRUE, IF(I61=J61,"SI","NO"), "-") -> SI | N61: LIMPIADOR DE PUNTAS METÁLICO PARA CAUTÍN | Q61: https://www.mercadolibre.com.pe/limpiador-de-puntas-metalico-para-cautin--takema/up/MPEU2463401498?has_official_store=false&highlight=false&headerTopBrand=false#polycard_client=search-nordic&search_layout=grid&position=3&type=product&tracking_id=b698c16e-d0c3-44e1-afb3-1f63d512b4de&wid=MPE622495745&sid=search | S61: TRUE | T61: TAKEMA | U61: ZD-10W-2 | V61: https://westor.pe/limpiador-de-puntas-de-cautin-zd-10w-2-takema/ | W61: =IFERROR(__xludf.DUMMYFUNCTION("IFERROR(VLOOKUP(G61,IMPORTRANGE(""https://docs.google.com/spreadsheets/d/12RxCea4e5ggM7QGn1XE3FbLQa_-QbCNdBi90OdPjRqg"", ""'Plan de Compras'!D4:Q""), 12, 0), ""NO ESTÁ EN REQ"")"),"Simple") -> Simple | X61: =IFERROR(__xludf.DUMMYFUNCTION("IFERROR(VLOOKUP(G61,IMPORTRANGE(""https://docs.google.com/spreadsheets/d/12RxCea4e5ggM7QGn1XE3FbLQa_-QbCNdBi90OdPjRqg"", ""'Plan de Compras'!D4:Q""), 13, 0), """")"),"NACIONAL") -> NACIONAL | Y61: =IFERROR(__xludf.DUMMYFUNCTION("IFERROR(VLOOKUP(G61,IMPORTRANGE(""https://docs.google.com/spreadsheets/d/12RxCea4e5ggM7QGn1XE3FbLQa_-QbCNdBi90OdPjRqg"", ""'Plan de Compras'!D4:Q""), 14, 0), """")"),"OMAR") -> OMAR | Z61: =IFERROR(__xludf.DUMMYFUNCTION("IFERROR(VLOOKUP(G61,IMPORTRANGE(""https://docs.google.com/spreadsheets/d/12RxCea4e5ggM7QGn1XE3FbLQa_-QbCNdBi90OdPjRqg"", ""'Plan de Compras'!D4:Q""), 4, 0), """")"),"LIMPIADOR DE PUNTA (1 UND)") -> LIMPIADOR DE PUNTA (1 UND) | AA61: =IF(H61=Z61,"TRUE", "FALSE") -> TRUE | AB61: =IFERROR(__xludf.DUMMYFUNCTION("IFERROR(IF(OR(C61=TRUE,C61=""""),VLOOKUP(G61,IMPORTRANGE(""https://docs.google.com/spreadsheets/d/1z9A1Wq-kKrhRNG5RS2a2fKpY1wIhSVz2ZNmP2mOl588/edit?usp=sharing"",""REQ VF!E4:H""),4,0),""NO APLICA""),""GENERAR REQ"")"),"GENERAR REQ") -> GENERAR REQ | AC61: =IFERROR(__xludf.DUMMYFUNCTION("IFERROR(QUERY(IMPORTRANGE(""https://docs.google.com/spreadsheets/d/1z9A1Wq-kKrhRNG5RS2a2fKpY1wIhSVz2ZNmP2mOl588/edit?usp=sharing"",""REQ VF!E4:Q""),""SELECT Col10, Col11, Col12 WHERE Col1 = '""&G61&""'"",0),""NO APLICA"")"),"NO APLICA") -> NO APLICA
A62: 23 | B62: TRUE | C62: TRUE | D62: BIEN | E62: EQUIPOS | F62: ESP-122 | G62: ESP-122 | H62: CIZALLA GUILLOTINA MECÁNICA | I62: =SUMIFS('Hoja 10'!$O:$O,'Hoja 10'!$F:$F,$G62) -> 1 | J62: =IFERROR(__xludf.DUMMYFUNCTION("VLOOKUP(G62,IMPORTRANGE(""https://docs.google.com/spreadsheets/d/12RxCea4e5ggM7QGn1XE3FbLQa_-QbCNdBi90OdPjRqg/edit?gid=1692403370#gid=1692403370"", ""'Plan de Compras'!D4:2432""), 8,0)"),1.0) -> 1 | K62: =IF( C62=TRUE, IF(I62=J62,"SI","NO"), "-") -> SI | L62: CONSTRUCCIONES METÁLICAS | M62: 16 Taller_Construcciones Metálicas_Firmado.pdf | O62: =VLOOKUP($G62,'Hoja 10'!$F$4:$AA478, 19,0) -> METALLKRAFT | P62: =VLOOKUP($G62,'Hoja 10'!$F$4:$AA478, 20,0) -> TBS 1051-20 | Q62: =VLOOKUP($G62,'Hoja 10'!$F$4:$AA478, 21,0) -> https://dimmtex.com/cizalla-manual-metal/cizalla-manual-tbs-1051-20.html | R62: ESP-122 CIZALLA GUILLOTINA MECÁNICA - CET | S62: TRUE | T62: =IFERROR(__xludf.DUMMYFUNCTION(" IF ( VLOOKUP($G62,IMPORTRANGE(""https://docs.google.com/spreadsheets/d/1Gpl6jkTg7sL4VDNimUm3S9Vi1i95esohXCF3wuKOE8c"", ""'CONSOLIDADO'!G5:AB""), 10, 0) <> 0, IFERROR(VLOOKUP($G62,IMPORTRANGE(""https://docs.google.com/spreadsheets/d/1Gpl6jkTg7sL4VDNimUm3"&"S9Vi1i95esohXCF3wuKOE8c"", ""'CONSOLIDADO'!G5:AB""), 17, 0), ""-""), """" )"),"METALLKRAFT") -> METALLKRAFT | U62: =IFERROR(__xludf.DUMMYFUNCTION(" IF ( VLOOKUP($G62,IMPORTRANGE(""https://docs.google.com/spreadsheets/d/1Gpl6jkTg7sL4VDNimUm3S9Vi1i95esohXCF3wuKOE8c"", ""'CONSOLIDADO'!G5:AB""), 10, 0) <> 0, IFERROR(VLOOKUP($G62,IMPORTRANGE(""https://docs.google.com/spreadsheets/d/1Gpl6jkTg7sL4VDNimUm3"&"S9Vi1i95esohXCF3wuKOE8c"", ""'CONSOLIDADO'!G5:AB""), 18, 0), ""-""), """" )"),"TBS 1051-20") -> TBS 1051-20 | V62: =IFERROR(__xludf.DUMMYFUNCTION(" IF ( VLOOKUP($G62,IMPORTRANGE(""https://docs.google.com/spreadsheets/d/1Gpl6jkTg7sL4VDNimUm3S9Vi1i95esohXCF3wuKOE8c"", ""'CONSOLIDADO'!G5:AB""), 10, 0) <> 0, IFERROR(VLOOKUP($G62,IMPORTRANGE(""https://docs.google.com/spreadsheets/d/1Gpl6jkTg7sL4VDNimUm3"&"S9Vi1i95esohXCF3wuKOE8c"", ""'CONSOLIDADO'!G5:AB""), 19, 0), ""-""), """" )"),"https://dimmtex.com/cizalla-manual-metal/cizalla-manual-tbs-1051-20.html") -> https://dimmtex.com/cizalla-manual-metal/cizalla-manual-tbs-1051-20.html | W62: =IFERROR(__xludf.DUMMYFUNCTION("IFERROR(VLOOKUP(G62,IMPORTRANGE(""https://docs.google.com/spreadsheets/d/12RxCea4e5ggM7QGn1XE3FbLQa_-QbCNdBi90OdPjRqg"", ""'Plan de Compras'!D4:Q""), 12, 0), ""NO ESTÁ EN REQ"")"),"Técnica") -> Técnica | X62: =IFERROR(__xludf.DUMMYFUNCTION("IFERROR(VLOOKUP(G62,IMPORTRANGE(""https://docs.google.com/spreadsheets/d/12RxCea4e5ggM7QGn1XE3FbLQa_-QbCNdBi90OdPjRqg"", ""'Plan de Compras'!D4:Q""), 13, 0), """")"),"INTERNACIONAL") -> INTERNACIONAL | Y62: =IFERROR(__xludf.DUMMYFUNCTION("IFERROR(VLOOKUP(G62,IMPORTRANGE(""https://docs.google.com/spreadsheets/d/12RxCea4e5ggM7QGn1XE3FbLQa_-QbCNdBi90OdPjRqg"", ""'Plan de Compras'!D4:Q""), 14, 0), """")"),"GEYDI") -> GEYDI | Z62: =IFERROR(__xludf.DUMMYFUNCTION("IFERROR(VLOOKUP(G62,IMPORTRANGE(""https://docs.google.com/spreadsheets/d/12RxCea4e5ggM7QGn1XE3FbLQa_-QbCNdBi90OdPjRqg"", ""'Plan de Compras'!D4:Q""), 4, 0), """")"),"CIZALLA GUILLOTINA MECÁNICA") -> CIZALLA GUILLOTINA MECÁNICA | AA62: =IF(H62=Z62,"TRUE", "FALSE") -> TRUE | AB62: =IFERROR(__xludf.DUMMYFUNCTION("IFERROR(IF(OR(C62=TRUE,C62=""""),VLOOKUP(G62,IMPORTRANGE(""https://docs.google.com/spreadsheets/d/1z9A1Wq-kKrhRNG5RS2a2fKpY1wIhSVz2ZNmP2mOl588/edit?usp=sharing"",""REQ VF!E4:H""),4,0),""NO APLICA""),""GENERAR REQ"")"),"GENERAR REQ") -> GENERAR REQ | AC62: =IFERROR(__xludf.DUMMYFUNCTION("IFERROR(QUERY(IMPORTRANGE(""https://docs.google.com/spreadsheets/d/1z9A1Wq-kKrhRNG5RS2a2fKpY1wIhSVz2ZNmP2mOl588/edit?usp=sharing"",""REQ VF!E4:Q""),""SELECT Col10, Col11, Col12 WHERE Col1 = '""&G62&""'"",0),""NO APLICA"")"),"NO APLICA") -> NO APLICA | AF62: C
A63: 24 | B63: TRUE | C63: TRUE | D63: BIEN | E63: EQUIPOS | F63: ESP-124 | G63: ESP-124 | H63: COCINA 1 HORNILLA A GAS | I63: =SUMIFS('Hoja 10'!$O:$O,'Hoja 10'!$F:$F,$G63) -> 4 | J63: =IFERROR(__xludf.DUMMYFUNCTION("VLOOKUP(G63,IMPORTRANGE(""https://docs.google.com/spreadsheets/d/12RxCea4e5ggM7QGn1XE3FbLQa_-QbCNdBi90OdPjRqg/edit?gid=1692403370#gid=1692403370"", ""'Plan de Compras'!D4:2432""), 8,0)"),4.0) -> 4 | K63: =IF( C63=TRUE, IF(I63=J63,"SI","NO"), "-") -> SI | L63: INDUSTRIA ALIMENTARIA | M63: 12 Taller_Industria_Alimentaria_Firmado.pdf | O63: =VLOOKUP($G63,'Hoja 10'!$F$4:$AA478, 19,0) -> LINOX | P63: =VLOOKUP($G63,'Hoja 10'!$F$4:$AA478, 20,0) -> Cocina Sobremesa Industrial de 1 Hornilla | Q63: =VLOOKUP($G63,'Hoja 10'!$F$4:$AA478, 21,0) -> https://linoxperu.com/producto/cocina-sobremesa-industrial-de-1-hornilla/?utm_source=chatgpt.com | R63: ESP-124 COCINA 1 HORNILLA A GAS - CET | S63: TRUE | T63: =IFERROR(__xludf.DUMMYFUNCTION(" IF ( VLOOKUP($G63,IMPORTRANGE(""https://docs.google.com/spreadsheets/d/1Gpl6jkTg7sL4VDNimUm3S9Vi1i95esohXCF3wuKOE8c"", ""'CONSOLIDADO'!G5:AB""), 10, 0) <> 0, IFERROR(VLOOKUP($G63,IMPORTRANGE(""https://docs.google.com/spreadsheets/d/1Gpl6jkTg7sL4VDNimUm3"&"S9Vi1i95esohXCF3wuKOE8c"", ""'CONSOLIDADO'!G5:AB""), 17, 0), ""-""), """" )"),"LINOX") -> LINOX | U63: =IFERROR(__xludf.DUMMYFUNCTION(" IF ( VLOOKUP($G63,IMPORTRANGE(""https://docs.google.com/spreadsheets/d/1Gpl6jkTg7sL4VDNimUm3S9Vi1i95esohXCF3wuKOE8c"", ""'CONSOLIDADO'!G5:AB""), 10, 0) <> 0, IFERROR(VLOOKUP($G63,IMPORTRANGE(""https://docs.google.com/spreadsheets/d/1Gpl6jkTg7sL4VDNimUm3"&"S9Vi1i95esohXCF3wuKOE8c"", ""'CONSOLIDADO'!G5:AB""), 18, 0), ""-""), """" )"),"Cocina Sobremesa Industrial de 1 Hornilla") -> Cocina Sobremesa Industrial de 1 Hornilla | V63: =IFERROR(__xludf.DUMMYFUNCTION(" IF ( VLOOKUP($G63,IMPORTRANGE(""https://docs.google.com/spreadsheets/d/1Gpl6jkTg7sL4VDNimUm3S9Vi1i95esohXCF3wuKOE8c"", ""'CONSOLIDADO'!G5:AB""), 10, 0) <> 0, IFERROR(VLOOKUP($G63,IMPORTRANGE(""https://docs.google.com/spreadsheets/d/1Gpl6jkTg7sL4VDNimUm3"&"S9Vi1i95esohXCF3wuKOE8c"", ""'CONSOLIDADO'!G5:AB""), 19, 0), ""-""), """" )"),"https://linoxperu.com/producto/cocina-sobremesa-industrial-de-1-hornilla/?utm_source=chatgpt.com") -> https://linoxperu.com/producto/cocina-sobremesa-industrial-de-1-hornilla/?utm_source=chatgpt.com | W63: =IFERROR(__xludf.DUMMYFUNCTION("IFERROR(VLOOKUP(G63,IMPORTRANGE(""https://docs.google.com/spreadsheets/d/12RxCea4e5ggM7QGn1XE3FbLQa_-QbCNdBi90OdPjRqg"", ""'Plan de Compras'!D4:Q""), 12, 0), ""NO ESTÁ EN REQ"")"),"Técnica") -> Técnica | X63: =IFERROR(__xludf.DUMMYFUNCTION("IFERROR(VLOOKUP(G63,IMPORTRANGE(""https://docs.google.com/spreadsheets/d/12RxCea4e5ggM7QGn1XE3FbLQa_-QbCNdBi90OdPjRqg"", ""'Plan de Compras'!D4:Q""), 13, 0), """")"),"NACIONAL") -> NACIONAL | Y63: =IFERROR(__xludf.DUMMYFUNCTION("IFERROR(VLOOKUP(G63,IMPORTRANGE(""https://docs.google.com/spreadsheets/d/12RxCea4e5ggM7QGn1XE3FbLQa_-QbCNdBi90OdPjRqg"", ""'Plan de Compras'!D4:Q""), 14, 0), """")"),"GEANFRANCO") -> GEANFRANCO | Z63: =IFERROR(__xludf.DUMMYFUNCTION("IFERROR(VLOOKUP(G63,IMPORTRANGE(""https://docs.google.com/spreadsheets/d/12RxCea4e5ggM7QGn1XE3FbLQa_-QbCNdBi90OdPjRqg"", ""'Plan de Compras'!D4:Q""), 4, 0), """")"),"COCINA 1 HORNILLA A GAS") -> COCINA 1 HORNILLA A GAS | AA63: =IF(H63=Z63,"TRUE", "FALSE") -> TRUE | AB63: =IFERROR(__xludf.DUMMYFUNCTION("IFERROR(IF(OR(C63=TRUE,C63=""""),VLOOKUP(G63,IMPORTRANGE(""https://docs.google.com/spreadsheets/d/1z9A1Wq-kKrhRNG5RS2a2fKpY1wIhSVz2ZNmP2mOl588/edit?usp=sharing"",""REQ VF!E4:H""),4,0),""NO APLICA""),""GENERAR REQ"")"),"GENERAR REQ") -> GENERAR REQ | AC63: =IFERROR(__xludf.DUMMYFUNCTION("IFERROR(QUERY(IMPORTRANGE(""https://docs.google.com/spreadsheets/d/1z9A1Wq-kKrhRNG5RS2a2fKpY1wIhSVz2ZNmP2mOl588/edit?usp=sharing"",""REQ VF!E4:Q""),""SELECT Col10, Col11, Col12 WHERE Col1 = '""&G63&""'"",0),""NO APLICA"")"),"NO APLICA") -> NO APLICA
A64: 25 | B64: TRUE | C64: TRUE | D64: BIEN | E64: EQUIPOS | F64: ESP-125 | G64: ESP-125 | H64: COCINA DE INDUCCIÓN CON 5 ZONAS DE COCCIÓN Y CON HORNO MULTIFUNCIONAL | I64: =SUMIFS('Hoja 10'!$O:$O,'Hoja 10'!$F:$F,$G64) -> 1 | J64: =IFERROR(__xludf.DUMMYFUNCTION("VLOOKUP(G64,IMPORTRANGE(""https://docs.google.com/spreadsheets/d/12RxCea4e5ggM7QGn1XE3FbLQa_-QbCNdBi90OdPjRqg/edit?gid=1692403370#gid=1692403370"", ""'Plan de Compras'!D4:2432""), 8,0)"),1.0) -> 1 | K64: =IF( C64=TRUE, IF(I64=J64,"SI","NO"), "-") -> SI | L64: COCINA Y REPOSTERÍA | M64: 5 Taller_Cocina y Respostería_Firmado.pdf | O64: =VLOOKUP($G64,'Hoja 10'!$F$4:$AA478, 19,0) -> SMEG | P64: =VLOOKUP($G64,'Hoja 10'!$F$4:$AA478, 20,0) -> Portofino CPF9IPOR | Q64: =VLOOKUP($G64,'Hoja 10'!$F$4:$AA478, 21,0) -> https://www.smeguk.com/products/CPF9IPOR | R64: ESP-125 COCINA DE INDUCCIÓN CON 5 ZONAS DE COCCIÓN Y CON HORNO MULTIFUNCIONAL - CET | S64: TRUE | T64: =IFERROR(__xludf.DUMMYFUNCTION(" IF ( VLOOKUP($G64,IMPORTRANGE(""https://docs.google.com/spreadsheets/d/1Gpl6jkTg7sL4VDNimUm3S9Vi1i95esohXCF3wuKOE8c"", ""'CONSOLIDADO'!G5:AB""), 10, 0) <> 0, IFERROR(VLOOKUP($G64,IMPORTRANGE(""https://docs.google.com/spreadsheets/d/1Gpl6jkTg7sL4VDNimUm3"&"S9Vi1i95esohXCF3wuKOE8c"", ""'CONSOLIDADO'!G5:AB""), 17, 0), ""-""), """" )"),"SMEG") -> SMEG | U64: =IFERROR(__xludf.DUMMYFUNCTION(" IF ( VLOOKUP($G64,IMPORTRANGE(""https://docs.google.com/spreadsheets/d/1Gpl6jkTg7sL4VDNimUm3S9Vi1i95esohXCF3wuKOE8c"", ""'CONSOLIDADO'!G5:AB""), 10, 0) <> 0, IFERROR(VLOOKUP($G64,IMPORTRANGE(""https://docs.google.com/spreadsheets/d/1Gpl6jkTg7sL4VDNimUm3"&"S9Vi1i95esohXCF3wuKOE8c"", ""'CONSOLIDADO'!G5:AB""), 18, 0), ""-""), """" )"),"Portofino CPF9IPOR") -> Portofino CPF9IPOR | V64: =IFERROR(__xludf.DUMMYFUNCTION(" IF ( VLOOKUP($G64,IMPORTRANGE(""https://docs.google.com/spreadsheets/d/1Gpl6jkTg7sL4VDNimUm3S9Vi1i95esohXCF3wuKOE8c"", ""'CONSOLIDADO'!G5:AB""), 10, 0) <> 0, IFERROR(VLOOKUP($G64,IMPORTRANGE(""https://docs.google.com/spreadsheets/d/1Gpl6jkTg7sL4VDNimUm3"&"S9Vi1i95esohXCF3wuKOE8c"", ""'CONSOLIDADO'!G5:AB""), 19, 0), ""-""), """" )"),"https://www.smeguk.com/products/CPF9IPOR") -> https://www.smeguk.com/products/CPF9IPOR | W64: =IFERROR(__xludf.DUMMYFUNCTION("IFERROR(VLOOKUP(G64,IMPORTRANGE(""https://docs.google.com/spreadsheets/d/12RxCea4e5ggM7QGn1XE3FbLQa_-QbCNdBi90OdPjRqg"", ""'Plan de Compras'!D4:Q""), 12, 0), ""NO ESTÁ EN REQ"")"),"Técnica") -> Técnica | X64: =IFERROR(__xludf.DUMMYFUNCTION("IFERROR(VLOOKUP(G64,IMPORTRANGE(""https://docs.google.com/spreadsheets/d/12RxCea4e5ggM7QGn1XE3FbLQa_-QbCNdBi90OdPjRqg"", ""'Plan de Compras'!D4:Q""), 13, 0), """")"),"INTERNACIONAL") -> INTERNACIONAL | Y64: =IFERROR(__xludf.DUMMYFUNCTION("IFERROR(VLOOKUP(G64,IMPORTRANGE(""https://docs.google.com/spreadsheets/d/12RxCea4e5ggM7QGn1XE3FbLQa_-QbCNdBi90OdPjRqg"", ""'Plan de Compras'!D4:Q""), 14, 0), """")"),"GEYDI") -> GEYDI | Z64: =IFERROR(__xludf.DUMMYFUNCTION("IFERROR(VLOOKUP(G64,IMPORTRANGE(""https://docs.google.com/spreadsheets/d/12RxCea4e5ggM7QGn1XE3FbLQa_-QbCNdBi90OdPjRqg"", ""'Plan de Compras'!D4:Q""), 4, 0), """")"),"COCINA DE INDUCCIÓN CON 5 ZONAS DE COCCIÓN Y CON HORNO MULTIFUNCIONAL") -> COCINA DE INDUCCIÓN CON 5 ZONAS DE COCCIÓN Y CON HORNO MULTIFUNCIONAL | AA64: =IF(H64=Z64,"TRUE", "FALSE") -> TRUE | AB64: =IFERROR(__xludf.DUMMYFUNCTION("IFERROR(IF(OR(C64=TRUE,C64=""""),VLOOKUP(G64,IMPORTRANGE(""https://docs.google.com/spreadsheets/d/1z9A1Wq-kKrhRNG5RS2a2fKpY1wIhSVz2ZNmP2mOl588/edit?usp=sharing"",""REQ VF!E4:H""),4,0),""NO APLICA""),""GENERAR REQ"")"),"GENERAR REQ") -> GENERAR REQ | AC64: =IFERROR(__xludf.DUMMYFUNCTION("IFERROR(QUERY(IMPORTRANGE(""https://docs.google.com/spreadsheets/d/1z9A1Wq-kKrhRNG5RS2a2fKpY1wIhSVz2ZNmP2mOl588/edit?usp=sharing"",""REQ VF!E4:Q""),""SELECT Col10, Col11, Col12 WHERE Col1 = '""&G64&""'"",0),""NO APLICA"")"),"NO APLICA") -> NO APLICA
C65: TRUE | D65: ACCESORIO | E65: EQUIPOS | F65: ESP-125 | G65: ESP-125.1 | H65: =UPPER("Rascador (scrapper) (1 UND)") -> RASCADOR (SCRAPPER) (1 UND) | I65: =$I$64 -> 1 | J65: =IFERROR(__xludf.DUMMYFUNCTION("VLOOKUP(G65,IMPORTRANGE(""https://docs.google.com/spreadsheets/d/12RxCea4e5ggM7QGn1XE3FbLQa_-QbCNdBi90OdPjRqg/edit?gid=1692403370#gid=1692403370"", ""'Plan de Compras'!D4:2432""), 8,0)"),1.0) -> 1 | K65: =IF( C65=TRUE, IF(I65=J65,"SI","NO"), "-") -> SI | N65: CON PROVEEDOR EXTERNO | S65: TRUE | T65: SMEG | U65: SCRP | V65: chrome-extension://efaidnbmnnnibpcajpcglclefindmkaj/https://pi-exchange.smeg.it/catalog/CPF9IPOR/en-GB | W65: =IFERROR(__xludf.DUMMYFUNCTION("IFERROR(VLOOKUP(G65,IMPORTRANGE(""https://docs.google.com/spreadsheets/d/12RxCea4e5ggM7QGn1XE3FbLQa_-QbCNdBi90OdPjRqg"", ""'Plan de Compras'!D4:Q""), 12, 0), ""NO ESTÁ EN REQ"")"),"Técnica") -> Técnica | X65: =IFERROR(__xludf.DUMMYFUNCTION("IFERROR(VLOOKUP(G65,IMPORTRANGE(""https://docs.google.com/spreadsheets/d/12RxCea4e5ggM7QGn1XE3FbLQa_-QbCNdBi90OdPjRqg"", ""'Plan de Compras'!D4:Q""), 13, 0), """")"),"INTERNACIONAL") -> INTERNACIONAL | Y65: =IFERROR(__xludf.DUMMYFUNCTION("IFERROR(VLOOKUP(G65,IMPORTRANGE(""https://docs.google.com/spreadsheets/d/12RxCea4e5ggM7QGn1XE3FbLQa_-QbCNdBi90OdPjRqg"", ""'Plan de Compras'!D4:Q""), 14, 0), """")"),"GEYDI") -> GEYDI | Z65: =IFERROR(__xludf.DUMMYFUNCTION("IFERROR(VLOOKUP(G65,IMPORTRANGE(""https://docs.google.com/spreadsheets/d/12RxCea4e5ggM7QGn1XE3FbLQa_-QbCNdBi90OdPjRqg"", ""'Plan de Compras'!D4:Q""), 4, 0), """")"),"RASCADOR (SCRAPPER) (1 UND)") -> RASCADOR (SCRAPPER) (1 UND) | AA65: =IF(H65=Z65,"TRUE", "FALSE") -> TRUE | AB65: =IFERROR(__xludf.DUMMYFUNCTION("IFERROR(IF(OR(C65=TRUE,C65=""""),VLOOKUP(G65,IMPORTRANGE(""https://docs.google.com/spreadsheets/d/1z9A1Wq-kKrhRNG5RS2a2fKpY1wIhSVz2ZNmP2mOl588/edit?usp=sharing"",""REQ VF!E4:H""),4,0),""NO APLICA""),""GENERAR REQ"")"),"GENERAR REQ") -> GENERAR REQ | AC65: =IFERROR(__xludf.DUMMYFUNCTION("IFERROR(QUERY(IMPORTRANGE(""https://docs.google.com/spreadsheets/d/1z9A1Wq-kKrhRNG5RS2a2fKpY1wIhSVz2ZNmP2mOl588/edit?usp=sharing"",""REQ VF!E4:Q""),""SELECT Col10, Col11, Col12 WHERE Col1 = '""&G65&""'"",0),""NO APLICA"")"),"NO APLICA") -> NO APLICA
C66: TRUE | D66: ACCESORIO | E66: EQUIPOS | F66: ESP-125 | G66: ESP-125.2 | H66: =UPPER("Asador (rotisserie) (1 UND)") -> ASADOR (ROTISSERIE) (1 UND) | I66: =$I$64 -> 1 | J66: =IFERROR(__xludf.DUMMYFUNCTION("VLOOKUP(G66,IMPORTRANGE(""https://docs.google.com/spreadsheets/d/12RxCea4e5ggM7QGn1XE3FbLQa_-QbCNdBi90OdPjRqg/edit?gid=1692403370#gid=1692403370"", ""'Plan de Compras'!D4:2432""), 8,0)"),1.0) -> 1 | K66: =IF( C66=TRUE, IF(I66=J66,"SI","NO"), "-") -> SI | N66: CON PROVEEDOR EXTERNO | S66: TRUE | T66: SMEG | U66: GRILLPLATE | V66: chrome-extension://efaidnbmnnnibpcajpcglclefindmkaj/https://pi-exchange.smeg.it/catalog/CPF9IPOR/en-GB | W66: =IFERROR(__xludf.DUMMYFUNCTION("IFERROR(VLOOKUP(G66,IMPORTRANGE(""https://docs.google.com/spreadsheets/d/12RxCea4e5ggM7QGn1XE3FbLQa_-QbCNdBi90OdPjRqg"", ""'Plan de Compras'!D4:Q""), 12, 0), ""NO ESTÁ EN REQ"")"),"Técnica") -> Técnica | X66: =IFERROR(__xludf.DUMMYFUNCTION("IFERROR(VLOOKUP(G66,IMPORTRANGE(""https://docs.google.com/spreadsheets/d/12RxCea4e5ggM7QGn1XE3FbLQa_-QbCNdBi90OdPjRqg"", ""'Plan de Compras'!D4:Q""), 13, 0), """")"),"INTERNACIONAL") -> INTERNACIONAL | Y66: =IFERROR(__xludf.DUMMYFUNCTION("IFERROR(VLOOKUP(G66,IMPORTRANGE(""https://docs.google.com/spreadsheets/d/12RxCea4e5ggM7QGn1XE3FbLQa_-QbCNdBi90OdPjRqg"", ""'Plan de Compras'!D4:Q""), 14, 0), """")"),"GEYDI") -> GEYDI | Z66: =IFERROR(__xludf.DUMMYFUNCTION("IFERROR(VLOOKUP(G66,IMPORTRANGE(""https://docs.google.com/spreadsheets/d/12RxCea4e5ggM7QGn1XE3FbLQa_-QbCNdBi90OdPjRqg"", ""'Plan de Compras'!D4:Q""), 4, 0), """")"),"ASADOR (ROTISSERIE) (1 UND)") -> ASADOR (ROTISSERIE) (1 UND) | AA66: =IF(H66=Z66,"TRUE", "FALSE") -> TRUE | AB66: =IFERROR(__xludf.DUMMYFUNCTION("IFERROR(IF(OR(C66=TRUE,C66=""""),VLOOKUP(G66,IMPORTRANGE(""https://docs.google.com/spreadsheets/d/1z9A1Wq-kKrhRNG5RS2a2fKpY1wIhSVz2ZNmP2mOl588/edit?usp=sharing"",""REQ VF!E4:H""),4,0),""NO APLICA""),""GENERAR REQ"")"),"GENERAR REQ") -> GENERAR REQ | AC66: =IFERROR(__xludf.DUMMYFUNCTION("IFERROR(QUERY(IMPORTRANGE(""https://docs.google.com/spreadsheets/d/1z9A1Wq-kKrhRNG5RS2a2fKpY1wIhSVz2ZNmP2mOl588/edit?usp=sharing"",""REQ VF!E4:Q""),""SELECT Col10, Col11, Col12 WHERE Col1 = '""&G66&""'"",0),""NO APLICA"")"),"NO APLICA") -> NO APLICA
C67: TRUE | D67: ACCESORIO | E67: EQUIPOS | F67: ESP-125 | G67: ESP-125.3 | H67: BANDEJA PROFUNDA 40 MM (1 UND) | I67: 1 | J67: =IFERROR(__xludf.DUMMYFUNCTION("VLOOKUP(G67,IMPORTRANGE(""https://docs.google.com/spreadsheets/d/12RxCea4e5ggM7QGn1XE3FbLQa_-QbCNdBi90OdPjRqg/edit?gid=1692403370#gid=1692403370"", ""'Plan de Compras'!D4:2432""), 8,0)"),1.0) -> 1 | K67: =IF( C67=TRUE, IF(I67=J67,"SI","NO"), "-") -> SI | N67: CON PROVEEDOR EXTERNO | S67: TRUE | T67: SMEG | U67: BN940 | V67: chrome-extension://efaidnbmnnnibpcajpcglclefindmkaj/https://pi-exchange.smeg.it/catalog/CPF9IPOR/en-GB | W67: =IFERROR(__xludf.DUMMYFUNCTION("IFERROR(VLOOKUP(G67,IMPORTRANGE(""https://docs.google.com/spreadsheets/d/12RxCea4e5ggM7QGn1XE3FbLQa_-QbCNdBi90OdPjRqg"", ""'Plan de Compras'!D4:Q""), 12, 0), ""NO ESTÁ EN REQ"")"),"Técnica") -> Técnica | X67: =IFERROR(__xludf.DUMMYFUNCTION("IFERROR(VLOOKUP(G67,IMPORTRANGE(""https://docs.google.com/spreadsheets/d/12RxCea4e5ggM7QGn1XE3FbLQa_-QbCNdBi90OdPjRqg"", ""'Plan de Compras'!D4:Q""), 13, 0), """")"),"INTERNACIONAL") -> INTERNACIONAL | Y67: =IFERROR(__xludf.DUMMYFUNCTION("IFERROR(VLOOKUP(G67,IMPORTRANGE(""https://docs.google.com/spreadsheets/d/12RxCea4e5ggM7QGn1XE3FbLQa_-QbCNdBi90OdPjRqg"", ""'Plan de Compras'!D4:Q""), 14, 0), """")"),"GEYDI") -> GEYDI | Z67: =IFERROR(__xludf.DUMMYFUNCTION("IFERROR(VLOOKUP(G67,IMPORTRANGE(""https://docs.google.com/spreadsheets/d/12RxCea4e5ggM7QGn1XE3FbLQa_-QbCNdBi90OdPjRqg"", ""'Plan de Compras'!D4:Q""), 4, 0), """")"),"BANDEJA PROFUNDA 40 MM") -> BANDEJA PROFUNDA 40 MM | AA67: =IF(H67=Z67,"TRUE", "FALSE") -> FALSE | AB67: =IFERROR(__xludf.DUMMYFUNCTION("IFERROR(IF(OR(C67=TRUE,C67=""""),VLOOKUP(G67,IMPORTRANGE(""https://docs.google.com/spreadsheets/d/1z9A1Wq-kKrhRNG5RS2a2fKpY1wIhSVz2ZNmP2mOl588/edit?usp=sharing"",""REQ VF!E4:H""),4,0),""NO APLICA""),""GENERAR REQ"")"),"GENERAR REQ") -> GENERAR REQ | AC67: =IFERROR(__xludf.DUMMYFUNCTION("IFERROR(QUERY(IMPORTRANGE(""https://docs.google.com/spreadsheets/d/1z9A1Wq-kKrhRNG5RS2a2fKpY1wIhSVz2ZNmP2mOl588/edit?usp=sharing"",""REQ VF!E4:Q""),""SELECT Col10, Col11, Col12 WHERE Col1 = '""&G67&""'"",0),""NO APLICA"")"),"NO APLICA") -> NO APLICA
C68: TRUE | D68: ACCESORIO | E68: EQUIPOS | F68: ESP-125 | G68: ESP-125.4 | H68: REJILLA CON TOPE (1 UND) | I68: 1 | J68: =IFERROR(__xludf.DUMMYFUNCTION("VLOOKUP(G68,IMPORTRANGE(""https://docs.google.com/spreadsheets/d/12RxCea4e5ggM7QGn1XE3FbLQa_-QbCNdBi90OdPjRqg/edit?gid=1692403370#gid=1692403370"", ""'Plan de Compras'!D4:2432""), 8,0)"),1.0) -> 1 | K68: =IF( C68=TRUE, IF(I68=J68,"SI","NO"), "-") -> SI | N68: CON PROVEEDOR EXTERNO | S68: TRUE | T68: SMEG | U68: Rejilla con tope trasero y lateral | V68: chrome-extension://efaidnbmnnnibpcajpcglclefindmkaj/https://pi-exchange.smeg.it/catalog/CPF9IPOR/en-GB | W68: =IFERROR(__xludf.DUMMYFUNCTION("IFERROR(VLOOKUP(G68,IMPORTRANGE(""https://docs.google.com/spreadsheets/d/12RxCea4e5ggM7QGn1XE3FbLQa_-QbCNdBi90OdPjRqg"", ""'Plan de Compras'!D4:Q""), 12, 0), ""NO ESTÁ EN REQ"")"),"Técnica") -> Técnica | X68: =IFERROR(__xludf.DUMMYFUNCTION("IFERROR(VLOOKUP(G68,IMPORTRANGE(""https://docs.google.com/spreadsheets/d/12RxCea4e5ggM7QGn1XE3FbLQa_-QbCNdBi90OdPjRqg"", ""'Plan de Compras'!D4:Q""), 13, 0), """")"),"INTERNACIONAL") -> INTERNACIONAL | Y68: =IFERROR(__xludf.DUMMYFUNCTION("IFERROR(VLOOKUP(G68,IMPORTRANGE(""https://docs.google.com/spreadsheets/d/12RxCea4e5ggM7QGn1XE3FbLQa_-QbCNdBi90OdPjRqg"", ""'Plan de Compras'!D4:Q""), 14, 0), """")"),"GEYDI") -> GEYDI | Z68: =IFERROR(__xludf.DUMMYFUNCTION("IFERROR(VLOOKUP(G68,IMPORTRANGE(""https://docs.google.com/spreadsheets/d/12RxCea4e5ggM7QGn1XE3FbLQa_-QbCNdBi90OdPjRqg"", ""'Plan de Compras'!D4:Q""), 4, 0), """")"),"REJILLA CON TOPES") -> REJILLA CON TOPES | AA68: =IF(H68=Z68,"TRUE", "FALSE") -> FALSE | AB68: =IFERROR(__xludf.DUMMYFUNCTION("IFERROR(IF(OR(C68=TRUE,C68=""""),VLOOKUP(G68,IMPORTRANGE(""https://docs.google.com/spreadsheets/d/1z9A1Wq-kKrhRNG5RS2a2fKpY1wIhSVz2ZNmP2mOl588/edit?usp=sharing"",""REQ VF!E4:H""),4,0),""NO APLICA""),""GENERAR REQ"")"),"GENERAR REQ") -> GENERAR REQ | AC68: =IFERROR(__xludf.DUMMYFUNCTION("IFERROR(QUERY(IMPORTRANGE(""https://docs.google.com/spreadsheets/d/1z9A1Wq-kKrhRNG5RS2a2fKpY1wIhSVz2ZNmP2mOl588/edit?usp=sharing"",""REQ VF!E4:Q""),""SELECT Col10, Col11, Col12 WHERE Col1 = '""&G68&""'"",0),""NO APLICA"")"),"NO APLICA") -> NO APLICA
A69: 26 | B69: TRUE | C69: TRUE | D69: BIEN | E69: EQUIPOS | F69: ESP-126 | G69: ESP-126-X | H69: COCINA SEMI INDUSTRIAL | I69: =SUMIFS('Hoja 10'!$O:$O,'Hoja 10'!$F:$F,$G69) -> 1 | J69: =IFERROR(__xludf.DUMMYFUNCTION("VLOOKUP(G69,IMPORTRANGE(""https://docs.google.com/spreadsheets/d/12RxCea4e5ggM7QGn1XE3FbLQa_-QbCNdBi90OdPjRqg/edit?gid=1692403370#gid=1692403370"", ""'Plan de Compras'!D4:2432""), 8,0)"),1.0) -> 1 | K69: =IF( C69=TRUE, IF(I69=J69,"SI","NO"), "-") -> SI | L69: COCINA Y REPOSTERÍA | M69: 5 Taller_Cocina y Respostería_Firmado.pdf | O69: =VLOOKUP($G69,'Hoja 10'!$F$4:$AA478, 19,0) -> LINOX | P69: =VLOOKUP($G69,'Hoja 10'!$F$4:$AA478, 20,0) -> Cocina Industrial de 2 Hornillas | Q69: =VLOOKUP($G69,'Hoja 10'!$F$4:$AA478, 21,0) -> https://linoxperu.com/producto/cocina-industrial-de-2-hornillas/?utm_source=chatgpt.com | R69: ESP-126-X COCINA SEMI INDUSTRIAL - CET | S69: TRUE | T69: =IFERROR(__xludf.DUMMYFUNCTION(" IF ( VLOOKUP($G69,IMPORTRANGE(""https://docs.google.com/spreadsheets/d/1Gpl6jkTg7sL4VDNimUm3S9Vi1i95esohXCF3wuKOE8c"", ""'CONSOLIDADO'!G5:AB""), 10, 0) <> 0, IFERROR(VLOOKUP($G69,IMPORTRANGE(""https://docs.google.com/spreadsheets/d/1Gpl6jkTg7sL4VDNimUm3"&"S9Vi1i95esohXCF3wuKOE8c"", ""'CONSOLIDADO'!G5:AB""), 17, 0), ""-""), """" )"),"LINOX") -> LINOX | U69: =IFERROR(__xludf.DUMMYFUNCTION(" IF ( VLOOKUP($G69,IMPORTRANGE(""https://docs.google.com/spreadsheets/d/1Gpl6jkTg7sL4VDNimUm3S9Vi1i95esohXCF3wuKOE8c"", ""'CONSOLIDADO'!G5:AB""), 10, 0) <> 0, IFERROR(VLOOKUP($G69,IMPORTRANGE(""https://docs.google.com/spreadsheets/d/1Gpl6jkTg7sL4VDNimUm3"&"S9Vi1i95esohXCF3wuKOE8c"", ""'CONSOLIDADO'!G5:AB""), 18, 0), ""-""), """" )"),"A MEDIDA") -> A MEDIDA | V69: =IFERROR(__xludf.DUMMYFUNCTION(" IF ( VLOOKUP($G69,IMPORTRANGE(""https://docs.google.com/spreadsheets/d/1Gpl6jkTg7sL4VDNimUm3S9Vi1i95esohXCF3wuKOE8c"", ""'CONSOLIDADO'!G5:AB""), 10, 0) <> 0, IFERROR(VLOOKUP($G69,IMPORTRANGE(""https://docs.google.com/spreadsheets/d/1Gpl6jkTg7sL4VDNimUm3"&"S9Vi1i95esohXCF3wuKOE8c"", ""'CONSOLIDADO'!G5:AB""), 19, 0), ""-""), """" )"),"https://drive.google.com/file/d/1wD4owhuWxnyormBfDcxxUIkF3obARv5l/view?usp=drive_link") -> https://drive.google.com/file/d/1wD4owhuWxnyormBfDcxxUIkF3obARv5l/view?usp=drive_link | W69: =IFERROR(__xludf.DUMMYFUNCTION("IFERROR(VLOOKUP(G69,IMPORTRANGE(""https://docs.google.com/spreadsheets/d/12RxCea4e5ggM7QGn1XE3FbLQa_-QbCNdBi90OdPjRqg"", ""'Plan de Compras'!D4:Q""), 12, 0), ""NO ESTÁ EN REQ"")"),"Técnica") -> Técnica | X69: =IFERROR(__xludf.DUMMYFUNCTION("IFERROR(VLOOKUP(G69,IMPORTRANGE(""https://docs.google.com/spreadsheets/d/12RxCea4e5ggM7QGn1XE3FbLQa_-QbCNdBi90OdPjRqg"", ""'Plan de Compras'!D4:Q""), 13, 0), """")"),"NACIONAL") -> NACIONAL | Y69: =IFERROR(__xludf.DUMMYFUNCTION("IFERROR(VLOOKUP(G69,IMPORTRANGE(""https://docs.google.com/spreadsheets/d/12RxCea4e5ggM7QGn1XE3FbLQa_-QbCNdBi90OdPjRqg"", ""'Plan de Compras'!D4:Q""), 14, 0), """")"),"GEANFRANCO") -> GEANFRANCO | Z69: =IFERROR(__xludf.DUMMYFUNCTION("IFERROR(VLOOKUP(G69,IMPORTRANGE(""https://docs.google.com/spreadsheets/d/12RxCea4e5ggM7QGn1XE3FbLQa_-QbCNdBi90OdPjRqg"", ""'Plan de Compras'!D4:Q""), 4, 0), """")"),"COCINA SEMI INDUSTRIAL") -> COCINA SEMI INDUSTRIAL | AA69: =IF(H69=Z69,"TRUE", "FALSE") -> TRUE | AB69: =IFERROR(__xludf.DUMMYFUNCTION("IFERROR(IF(OR(C69=TRUE,C69=""""),VLOOKUP(G69,IMPORTRANGE(""https://docs.google.com/spreadsheets/d/1z9A1Wq-kKrhRNG5RS2a2fKpY1wIhSVz2ZNmP2mOl588/edit?usp=sharing"",""REQ VF!E4:H""),4,0),""NO APLICA""),""GENERAR REQ"")"),"GENERAR REQ") -> GENERAR REQ | AC69: =IFERROR(__xludf.DUMMYFUNCTION("IFERROR(QUERY(IMPORTRANGE(""https://docs.google.com/spreadsheets/d/1z9A1Wq-kKrhRNG5RS2a2fKpY1wIhSVz2ZNmP2mOl588/edit?usp=sharing"",""REQ VF!E4:Q""),""SELECT Col10, Col11, Col12 WHERE Col1 = '""&G69&""'"",0),""NO APLICA"")"),"NO APLICA") -> NO APLICA
A70: 27 | B70: TRUE | C70: TRUE | D70: BIEN | E70: EQUIPOS | F70: ESP-126 | G70: ESP-126-Y | H70: COCINA SEMI INDUSTRIAL A GAS | I70: =SUMIFS('Hoja 10'!$O:$O,'Hoja 10'!$F:$F,$G70) -> 8 | J70: =IFERROR(__xludf.DUMMYFUNCTION("VLOOKUP(G70,IMPORTRANGE(""https://docs.google.com/spreadsheets/d/12RxCea4e5ggM7QGn1XE3FbLQa_-QbCNdBi90OdPjRqg/edit?gid=1692403370#gid=1692403370"", ""'Plan de Compras'!D4:2432""), 8,0)"),8.0) -> 8 | K70: =IF( C70=TRUE, IF(I70=J70,"SI","NO"), "-") -> SI | L70: INDUSTRIA ALIMENTARIA | M70: 12 Taller_Industria_Alimentaria_Firmado.pdf | O70: =VLOOKUP($G70,'Hoja 10'!$F$4:$AA478, 19,0) -> DRACCO | P70: =VLOOKUP($G70,'Hoja 10'!$F$4:$AA478, 20,0) -> CSI-2H | Q70: =VLOOKUP($G70,'Hoja 10'!$F$4:$AA478, 21,0) -> https://drive.google.com/file/d/1L2xTfes6smSwtJk_Ok6YfxYiLIC_YUcY/view?usp=sharing | R70: ESP-126-Y COCINA SEMI INDUSTRIAL A GAS - CET | S70: TRUE | T70: =IFERROR(__xludf.DUMMYFUNCTION(" IF ( VLOOKUP($G70,IMPORTRANGE(""https://docs.google.com/spreadsheets/d/1Gpl6jkTg7sL4VDNimUm3S9Vi1i95esohXCF3wuKOE8c"", ""'CONSOLIDADO'!G5:AB""), 10, 0) <> 0, IFERROR(VLOOKUP($G70,IMPORTRANGE(""https://docs.google.com/spreadsheets/d/1Gpl6jkTg7sL4VDNimUm3"&"S9Vi1i95esohXCF3wuKOE8c"", ""'CONSOLIDADO'!G5:AB""), 17, 0), ""-""), """" )"),"LINOX") -> LINOX | U70: =IFERROR(__xludf.DUMMYFUNCTION(" IF ( VLOOKUP($G70,IMPORTRANGE(""https://docs.google.com/spreadsheets/d/1Gpl6jkTg7sL4VDNimUm3S9Vi1i95esohXCF3wuKOE8c"", ""'CONSOLIDADO'!G5:AB""), 10, 0) <> 0, IFERROR(VLOOKUP($G70,IMPORTRANGE(""https://docs.google.com/spreadsheets/d/1Gpl6jkTg7sL4VDNimUm3"&"S9Vi1i95esohXCF3wuKOE8c"", ""'CONSOLIDADO'!G5:AB""), 18, 0), ""-""), """" )"),"A MEDIDA") -> A MEDIDA | V70: =IFERROR(__xludf.DUMMYFUNCTION(" IF ( VLOOKUP($G70,IMPORTRANGE(""https://docs.google.com/spreadsheets/d/1Gpl6jkTg7sL4VDNimUm3S9Vi1i95esohXCF3wuKOE8c"", ""'CONSOLIDADO'!G5:AB""), 10, 0) <> 0, IFERROR(VLOOKUP($G70,IMPORTRANGE(""https://docs.google.com/spreadsheets/d/1Gpl6jkTg7sL4VDNimUm3"&"S9Vi1i95esohXCF3wuKOE8c"", ""'CONSOLIDADO'!G5:AB""), 19, 0), ""-""), """" )"),"https://drive.google.com/file/d/1OPcH9VfDuaJC5_ssSN_3kau8tNkJxgRp/view?usp=drive_link") -> https://drive.google.com/file/d/1OPcH9VfDuaJC5_ssSN_3kau8tNkJxgRp/view?usp=drive_link | W70: =IFERROR(__xludf.DUMMYFUNCTION("IFERROR(VLOOKUP(G70,IMPORTRANGE(""https://docs.google.com/spreadsheets/d/12RxCea4e5ggM7QGn1XE3FbLQa_-QbCNdBi90OdPjRqg"", ""'Plan de Compras'!D4:Q""), 12, 0), ""NO ESTÁ EN REQ"")"),"Técnica") -> Técnica | X70: =IFERROR(__xludf.DUMMYFUNCTION("IFERROR(VLOOKUP(G70,IMPORTRANGE(""https://docs.google.com/spreadsheets/d/12RxCea4e5ggM7QGn1XE3FbLQa_-QbCNdBi90OdPjRqg"", ""'Plan de Compras'!D4:Q""), 13, 0), """")"),"NACIONAL") -> NACIONAL | Y70: =IFERROR(__xludf.DUMMYFUNCTION("IFERROR(VLOOKUP(G70,IMPORTRANGE(""https://docs.google.com/spreadsheets/d/12RxCea4e5ggM7QGn1XE3FbLQa_-QbCNdBi90OdPjRqg"", ""'Plan de Compras'!D4:Q""), 14, 0), """")"),"GEANFRANCO") -> GEANFRANCO | Z70: =IFERROR(__xludf.DUMMYFUNCTION("IFERROR(VLOOKUP(G70,IMPORTRANGE(""https://docs.google.com/spreadsheets/d/12RxCea4e5ggM7QGn1XE3FbLQa_-QbCNdBi90OdPjRqg"", ""'Plan de Compras'!D4:Q""), 4, 0), """")"),"COCINA SEMI INDUSTRIAL A GAS") -> COCINA SEMI INDUSTRIAL A GAS | AA70: =IF(H70=Z70,"TRUE", "FALSE") -> TRUE | AB70: =IFERROR(__xludf.DUMMYFUNCTION("IFERROR(IF(OR(C70=TRUE,C70=""""),VLOOKUP(G70,IMPORTRANGE(""https://docs.google.com/spreadsheets/d/1z9A1Wq-kKrhRNG5RS2a2fKpY1wIhSVz2ZNmP2mOl588/edit?usp=sharing"",""REQ VF!E4:H""),4,0),""NO APLICA""),""GENERAR REQ"")"),"GENERAR REQ") -> GENERAR REQ | AC70: =IFERROR(__xludf.DUMMYFUNCTION("IFERROR(QUERY(IMPORTRANGE(""https://docs.google.com/spreadsheets/d/1z9A1Wq-kKrhRNG5RS2a2fKpY1wIhSVz2ZNmP2mOl588/edit?usp=sharing"",""REQ VF!E4:Q""),""SELECT Col10, Col11, Col12 WHERE Col1 = '""&G70&""'"",0),""NO APLICA"")"),"NO APLICA") -> NO APLICA
A71: 28 | B71: TRUE | C71: TRUE | D71: BIEN | E71: EQUIPOS | F71: ESP-128 | G71: ESP-128 | H71: COMPRENSORA DE AIRE DE 50 LITROS | I71: =SUMIFS('Hoja 10'!$O:$O,'Hoja 10'!$F:$F,$G71) -> 2 | J71: =IFERROR(__xludf.DUMMYFUNCTION("VLOOKUP(G71,IMPORTRANGE(""https://docs.google.com/spreadsheets/d/12RxCea4e5ggM7QGn1XE3FbLQa_-QbCNdBi90OdPjRqg/edit?gid=1692403370#gid=1692403370"", ""'Plan de Compras'!D4:2432""), 8,0)"),2.0) -> 2 | K71: =IF( C71=TRUE, IF(I71=J71,"SI","NO"), "-") -> SI | L71: EBANISTERÍA | M71: 6 Taller_Ebanistería_Firmado.pdf | O71: =VLOOKUP($G71,'Hoja 10'!$F$4:$AA478, 19,0) -> GOODYEAR | P71: =VLOOKUP($G71,'Hoja 10'!$F$4:$AA478, 20,0) -> GY 351D | Q71: =VLOOKUP($G71,'Hoja 10'!$F$4:$AA478, 21,0) -> https://www.leroymerlin.es/productos/compresor-goodyear-gy351d-3hp-50l-86538711.html | R71: ESP-128 COMPRENSORA DE AIRE DE 50 LITROS - CET | S71: TRUE | T71: =IFERROR(__xludf.DUMMYFUNCTION(" IF ( VLOOKUP($G71,IMPORTRANGE(""https://docs.google.com/spreadsheets/d/1Gpl6jkTg7sL4VDNimUm3S9Vi1i95esohXCF3wuKOE8c"", ""'CONSOLIDADO'!G5:AB""), 10, 0) <> 0, IFERROR(VLOOKUP($G71,IMPORTRANGE(""https://docs.google.com/spreadsheets/d/1Gpl6jkTg7sL4VDNimUm3"&"S9Vi1i95esohXCF3wuKOE8c"", ""'CONSOLIDADO'!G5:AB""), 17, 0), ""-""), """" )"),"GOODYEAR") -> GOODYEAR | U71: =IFERROR(__xludf.DUMMYFUNCTION(" IF ( VLOOKUP($G71,IMPORTRANGE(""https://docs.google.com/spreadsheets/d/1Gpl6jkTg7sL4VDNimUm3S9Vi1i95esohXCF3wuKOE8c"", ""'CONSOLIDADO'!G5:AB""), 10, 0) <> 0, IFERROR(VLOOKUP($G71,IMPORTRANGE(""https://docs.google.com/spreadsheets/d/1Gpl6jkTg7sL4VDNimUm3"&"S9Vi1i95esohXCF3wuKOE8c"", ""'CONSOLIDADO'!G5:AB""), 18, 0), ""-""), """" )"),"GY 351D") -> GY 351D | V71: =IFERROR(__xludf.DUMMYFUNCTION(" IF ( VLOOKUP($G71,IMPORTRANGE(""https://docs.google.com/spreadsheets/d/1Gpl6jkTg7sL4VDNimUm3S9Vi1i95esohXCF3wuKOE8c"", ""'CONSOLIDADO'!G5:AB""), 10, 0) <> 0, IFERROR(VLOOKUP($G71,IMPORTRANGE(""https://docs.google.com/spreadsheets/d/1Gpl6jkTg7sL4VDNimUm3"&"S9Vi1i95esohXCF3wuKOE8c"", ""'CONSOLIDADO'!G5:AB""), 19, 0), ""-""), """" )"),"https://www.leroymerlin.es/productos/compresor-goodyear-gy351d-3hp-50l-86538711.html") -> https://www.leroymerlin.es/productos/compresor-goodyear-gy351d-3hp-50l-86538711.html | W71: =IFERROR(__xludf.DUMMYFUNCTION("IFERROR(VLOOKUP(G71,IMPORTRANGE(""https://docs.google.com/spreadsheets/d/12RxCea4e5ggM7QGn1XE3FbLQa_-QbCNdBi90OdPjRqg"", ""'Plan de Compras'!D4:Q""), 12, 0), ""NO ESTÁ EN REQ"")"),"Técnica") -> Técnica | X71: =IFERROR(__xludf.DUMMYFUNCTION("IFERROR(VLOOKUP(G71,IMPORTRANGE(""https://docs.google.com/spreadsheets/d/12RxCea4e5ggM7QGn1XE3FbLQa_-QbCNdBi90OdPjRqg"", ""'Plan de Compras'!D4:Q""), 13, 0), """")"),"INTERNACIONAL") -> INTERNACIONAL | Y71: =IFERROR(__xludf.DUMMYFUNCTION("IFERROR(VLOOKUP(G71,IMPORTRANGE(""https://docs.google.com/spreadsheets/d/12RxCea4e5ggM7QGn1XE3FbLQa_-QbCNdBi90OdPjRqg"", ""'Plan de Compras'!D4:Q""), 14, 0), """")"),"ALEJANDRA") -> ALEJANDRA | Z71: =IFERROR(__xludf.DUMMYFUNCTION("IFERROR(VLOOKUP(G71,IMPORTRANGE(""https://docs.google.com/spreadsheets/d/12RxCea4e5ggM7QGn1XE3FbLQa_-QbCNdBi90OdPjRqg"", ""'Plan de Compras'!D4:Q""), 4, 0), """")"),"COMPRENSORA DE AIRE DE 50 LITROS") -> COMPRENSORA DE AIRE DE 50 LITROS | AA71: =IF(H71=Z71,"TRUE", "FALSE") -> TRUE | AB71: =IFERROR(__xludf.DUMMYFUNCTION("IFERROR(IF(OR(C71=TRUE,C71=""""),VLOOKUP(G71,IMPORTRANGE(""https://docs.google.com/spreadsheets/d/1z9A1Wq-kKrhRNG5RS2a2fKpY1wIhSVz2ZNmP2mOl588/edit?usp=sharing"",""REQ VF!E4:H""),4,0),""NO APLICA""),""GENERAR REQ"")"),"GENERAR REQ") -> GENERAR REQ | AC71: =IFERROR(__xludf.DUMMYFUNCTION("IFERROR(QUERY(IMPORTRANGE(""https://docs.google.com/spreadsheets/d/1z9A1Wq-kKrhRNG5RS2a2fKpY1wIhSVz2ZNmP2mOl588/edit?usp=sharing"",""REQ VF!E4:Q""),""SELECT Col10, Col11, Col12 WHERE Col1 = '""&G71&""'"",0),""NO APLICA"")"),"NO APLICA") -> NO APLICA | AF71: C
C72: TRUE | D72: ACCESORIO | E72: EQUIPOS | F72: ESP-128 | G72: ESP-128.1 | H72: FILTRO Y REGULADOR DE AIRE (1 UND) | I72: =$I$71 -> 2 | J72: =IFERROR(__xludf.DUMMYFUNCTION("VLOOKUP(G72,IMPORTRANGE(""https://docs.google.com/spreadsheets/d/12RxCea4e5ggM7QGn1XE3FbLQa_-QbCNdBi90OdPjRqg/edit?gid=1692403370#gid=1692403370"", ""'Plan de Compras'!D4:2432""), 8,0)"),2.0) -> 2 | K72: =IF( C72=TRUE, IF(I72=J72,"SI","NO"), "-") -> SI | P72: 1/4" NPT TRUPER 19238 | Q72: https://cahema.pe/filtro/16133-filtro-y-regulador-de-aire-14-npt-truper-19238-7501206628607.html | S72: TRUE | T72: TRUPER | U72: 19238 | V72: https://cahema.pe/filtro/16133-filtro-y-regulador-de-aire-14-npt-truper-19238-7501206628607.html | W72: =IFERROR(__xludf.DUMMYFUNCTION("IFERROR(VLOOKUP(G72,IMPORTRANGE(""https://docs.google.com/spreadsheets/d/12RxCea4e5ggM7QGn1XE3FbLQa_-QbCNdBi90OdPjRqg"", ""'Plan de Compras'!D4:Q""), 12, 0), ""NO ESTÁ EN REQ"")"),"Técnica") -> Técnica | X72: =IFERROR(__xludf.DUMMYFUNCTION("IFERROR(VLOOKUP(G72,IMPORTRANGE(""https://docs.google.com/spreadsheets/d/12RxCea4e5ggM7QGn1XE3FbLQa_-QbCNdBi90OdPjRqg"", ""'Plan de Compras'!D4:Q""), 13, 0), """")"),"NACIONAL") -> NACIONAL | Y72: =IFERROR(__xludf.DUMMYFUNCTION("IFERROR(VLOOKUP(G72,IMPORTRANGE(""https://docs.google.com/spreadsheets/d/12RxCea4e5ggM7QGn1XE3FbLQa_-QbCNdBi90OdPjRqg"", ""'Plan de Compras'!D4:Q""), 14, 0), """")"),"ANGIE") -> ANGIE | Z72: =IFERROR(__xludf.DUMMYFUNCTION("IFERROR(VLOOKUP(G72,IMPORTRANGE(""https://docs.google.com/spreadsheets/d/12RxCea4e5ggM7QGn1XE3FbLQa_-QbCNdBi90OdPjRqg"", ""'Plan de Compras'!D4:Q""), 4, 0), """")"),"FILTRO Y REGULADOR DE AIRE (1 UND)") -> FILTRO Y REGULADOR DE AIRE (1 UND) | AA72: =IF(H72=Z72,"TRUE", "FALSE") -> TRUE | AB72: =IFERROR(__xludf.DUMMYFUNCTION("IFERROR(IF(OR(C72=TRUE,C72=""""),VLOOKUP(G72,IMPORTRANGE(""https://docs.google.com/spreadsheets/d/1z9A1Wq-kKrhRNG5RS2a2fKpY1wIhSVz2ZNmP2mOl588/edit?usp=sharing"",""REQ VF!E4:H""),4,0),""NO APLICA""),""GENERAR REQ"")"),"GENERAR REQ") -> GENERAR REQ | AC72: =IFERROR(__xludf.DUMMYFUNCTION("IFERROR(QUERY(IMPORTRANGE(""https://docs.google.com/spreadsheets/d/1z9A1Wq-kKrhRNG5RS2a2fKpY1wIhSVz2ZNmP2mOl588/edit?usp=sharing"",""REQ VF!E4:Q""),""SELECT Col10, Col11, Col12 WHERE Col1 = '""&G72&""'"",0),""NO APLICA"")"),"NO APLICA") -> NO APLICA
C73: TRUE | D73: ACCESORIO | E73: EQUIPOS | F73: ESP-128 | G73: ESP-128.2 | H73: KIT ACCESORIOS DE COMPRESOR AIRE (1 UND) | I73: =$I$71 -> 2 | J73: =IFERROR(__xludf.DUMMYFUNCTION("VLOOKUP(G73,IMPORTRANGE(""https://docs.google.com/spreadsheets/d/12RxCea4e5ggM7QGn1XE3FbLQa_-QbCNdBi90OdPjRqg/edit?gid=1692403370#gid=1692403370"", ""'Plan de Compras'!D4:2432""), 8,0)"),2.0) -> 2 | K73: =IF( C73=TRUE, IF(I73=J73,"SI","NO"), "-") -> SI | P73: 1/4 14 Pzas TC2029 TOOLCRAFT | Q73: https://cahema.pe/juego-de-accesorios/8237-kit-accesorios-compresor-aire-14-14-pzas-tc2029-toolcraft-7501892804026.html | S73: TRUE | T73: TOOLCARFT | U73: TC2029 | V73: https://cahema.pe/juego-de-accesorios/8237-kit-accesorios-compresor-aire-14-14-pzas-tc2029-toolcraft-7501892804026.html | W73: =IFERROR(__xludf.DUMMYFUNCTION("IFERROR(VLOOKUP(G73,IMPORTRANGE(""https://docs.google.com/spreadsheets/d/12RxCea4e5ggM7QGn1XE3FbLQa_-QbCNdBi90OdPjRqg"", ""'Plan de Compras'!D4:Q""), 12, 0), ""NO ESTÁ EN REQ"")"),"Técnica") -> Técnica | X73: =IFERROR(__xludf.DUMMYFUNCTION("IFERROR(VLOOKUP(G73,IMPORTRANGE(""https://docs.google.com/spreadsheets/d/12RxCea4e5ggM7QGn1XE3FbLQa_-QbCNdBi90OdPjRqg"", ""'Plan de Compras'!D4:Q""), 13, 0), """")"),"NACIONAL") -> NACIONAL | Y73: =IFERROR(__xludf.DUMMYFUNCTION("IFERROR(VLOOKUP(G73,IMPORTRANGE(""https://docs.google.com/spreadsheets/d/12RxCea4e5ggM7QGn1XE3FbLQa_-QbCNdBi90OdPjRqg"", ""'Plan de Compras'!D4:Q""), 14, 0), """")"),"ANGIE") -> ANGIE | Z73: =IFERROR(__xludf.DUMMYFUNCTION("IFERROR(VLOOKUP(G73,IMPORTRANGE(""https://docs.google.com/spreadsheets/d/12RxCea4e5ggM7QGn1XE3FbLQa_-QbCNdBi90OdPjRqg"", ""'Plan de Compras'!D4:Q""), 4, 0), """")"),"KIT ACCESORIOS DE COMPRESOR AIRE (1 UND)") -> KIT ACCESORIOS DE COMPRESOR AIRE (1 UND) | AA73: =IF(H73=Z73,"TRUE", "FALSE") -> TRUE | AB73: =IFERROR(__xludf.DUMMYFUNCTION("IFERROR(IF(OR(C73=TRUE,C73=""""),VLOOKUP(G73,IMPORTRANGE(""https://docs.google.com/spreadsheets/d/1z9A1Wq-kKrhRNG5RS2a2fKpY1wIhSVz2ZNmP2mOl588/edit?usp=sharing"",""REQ VF!E4:H""),4,0),""NO APLICA""),""GENERAR REQ"")"),"GENERAR REQ") -> GENERAR REQ | AC73: =IFERROR(__xludf.DUMMYFUNCTION("IFERROR(QUERY(IMPORTRANGE(""https://docs.google.com/spreadsheets/d/1z9A1Wq-kKrhRNG5RS2a2fKpY1wIhSVz2ZNmP2mOl588/edit?usp=sharing"",""REQ VF!E4:Q""),""SELECT Col10, Col11, Col12 WHERE Col1 = '""&G73&""'"",0),""NO APLICA"")"),"NO APLICA") -> NO APLICA
C74: FALSE | D74: ACCESORIO | E74: EQUIPOS | F74: ESP-128 | G74: ESP-128.3 | H74: ADAPTADOR DE ROSCA 1/2" (1 UND) | I74: 2 | J74: =IFERROR(__xludf.DUMMYFUNCTION("VLOOKUP(G74,IMPORTRANGE(""https://docs.google.com/spreadsheets/d/12RxCea4e5ggM7QGn1XE3FbLQa_-QbCNdBi90OdPjRqg/edit?gid=1692403370#gid=1692403370"", ""'Plan de Compras'!D4:2432""), 8,0)"),"#N/A") -> #N/A | K74: =IF( C74=TRUE, IF(I74=J74,"SI","NO"), "-") -> - | S74: FALSE | AA74: =IF(H74=Z74,"TRUE", "FALSE") -> FALSE | AB74: =IFERROR(__xludf.DUMMYFUNCTION("IFERROR(IF(OR(C74=TRUE,C74=""""),VLOOKUP(G74,IMPORTRANGE(""https://docs.google.com/spreadsheets/d/1z9A1Wq-kKrhRNG5RS2a2fKpY1wIhSVz2ZNmP2mOl588/edit?usp=sharing"",""REQ VF!E4:H""),4,0),""NO APLICA""),""GENERAR REQ"")"),"NO APLICA") -> NO APLICA | AC74: =IFERROR(__xludf.DUMMYFUNCTION("IFERROR(QUERY(IMPORTRANGE(""https://docs.google.com/spreadsheets/d/1z9A1Wq-kKrhRNG5RS2a2fKpY1wIhSVz2ZNmP2mOl588/edit?usp=sharing"",""REQ VF!E4:Q""),""SELECT Col10, Col11, Col12 WHERE Col1 = '""&G74&""'"",0),""NO APLICA"")"),"NO APLICA") -> NO APLICA
A75: 29 | B75: TRUE | C75: TRUE | D75: BIEN | E75: EQUIPOS | F75: ESP-130 | G75: ESP-130 | H75: COMPRESORA DE AIRE (50L - 2HP) | I75: =SUMIFS('Hoja 10'!$O:$O,'Hoja 10'!$F:$F,$G75) -> 1 | J75: =IFERROR(__xludf.DUMMYFUNCTION("VLOOKUP(G75,IMPORTRANGE(""https://docs.google.com/spreadsheets/d/12RxCea4e5ggM7QGn1XE3FbLQa_-QbCNdBi90OdPjRqg/edit?gid=1692403370#gid=1692403370"", ""'Plan de Compras'!D4:2432""), 8,0)"),1.0) -> 1 | K75: =IF( C75=TRUE, IF(I75=J75,"SI","NO"), "-") -> SI | L75: CONSTRUCCIONES METÁLICAS | M75: 16 Taller_Construcciones Metálicas_Firmado.pdf | O75: =VLOOKUP($G75,'Hoja 10'!$F$4:$AA478, 19,0) -> TRUPER | P75: =VLOOKUP($G75,'Hoja 10'!$F$4:$AA478, 20,0) -> COMP-KIT50-260 | Q75: =VLOOKUP($G75,'Hoja 10'!$F$4:$AA478, 21,0) -> https://www.aibitech.com/herramientas-electricas/sierras/compresora-de-aire/compresora-de-aire-de-35-hp-50l-arranque-automatico-comp-50lt-260-11837-truper-16441.html?srsltid=AfmBOopR8FWY-1gVYn-_wN1--TVCWMoTpxXvVOxalx6Owo6EUWkqzOgQ | R75: ESP-130 COMPRESORA DE AIRE (50L - 2HP) - CET | S75: TRUE | T75: =IFERROR(__xludf.DUMMYFUNCTION(" IF ( VLOOKUP($G75,IMPORTRANGE(""https://docs.google.com/spreadsheets/d/1Gpl6jkTg7sL4VDNimUm3S9Vi1i95esohXCF3wuKOE8c"", ""'CONSOLIDADO'!G5:AB""), 10, 0) <> 0, IFERROR(VLOOKUP($G75,IMPORTRANGE(""https://docs.google.com/spreadsheets/d/1Gpl6jkTg7sL4VDNimUm3"&"S9Vi1i95esohXCF3wuKOE8c"", ""'CONSOLIDADO'!G5:AB""), 17, 0), ""-""), """" )"),"TRUPER") -> TRUPER | U75: =IFERROR(__xludf.DUMMYFUNCTION(" IF ( VLOOKUP($G75,IMPORTRANGE(""https://docs.google.com/spreadsheets/d/1Gpl6jkTg7sL4VDNimUm3S9Vi1i95esohXCF3wuKOE8c"", ""'CONSOLIDADO'!G5:AB""), 10, 0) <> 0, IFERROR(VLOOKUP($G75,IMPORTRANGE(""https://docs.google.com/spreadsheets/d/1Gpl6jkTg7sL4VDNimUm3"&"S9Vi1i95esohXCF3wuKOE8c"", ""'CONSOLIDADO'!G5:AB""), 18, 0), ""-""), """" )"),"COMP-KIT50-260") -> COMP-KIT50-260 | V75: =IFERROR(__xludf.DUMMYFUNCTION(" IF ( VLOOKUP($G75,IMPORTRANGE(""https://docs.google.com/spreadsheets/d/1Gpl6jkTg7sL4VDNimUm3S9Vi1i95esohXCF3wuKOE8c"", ""'CONSOLIDADO'!G5:AB""), 10, 0) <> 0, IFERROR(VLOOKUP($G75,IMPORTRANGE(""https://docs.google.com/spreadsheets/d/1Gpl6jkTg7sL4VDNimUm3"&"S9Vi1i95esohXCF3wuKOE8c"", ""'CONSOLIDADO'!G5:AB""), 19, 0), ""-""), """" )"),"https://www.indupartescorp.com/product/combo-compresora-50-litros-manguera-y-pistola-para-pintar-truper-101744?srsltid=AfmBOooJByXDjXWlbbiJ-6GBD7HGONzqyMUGcDpudIUPk2hGhzdUP23z") -> https://www.indupartescorp.com/product/combo-compresora-50-litros-manguera-y-pistola-para-pintar-truper-101744?srsltid=AfmBOooJByXDjXWlbbiJ-6GBD7HGONzqyMUGcDpudIUPk2hGhzdUP23z | W75: =IFERROR(__xludf.DUMMYFUNCTION("IFERROR(VLOOKUP(G75,IMPORTRANGE(""https://docs.google.com/spreadsheets/d/12RxCea4e5ggM7QGn1XE3FbLQa_-QbCNdBi90OdPjRqg"", ""'Plan de Compras'!D4:Q""), 12, 0), ""NO ESTÁ EN REQ"")"),"Técnica") -> Técnica | X75: =IFERROR(__xludf.DUMMYFUNCTION("IFERROR(VLOOKUP(G75,IMPORTRANGE(""https://docs.google.com/spreadsheets/d/12RxCea4e5ggM7QGn1XE3FbLQa_-QbCNdBi90OdPjRqg"", ""'Plan de Compras'!D4:Q""), 13, 0), """")"),"NACIONAL") -> NACIONAL | Y75: =IFERROR(__xludf.DUMMYFUNCTION("IFERROR(VLOOKUP(G75,IMPORTRANGE(""https://docs.google.com/spreadsheets/d/12RxCea4e5ggM7QGn1XE3FbLQa_-QbCNdBi90OdPjRqg"", ""'Plan de Compras'!D4:Q""), 14, 0), """")"),"OMAR") -> OMAR | Z75: =IFERROR(__xludf.DUMMYFUNCTION("IFERROR(VLOOKUP(G75,IMPORTRANGE(""https://docs.google.com/spreadsheets/d/12RxCea4e5ggM7QGn1XE3FbLQa_-QbCNdBi90OdPjRqg"", ""'Plan de Compras'!D4:Q""), 4, 0), """")"),"COMPRESORA DE AIRE (50L - 2HP)") -> COMPRESORA DE AIRE (50L - 2HP) | AA75: =IF(H75=Z75,"TRUE", "FALSE") -> TRUE | AB75: =IFERROR(__xludf.DUMMYFUNCTION("IFERROR(IF(OR(C75=TRUE,C75=""""),VLOOKUP(G75,IMPORTRANGE(""https://docs.google.com/spreadsheets/d/1z9A1Wq-kKrhRNG5RS2a2fKpY1wIhSVz2ZNmP2mOl588/edit?usp=sharing"",""REQ VF!E4:H""),4,0),""NO APLICA""),""GENERAR REQ"")"),"GENERAR REQ") -> GENERAR REQ | AC75: =IFERROR(__xludf.DUMMYFUNCTION("IFERROR(QUERY(IMPORTRANGE(""https://docs.google.com/spreadsheets/d/1z9A1Wq-kKrhRNG5RS2a2fKpY1wIhSVz2ZNmP2mOl588/edit?usp=sharing"",""REQ VF!E4:Q""),""SELECT Col10, Col11, Col12 WHERE Col1 = '""&G75&""'"",0),""NO APLICA"")"),"NO APLICA") -> NO APLICA | AF75: C
A76: 30 | B76: TRUE | C76: TRUE | D76: BIEN | E76: EQUIPOS | F76: ESP-131 | G76: ESP-131 | H76: COMPRESORA DE AIRE (50L - 3HP) | I76: =SUMIFS('Hoja 10'!$O:$O,'Hoja 10'!$F:$F,$G76) -> 3 | J76: =IFERROR(__xludf.DUMMYFUNCTION("VLOOKUP(G76,IMPORTRANGE(""https://docs.google.com/spreadsheets/d/12RxCea4e5ggM7QGn1XE3FbLQa_-QbCNdBi90OdPjRqg/edit?gid=1692403370#gid=1692403370"", ""'Plan de Compras'!D4:2432""), 8,0)"),3.0) -> 3 | K76: =IF( C76=TRUE, IF(I76=J76,"SI","NO"), "-") -> SI | L76: MECÁNICA AUTOMOTRÍZ | M76: 1 Taller_Mecanica_Automotriz_Firmado.pdf | O76: =VLOOKUP($G76,'Hoja 10'!$F$4:$AA478, 19,0) -> TRUPER | P76: =VLOOKUP($G76,'Hoja 10'!$F$4:$AA478, 20,0) -> COMP-KIT50-260 | Q76: =VLOOKUP($G76,'Hoja 10'!$F$4:$AA478, 21,0) -> https://www.aibitech.com/herramientas-electricas/sierras/compresora-de-aire/compresora-de-aire-de-35-hp-50l-arranque-automatico-comp-50lt-260-11837-truper-16441.html?srsltid=AfmBOopR8FWY-1gVYn-_wN1--TVCWMoTpxXvVOxalx6Owo6EUWkqzOgQ | R76: ESP-131 COMPRESORA DE AIRE (50L - 3HP) - CET | S76: TRUE | T76: EINHELL | U76: TC-AC 420/50/10 V | V76: https://docs.google.com/spreadsheets/d/19YosAmj_OvIfChEVT_fA37lQeHG-KBhIfS2SV-mx4F8/edit?gid=0#gid=0 | W76: =IFERROR(__xludf.DUMMYFUNCTION("IFERROR(VLOOKUP(G76,IMPORTRANGE(""https://docs.google.com/spreadsheets/d/12RxCea4e5ggM7QGn1XE3FbLQa_-QbCNdBi90OdPjRqg"", ""'Plan de Compras'!D4:Q""), 12, 0), ""NO ESTÁ EN REQ"")"),"Técnica") -> Técnica | X76: =IFERROR(__xludf.DUMMYFUNCTION("IFERROR(VLOOKUP(G76,IMPORTRANGE(""https://docs.google.com/spreadsheets/d/12RxCea4e5ggM7QGn1XE3FbLQa_-QbCNdBi90OdPjRqg"", ""'Plan de Compras'!D4:Q""), 13, 0), """")"),"NACIONAL") -> NACIONAL | Y76: =IFERROR(__xludf.DUMMYFUNCTION("IFERROR(VLOOKUP(G76,IMPORTRANGE(""https://docs.google.com/spreadsheets/d/12RxCea4e5ggM7QGn1XE3FbLQa_-QbCNdBi90OdPjRqg"", ""'Plan de Compras'!D4:Q""), 14, 0), """")"),"OMAR") -> OMAR | Z76: =IFERROR(__xludf.DUMMYFUNCTION("IFERROR(VLOOKUP(G76,IMPORTRANGE(""https://docs.google.com/spreadsheets/d/12RxCea4e5ggM7QGn1XE3FbLQa_-QbCNdBi90OdPjRqg"", ""'Plan de Compras'!D4:Q""), 4, 0), """")"),"COMPRESORA DE AIRE (50L - 3HP)") -> COMPRESORA DE AIRE (50L - 3HP) | AA76: =IF(H76=Z76,"TRUE", "FALSE") -> TRUE | AB76: =IFERROR(__xludf.DUMMYFUNCTION("IFERROR(IF(OR(C76=TRUE,C76=""""),VLOOKUP(G76,IMPORTRANGE(""https://docs.google.com/spreadsheets/d/1z9A1Wq-kKrhRNG5RS2a2fKpY1wIhSVz2ZNmP2mOl588/edit?usp=sharing"",""REQ VF!E4:H""),4,0),""NO APLICA""),""GENERAR REQ"")"),"GENERAR REQ") -> GENERAR REQ | AC76: =IFERROR(__xludf.DUMMYFUNCTION("IFERROR(QUERY(IMPORTRANGE(""https://docs.google.com/spreadsheets/d/1z9A1Wq-kKrhRNG5RS2a2fKpY1wIhSVz2ZNmP2mOl588/edit?usp=sharing"",""REQ VF!E4:Q""),""SELECT Col10, Col11, Col12 WHERE Col1 = '""&G76&""'"",0),""NO APLICA"")"),"NO APLICA") -> NO APLICA | AF76: C
